Workbook

Sheet Cover
A1: FluxMuse Financial Model
A2: AI marketing team & WhatsApp commerce for African SMBs | Fluxmuse Pty Ltd
A4: Version | B4: v3 (current offer: 9 tiers, no trials, R25M seed test)
A5: Model date | B5: 2026-10-05
A6: Horizon | B6: 60 months: Oct 2026 - Sep 2031 (FY1-FY5, fiscal year Oct-Sep). Month 1 = Oct 2026
A7: Currency | B7: ZAR (R); US$ at R18.50 = US$1 (input on Assumptions)
A8: Active scenario | B8: =Assumptions!$B$6
A9: Disclaimer | B9: Forward-looking projections. FluxMuse has no paying customers yet; every volume and rate is an assumption to replace with live data. Red-flagged inputs need founder confirmation.
A11: Headline (live formulas, selected scenario) | C11: FY1 | D11: FY2 | E11: FY3 | F11: FY4 | G11: FY5
A12: Total revenue (net of launch discounts) | C12: =Annual_Summary!$C$16 | D12: =Annual_Summary!$D$16 | E12: =Annual_Summary!$E$16 | F12: =Annual_Summary!$F$16 | G12: =Annual_Summary!$G$16
A13: EBITDA | C13: =Annual_Summary!$C$51 | D13: =Annual_Summary!$D$51 | E13: =Annual_Summary!$E$51 | F13: =Annual_Summary!$F$51 | G13: =Annual_Summary!$G$51
A14: EBITDA margin | C14: =Annual_Summary!$C$52 | D14: =Annual_Summary!$D$52 | E14: =Annual_Summary!$E$52 | F14: =Annual_Summary!$F$52 | G14: =Annual_Summary!$G$52
A15: Paying workspaces (end of FY) | C15: =Annual_Summary!$C$87 | D15: =Annual_Summary!$D$87 | E15: =Annual_Summary!$E$87 | F15: =Annual_Summary!$F$87 | G15: =Annual_Summary!$G$87
A16: Subscription ARR | C16: =Annual_Summary!$C$106 | D16: =Annual_Summary!$D$106 | E16: =Annual_Summary!$E$106 | F16: =Annual_Summary!$F$106 | G16: =Annual_Summary!$G$106
A17: Closing cash | C17: =Annual_Summary!$C$60 | D17: =Annual_Summary!$D$60 | E17: =Annual_Summary!$E$60 | F17: =Annual_Summary!$F$60 | G17: =Annual_Summary!$G$60
A18: Headcount (end of FY) | C18: =Annual_Summary!$C$112 | D18: =Annual_Summary!$D$112 | E18: =Annual_Summary!$E$112 | F18: =Annual_Summary!$F$112 | G18: =Annual_Summary!$G$112
A19: Founding Member discount cost | C19: =Annual_Summary!$C$21 | D19: =Annual_Summary!$D$21 | E19: =Annual_Summary!$E$21 | F19: =Annual_Summary!$F$21 | G19: =Annual_Summary!$G$21
A20: Active Free users (end of FY) | C20: =Annual_Summary!$C$101 | D20: =Annual_Summary!$D$101 | E20: =Annual_Summary!$E$101 | F20: =Annual_Summary!$F$101 | G20: =Annual_Summary!$G$101
A22: Constraint check & key outputs (live formulas, selected scenario)
A23: Profitable on the R25M seed alone? | C23: =Cash_Flow!$B$68
A24: EBITDA break-even (first month) | C24: =Cash_Flow!$B$46
A25: EBITDA break-even (sustained) | C25: =Cash_Flow!$B$48
A26: Operating cash flow positive (first month) | C26: =Cash_Flow!$B$50
A27: Operating cash flow positive (sustained) | C27: =Cash_Flow!$B$52
A28: Minimum closing cash from the seed month on | C28: =Cash_Flow!$B$56
A29: Month of minimum post-seed cash | C29: =Cash_Flow!$B$58
A30: Minimum-cash buffer | C30: =Cash_Flow!$B$63
A31: Shortfall vs buffer | C31: =Cash_Flow!$B$65
A32: Pre-seed bridge required | C32: =Cash_Flow!$B$62
A33: Nigeria launch | C33: =Cash_Flow!$B$77
A34: Kenya launch | C34: =Cash_Flow!$B$79
A35: Ghana launch | C35: =Cash_Flow!$B$81
A36: Rest of Africa (USD) launch | C36: =Cash_Flow!$B$83
A38: Changes from v2 (11 Sep 2026 model) and why
A39: Tiers | B39: 5 tiers -> the live 9: Free R0, Nano R149, Micro R289, Starter R499, Growth R1,999, Scale R4,999, Corporate R6,999, Agency R9,999, Custom (from R19,999). Local NGN/KES/GHS/USD prices from tier_regional_prices. Annual = 10x monthly.
A40: No trials, no pilot | B40: 14-day trial and the 12-brand pilot removed. Paid plans start with payment. A small first group is set up by hand from Oct 2026 (4 a month to Jan 2027) [[CONFIRM]]. South Africa sells from Oct 2026.
A41: Free plan | B41: Sign-ups either pay at once (Solo 5%, SME 8%) or join Free. Active Free users upgrade at 0.5% a month or go dormant at 10% a month. Free AI cost at the live 60 credits a month [[CONFIRM]].
A42: Segments | B42: Solo: Nano 45% / Micro 40% / Starter 15%. SMEs: Starter 40% / Growth 50% / Scale 10%. Corporate is a new inbound line. Agencies on partner wholesale R6,999. Upgrade chains Nano -> Micro -> Starter and Starter -> Growth -> Scale [[CONFIRM]].
A43: Founding Member | B43: 30% off the first 2 monthly bills, South Africa only, Oct 2026 to Mar 2027 (proposed end) [[CONFIRM]]. Old 1 Dec 2026 - 31 Jan 2027 window, NG/KE/GH windows, annual bonus months and pilot 50% pricing removed.
A44: Markets | B44: South Africa only until NG/KE/GH checkout is live. Plan months moved later: Nigeria Apr 2028, Kenya Jul 2028, Ghana Oct 2028, Rest of Africa (USD) May 2029 [[CONFIRM]]. BW/NA still off.
A45: AI cost | B45: 1 credit = R0.15 of provider cost (ai-credit-math.ts, platform_billing_config). Allowances at live levels; Corporate, Agency and Custom run on their own keys (no AI cost). Packs R300 for 1,000 credits, no overage.
A46: Commerce & VAT | B46: No FluxMuse fee on checkout: Paystack fees pass through to the merchant (0% in every scenario). Not VAT-registered: no VAT in revenue. Agency setup fee removed (not in the live price list).
A47: Unchanged | B47: R25M seed in Feb 2027, 40/30/15/15 use of funds, R3.0M buffer, MRR-gated hiring and launches, paid cap, scenario switch, FX drift and repricing.
A49: Sheet guide
A50: Assumptions | B50: All drivers with units and sources; scenario selector (B6); lean mode, first group, Founding Member, markets, Free funnel, segments; MRR-gated headcount plan.
A51: Pricing | B51: Nine tiers: ZAR list, NGN/KES/GHS/USD price points, partner wholesale, Founding Member prices, FX depreciation & repricing, ZAR-parity table.
A52: Revenue_Build | B52: Monthly launch gates, FX value factors, sign-ups, Free plan funnel, marketing cap & payback test, cohorts by market/segment/tier, discounts, revenue.
A53: Costs | B53: MRR-gated headcount by role, payroll, COGS (AI, hosting, WhatsApp, processing, support, CS), opex.
A54: P&L | B54: Monthly P&L: gross subscriptions -> discounts -> net, other revenue, gross margin, opex, EBITDA, tax, net income.
A55: Annual_Summary | B55: FY1-FY5 roll-up: revenue, discounts, margins, EBITDA, cash, customers by segment/market/tier, ARR, ARPA, headcount.
A56: Cash_Flow | B56: Working capital, funding (seed only), cash vs R3.0M buffer, runway, break-even, bridge, launch months and the constraint check.
A57: Unit_Economics | B57: ARPA, churn, LTV, CAC, LTV:CAC and payback by segment (tier memo); magic number, burn multiple, Rule of 40.
A58: Use_of_Funds | B58: R25M allocation and reconciliation against modelled spend in the 18 and 24 months after close.
A59: Sensitivity | B59: Scenario comparison, FX shock, Founding Member vs none, Free-to-paid conversion, Conservative shortfall & fix, churn x volume grids (build-time values).
A60: Market_Sizing | B60: TAM / SAM / SOM (estimates) linked to modelled FY5 workspaces.
A62: Colour legend
A63: 1,234 | B63: Input: blue font on light yellow. Change these.
A64: =1+1 | B64: Formula: black font. Do not overwrite.
A65: 5,678 | B65: Value computed at build time by the Python mirror (Sensitivity sheet only).
A66: [[CONFIRM]] | B66: Red source note: founder confirmation or decision needed.
A68: Not in any scenario | B68: Campaign Financing (upside only). Partner referral commission (undecided). Series A (optional acceleration only; switched off). Any FluxMuse checkout fee (none in the current offer). VAT (not registered).

Sheet Assumptions
A1: Assumptions
A2: Every driver of the model. Blue on yellow = input. Black = formula. Red source text = [[CONFIRM]] / founder decision pending.
A4: Driver | B4: Live value | C4: Unit | D4: Conservative | E4: Base | F4: Upside | G4: Source / rationale
A6: Active scenario (select) | B6: Base | C6: list | G6: Choose Conservative / Base / Upside. Every scenario driver below uses CHOOSE on this index.
A7: Scenario index (1 = Conservative, 2 = Base, 3 = Upside) | B7: =MATCH($B$6,$D$4:$F$4,0)
A9: General, funding & tax
A10: FX rate | B10: 18.5 | C10: ZAR per US$ | G10: Facts file §2: R18.50 = US$1 (planning rate; live cost rate was R16.43 on 25 Sep 2026)
A11: SA corporate income tax rate | B11: 0.27 | C11: % | G11: SARS 27%. Applied only once cumulative EBITDA is positive (assessed-loss simplification).
A12: Opening cash (1 Oct 2026) | B12: 500000 | C12: R | G12: [[CONFIRM]] founder to confirm cash in bank at 1 Oct 2026; default R500k
A13: Seed raise | B13: 25000000 | C13: R | G13: Facts file §7: Seed R25M (≈US$1.35M). Must reach profitability alone (founder, 2026-09-11)
A14: Seed lands in model month # | B14: 5 | C14: month # | G14: [[CONFIRM]] Month 5 = Feb 2027 (unchanged from v2; no pilot results now gate the close)
A15: Minimum-cash buffer (closing cash must stay above this from the seed month on) | B15: 3000000 | C15: R | G15: Founder constraint: never below R3.0M after the seed lands
A16: Include Series A? (1 = yes, 0 = no) | B16: 0 | C16: switch | G16: OFF in every scenario. Optional acceleration only, not needed for survival
A17: Series A amount (optional acceleration, if switched on) | B17: 0 | C17: R | G17: Default 0 (founder: no Series A in Base or Conservative)
A18: Series A lands in model month # | B18: 30 | C18: month # | G18: Month 30 = Mar 2029 (illustrative)
A19: VAT: Fluxmuse (Pty) Ltd is not VAT-registered. List prices are the amounts charged; revenue is booked as charged with no VAT gross-up or deduction.
A20: Launch, first group set up by hand & lean pre-seed mode (no trials, no pilot)
A21: First group: paying businesses set up by hand each month | B21: 4 | C21: workspaces / month | G21: [[CONFIRM]] Founders onboard a small first group by hand (CURRENT_OFFER §4); no pilot cohort exists
A22: First group: last month # of hand set-up | B22: 4 | C22: month # | G22: [[CONFIRM]] Month 4 = Jan 2027 (Oct 2026 - Jan 2027, until the seed lands)
A23: First group: share that are Solo entrepreneurs (rest SMEs) | B23: 0.5 | C23: % | G23: [[CONFIRM]] Each takes its segment's tier mix; agencies come through the partner channel
A24: First group: hand set-up cost while it runs | B24: 10000 | C24: R / month | G24: [[CONFIRM]] Onboarding visits, set-up time, WhatsApp/AI usage (replaces the R15k pilot cost)
A25: Hosting base before the seed (lean mode) | B25: 15000 | C25: R / month | G25: Supabase/Vercel at early scale (ASSUMPTION)
A26: Overheads before the seed (accounting, banking, Meta/legal minimum) | B26: 15000 | C26: R / month | G26: Lean mode replaces fixed G&A and the legal retainer until the seed lands
A27: Lean mode (months before the seed): founders only, no paid marketing, no office/travel; hiring, brand, partner and legal budgets start in the seed month.
A28: Sensitivity & option levers (leave at defaults for the scenarios)
A29: New sign-up volume multiplier | B29: 1 | C29: x | G29: Scales self-serve sign-ups in every market; Sensitivity sheet
A30: Churn sensitivity multiplier | B30: 1 | C30: x | G30: Multiplies all churn; Sensitivity sheet
A31: Launch discount option (1 = Founding Member, 2 = None) | B31: 1 | C31: option | G31: Founding Member live since 1 Oct 2026 (CURRENT_OFFER §1); None is a sensitivity only
A32: Founding Member: discount on the first 2 monthly bills | B32: 0.3 | C32: % off | G32: CURRENT_OFFER §1: 30% off the first two monthly billing cycles, South African sign-ups. Not modelled on Agency, Corporate or Custom
A33: Founding Member: first month # (South Africa) | B33: 1 | C33: month # | G33: Live from Oct 2026 (confirmed 1 Oct 2026)
A34: Founding Member: last month # (South Africa) | B34: 6 | C34: month # | G34: [[CONFIRM]] No end date is set. Proposed: 31 Mar 2027 (6 months, ends a month after the seed lands)
A35: New sign-up uplift while Founding Member runs | B35: 0.2 | C35: % | G35: [[CONFIRM]] +20% paying sign-ups while the offer runs (unchanged from v2; unproven)
A36: Churn of new sign-ups between discounted bill 1 and 2 | B36: 0.08 | C36: % | G36: Used only to size the second discounted bill (ASSUMPTION)
A37: FX shock: ZAR stronger vs NGN/KES/GHS/USD | B37: 0 | C37: % | G37: Sensitivity sets 15%
A38: FX shock starts in month # | B38: 31 | C38: month # | G38: [[CONFIRM]] Month 31 = Apr 2029, after the later NG/KE/GH plan months
A39: Scenario drivers (switched by the selector above: CHOOSE on columns D:F)
A40: Monthly growth in self-serve sign-ups (Free + paid): FY1 | B40: =CHOOSE($B$7,D40,E40,F40) | C40: % m/m | D40: 0.1 | E40: 0.12 | F40: 0.14 | G40: Per market from its launch month; decays as channels mature (unchanged from v2)
A41: Monthly growth in self-serve sign-ups (Free + paid): FY2 | B41: =CHOOSE($B$7,D41,E41,F41) | C41: % m/m | D41: 0.035 | E41: 0.045 | F41: 0.06
A42: Monthly growth in self-serve sign-ups (Free + paid): FY3 | B42: =CHOOSE($B$7,D42,E42,F42) | C42: % m/m | D42: 0.025 | E42: 0.035 | F42: 0.045
A43: Monthly growth in self-serve sign-ups (Free + paid): FY4 | B43: =CHOOSE($B$7,D43,E43,F43) | C43: % m/m | D43: 0.015 | E43: 0.028 | F43: 0.032
A44: Monthly growth in self-serve sign-ups (Free + paid): FY5 | B44: =CHOOSE($B$7,D44,E44,F44) | C44: % m/m | D44: 0.01 | E44: 0.015 | F44: 0.02
A45: Conversion multiplier (on direct-paid and Free-to-paid conversion) | B45: =CHOOSE($B$7,D45,E45,F45) | C45: x | D45: 0.85 | E45: 1 | F45: 1.2
A46: Churn multiplier | B46: =CHOOSE($B$7,D46,E46,F46) | C46: x | D46: 1.2 | E46: 1 | F46: 0.85
A47: Paid CAC multiplier | B47: =CHOOSE($B$7,D47,E47,F47) | C47: x | D47: 1.2 | E47: 1 | F47: 0.85 | G47: Ad-auction inflation vs creative & referral efficiency
A48: Expansion timing shift (months, + = later) | B48: =CHOOSE($B$7,D48,E48,F48) | C48: months | D48: 3 | E48: 0 | F48: -2 | G48: Shifts planned NG/KE/GH/Rest/BW-NA launches (MRR gates still apply)
A49: Inbound Corporate & Custom deal multiplier | B49: =CHOOSE($B$7,D49,E49,F49) | C49: x | D49: 0.5 | E49: 1 | F49: 1.5
A50: COST DISCIPLINE: paid acquisition cap, % of last month's net MRR | B50: =CHOOSE($B$7,D50,E50,F50) | C50: % of MRR | D50: 0.3 | E50: 0.35 | F50: 0.5 | G50: Paid spend = MIN(desired, floor + cap x MRR); unfunded paid sign-ups are not acquired
A51: COST DISCIPLINE: hiring & launch MRR-gate multiplier | B51: =CHOOSE($B$7,D51,E51,F51) | C51: x | D51: 1.4 | E51: 1 | F51: 0.8 | G51: Each hire/launch waits for its MRR milestone x this (unchanged from v2)
A52: FluxMuse fee on checkout GMV (on top of pass-through Paystack fees) | B52: =CHOOSE($B$7,D52,E52,F52) | C52: % of GMV | D52: 0 | E52: 0 | F52: 0 | G52: [[CONFIRM]] CURRENT_OFFER §2: checkout fees are pass-through (Paystack 2.9% + R1 card, 2% EFT); no FluxMuse service fee. 0% in every scenario
A53: Launch discount parameters (formulas on the option switch)
A54: Founding Member: discount applied to monthly plans | B54: =IF(Assumptions!$B$31=1,Assumptions!$B$32,0) | C54: % off | G54: Solo & SME sign-ups in South Africa inside the offer months. Annual plans: no Founding Member discount modelled [[CONFIRM]]
A55: Sign-up uplift applied while the offer runs | B55: =IF(Assumptions!$B$31=1,Assumptions!$B$35,0) | C55: %
A56: Markets & sequence (ZA only until NG/KE/GH checkout is live; Rest of Africa self-serve later; BW/NA coming soon; gated countries = 0)
A57: South Africa commercial launch month # | B57: 1 | C57: month # | G57: Oct 2026: paid plans and Founding Member live (CURRENT_OFFER §1)
A58: Self-serve sign-ups (Free + paid) in launch month: South Africa | B58: 150 | C58: sign-ups / month | G58: [[CONFIRM]] Organic only until the seed (no paid marketing); founder-led outreach
A59: Nigeria: switch (1 = on) | B59: 1 | C59: switch
A60: Nigeria: planned launch month # (earliest) | B60: 19 | C60: month # | G60: [[CONFIRM]] Apr 2028 (was Nov 2027): needs Fincra/pawaPay checkout live; largest MSME base
A61: Nigeria: MRR gate for the launch decision | B61: 900000 | C61: R net MRR | G61: Decision (and country-lead hire) needs last month's net MRR >= gate x gate multiplier; launch follows 2 months later
A62: Nigeria: self-serve sign-ups (Free + paid) in launch month | B62: 220 | C62: sign-ups / month
A63: Nigeria: paid CAC index vs SA | B63: 0.75 | C63: x | G63: Cheaper media; lower price point
A64: Nigeria: churn index vs SA | B64: 1.15 | C64: x | G64: FX affordability pressure (ASSUMPTION)
A65: Nigeria: local compliance & registration (one-off at launch) | B65: 300000 | C65: R | G65: NDPR registration, entity, local counsel
A66: Nigeria: ongoing local compliance | B66: 12000 | C66: R / month | G66: Local accounting, DPO filings, tax returns
A67: Nigeria: launch marketing budget (spread over first 3 months) | B67: 350000 | C67: R | G67: Launch campaign, local creators, events
A68: Nigeria: inbound agency sign-ups after launch | B68: 0.25 | C68: agencies / month
A69: Kenya: switch (1 = on) | B69: 1 | C69: switch
A70: Kenya: planned launch month # (earliest) | B70: 22 | C70: month # | G70: [[CONFIRM]] Jul 2028 (was Feb 2028): M-Pesa via pawaPay once the account is live
A71: Kenya: MRR gate for the launch decision | B71: 1200000 | C71: R net MRR | G71: Decision (and country-lead hire) needs last month's net MRR >= gate x gate multiplier; launch follows 2 months later
A72: Kenya: self-serve sign-ups (Free + paid) in launch month | B72: 150 | C72: sign-ups / month
A73: Kenya: paid CAC index vs SA | B73: 0.8 | C73: x | G73: Cheaper media; lower price point
A74: Kenya: churn index vs SA | B74: 1.05 | C74: x | G74: FX affordability pressure (ASSUMPTION)
A75: Kenya: local compliance & registration (one-off at launch) | B75: 250000 | C75: R | G75: KDPA (ODPC) registration, local counsel
A76: Kenya: ongoing local compliance | B76: 12000 | C76: R / month | G76: Local accounting, DPO filings, tax returns
A77: Kenya: launch marketing budget (spread over first 3 months) | B77: 300000 | C77: R | G77: Launch campaign, local creators, events
A78: Kenya: inbound agency sign-ups after launch | B78: 0.2 | C78: agencies / month
A79: Ghana: switch (1 = on) | B79: 1 | C79: switch
A80: Ghana: planned launch month # (earliest) | B80: 25 | C80: month # | G80: [[CONFIRM]] Oct 2028 (was May 2028): MoMo via pawaPay once the account is live
A81: Ghana: MRR gate for the launch decision | B81: 1500000 | C81: R net MRR | G81: Decision (and country-lead hire) needs last month's net MRR >= gate x gate multiplier; launch follows 2 months later
A82: Ghana: self-serve sign-ups (Free + paid) in launch month | B82: 110 | C82: sign-ups / month
A83: Ghana: paid CAC index vs SA | B83: 0.8 | C83: x | G83: Cheaper media; lower price point
A84: Ghana: churn index vs SA | B84: 1.1 | C84: x | G84: FX affordability pressure (ASSUMPTION)
A85: Ghana: local compliance & registration (one-off at launch) | B85: 200000 | C85: R | G85: Ghana DPC registration, local counsel
A86: Ghana: ongoing local compliance | B86: 10000 | C86: R / month | G86: Local accounting, DPO filings, tax returns
A87: Ghana: launch marketing budget (spread over first 3 months) | B87: 250000 | C87: R | G87: Launch campaign, local creators, events
A88: Ghana: inbound agency sign-ups after launch | B88: 0.15 | C88: agencies / month
A89: Rest of Africa (USD): switch (1 = on) | B89: 1 | C89: switch
A90: Rest of Africa (USD): planned launch month # (earliest) | B90: 32 | C90: month # | G90: [[CONFIRM]] May 2029 (was Nov 2028): 19 countries, USD, self-serve only, no local team
A91: Rest of Africa (USD): MRR gate for the launch decision | B91: 2500000 | C91: R net MRR | G91: Decision (and country-lead hire) needs last month's net MRR >= gate x gate multiplier; launch follows 2 months later
A92: Rest of Africa (USD): self-serve sign-ups (Free + paid) in launch month | B92: 120 | C92: sign-ups / month
A93: Rest of Africa (USD): paid CAC index vs SA | B93: 0.6 | C93: x | G93: Cheaper media; lower price point
A94: Rest of Africa (USD): churn index vs SA | B94: 1.25 | C94: x | G94: FX affordability pressure (ASSUMPTION)
A95: Rest of Africa (USD): local compliance & registration (one-off at launch) | B95: 150000 | C95: R | G95: Digital-services tax registrations where required (hub approach)
A96: Rest of Africa (USD): ongoing local compliance | B96: 20000 | C96: R / month | G96: Local accounting, DPO filings, tax returns
A97: Botswana & Namibia: switch (1 = on) | B97: 0 | C97: switch | G97: Default OFF: no secured rail yet
A98: Botswana & Namibia: planned launch month # (earliest) | B98: 34 | C98: month # | G98: Coming soon: switch on once a rail covers BW/NA
A99: Botswana & Namibia: MRR gate for the launch decision | B99: 3000000 | C99: R net MRR | G99: Decision (and country-lead hire) needs last month's net MRR >= gate x gate multiplier; launch follows 2 months later
A100: Botswana & Namibia: self-serve sign-ups (Free + paid) in launch month | B100: 40 | C100: sign-ups / month
A101: Botswana & Namibia: paid CAC index vs SA | B101: 0.9 | C101: x | G101: Cheaper media; lower price point
A102: Botswana & Namibia: churn index vs SA | B102: 1 | C102: x | G102: FX affordability pressure (ASSUMPTION)
A103: Botswana & Namibia: local compliance & registration (one-off at launch) | B103: 100000 | C103: R | G103: BW/NA data-protection & tax registration
...

Sheet Pricing
A1: Pricing
A2: Live prices (subscription_tiers & tier_regional_prices, CURRENT_OFFER §1). ZAR list for South Africa; fixed local price points for NG/KE/GH and USD for the rest of rail-covered Africa, at FX parity. Annual = 10x monthly. No VAT (not VAT-registered). Free (R0) is modelled on Assumptions as a funnel stage.
A4: Tier | B4: ZAR list / month | C4: ZAR annual | D4: ≈ US$ / month (R18.50) | E4: Modelled AI allowance (credits; internal cost input, never quoted) | F4: Founding Member price, first 2 monthly bills (R, South Africa) | G4: Band | H4: NGN / month | I4: KES / month | J4: GHS / month | K4: USD / month (19 USD markets) | L4: Note
A5: Nano | B5: 149 | C5: =B5*Pricing!$B$18 | D5: =B5/Assumptions!$B$10 | E5: 450 | F5: =ROUNDDOWN(B5*(1-Assumptions!$B$32),0) | G5: Small | H5: 12000 | I5: 1199 | J5: 99 | K5: 8 | L5: Small band. 1 brand, 3 channels; side-hustles
A6: Micro | B6: 289 | C6: =B6*Pricing!$B$18 | D6: =B6/Assumptions!$B$10 | E6: 900 | F6: =ROUNDDOWN(B6*(1-Assumptions!$B$32),0) | G6: Small | H6: 24000 | I6: 2299 | J6: 199 | K6: 16 | L6: Small band. 1 brand, 4 channels, 1 WhatsApp number, WhatsApp commerce
A7: Starter | B7: 499 | C7: =B7*Pricing!$B$18 | D7: =B7/Assumptions!$B$10 | E7: 1500 | F7: =ROUNDDOWN(B7*(1-Assumptions!$B$32),0) | G7: Medium | H7: 41000 | I7: 3999 | J7: 339 | K7: 27 | L7: Medium band. 1 brand, 3 channels
A8: Growth | B8: 1999 | C8: =B8*Pricing!$B$18 | D8: =B8/Assumptions!$B$10 | E8: 6500 | F8: =ROUNDDOWN(B8*(1-Assumptions!$B$32),0) | G8: Medium | H8: 165000 | I8: 15999 | J8: 1359 | K8: 109 | L8: Medium band. 3 brands, 15 channels, inbound AI Voice (beta). Credits incl. 500 bonus where voice is not offered
A9: Scale | B9: 4999 | C9: =B9*Pricing!$B$18 | D9: =B9/Assumptions!$B$10 | E9: 15500 | F9: =ROUNDDOWN(B9*(1-Assumptions!$B$32),0) | G9: Medium | H9: 413000 | I9: 39999 | J9: 3399 | K9: 269 | L9: Medium band. 10 brands, 40 channels, in+out AI Voice (beta). Credits incl. 2,000 bonus (cost-equivalent of outbound voice minutes)
A10: Corporate | B10: 6999 | C10: =B10*Pricing!$B$18 | D10: =B10/Assumptions!$B$10 | E10: 0 | F10: Not modelled | G10: Enterprise | H10: 579000 | I10: 56999 | J10: 4799 | K10: 379 | L10: Enterprise band. 25 brands, 60 channels, BYOC: AI on the customer's own keys, so no AI credit cost to FluxMuse
A11: Agency | B11: 9999 | C11: =B11*Pricing!$B$18 | D11: =B11/Assumptions!$B$10 | E11: 0 | F11: Not modelled | G11: Enterprise | H11: 829000 | I11: 80999 | J11: 6799 | K11: 539 | L11: Enterprise band. Unlimited brands, 80 channels, BYOC, white-label, multi-client; own keys
A12: Custom | B12: 19999 | C12: =B12*Pricing!$B$18 | D12: =B12/Assumptions!$B$10 | E12: 0 | F12: Not modelled | G12: Enterprise | H12: 1650000 | I12: 161000 | J12: 13600 | K12: 1099 | L12: Custom, by consultation. Modelled at 'from R19,999' [[CONFIRM]]; own keys
A13: Partner wholesale: Agency tier -30% | B13: 6999 | C13: =B13*Pricing!$B$18 | D13: =B13/Assumptions!$B$10 | E13: =E11 | F13: Does not stack | G13: Enterprise | H13: 579000 | I13: 56999 | J13: 4799 | K13: 379 | L13: CURRENT_OFFER §1 (confirmed 1 Oct 2026): partners buy Agency at 30% off R9,999 = R6,999. Local wholesale = Corporate local price points [[CONFIRM]]. Referral commission: undecided, not modelled.
A15: Pricing drivers
A16: Annual price escalator (applied each 1 Oct, all markets) | B16: 0.06 | C16: % / year | D16: CPI-linked list-price increase (ASSUMPTION)
A17: Share of subscriptions on annual billing | B17: 0.25 | C17: % | D17: Annual = 10x monthly (unchanged from v2)
A18: Months charged on an annual plan | B18: 10 | C18: months | D18: CURRENT_OFFER §1: annual = 10x monthly
A19: Effective price factor from annual-billing mix | B19: =1-Pricing!$B$17*(12-Pricing!$B$18)/12 | C19: x | D19: Formula: 1 - annual share x (12 - months charged) / 12
A20: Share of agency-segment customers on partner wholesale pricing | B20: 1 | C20: % | D20: CURRENT_OFFER §1 (1 Oct 2026): partners buy Agency at 30% off list (R6,999); default 100% of agency customers
A22: FX: price-setting rates, depreciation vs ZAR and the quarterly repricing policy (depreciation rates are ASSUMPTIONS)
A23: NGN per R1 at price-setting (Sept 2026) | B23: 82.83 | C23: NGN per ZAR | D23: Facts file §2 mid-market rate
A24: KES per R1 at price-setting | B24: 8.07 | C24: KES per ZAR | D24: Facts file §2
A25: GHS per R1 at price-setting | B25: 0.68 | C25: GHS per ZAR | D25: Facts file §2
A26: Annual depreciation of NGN vs ZAR | B26: -0.1 | C26: % / year | D26: ASSUMPTION
A27: Annual depreciation of KES vs ZAR | B27: -0.03 | C27: % / year | D27: ASSUMPTION
A28: Annual depreciation of GHS vs ZAR | B28: -0.08 | C28: % / year | D28: ASSUMPTION
A29: Annual depreciation of USD vs ZAR | B29: 0 | C29: % / year | D29: ASSUMPTION (USD markets)
A30: Repricing trigger: drift in ZAR value of local prices | B30: 0.1 | C30: % | D30: Facts file §2: reprice if FX moves more than ±10%
A31: Quarterly repricing policy on? (1 = yes) | B31: 1 | C31: switch | D31: Reviewed each quarter; new price applies one quarter after the drift is observed
A33: ZAR value of each market's monthly price at price-setting FX (formulas; used by Revenue_Build, then x FX value factor after drift & repricing)
A34: Tier (R / month) | B34: South Africa | C34: Nigeria | D34: Kenya | E34: Ghana | F34: Rest of Africa (USD) | G34: Botswana & Namibia
A35: Nano | B35: =$B$5 | C35: =$H$5/$B$23 | D35: =$I$5/$B$24 | E35: =$J$5/$B$25 | F35: =$K$5*Assumptions!$B$10 | G35: =$B$5
A36: Micro | B36: =$B$6 | C36: =$H$6/$B$23 | D36: =$I$6/$B$24 | E36: =$J$6/$B$25 | F36: =$K$6*Assumptions!$B$10 | G36: =$B$6
A37: Starter | B37: =$B$7 | C37: =$H$7/$B$23 | D37: =$I$7/$B$24 | E37: =$J$7/$B$25 | F37: =$K$7*Assumptions!$B$10 | G37: =$B$7
A38: Growth | B38: =$B$8 | C38: =$H$8/$B$23 | D38: =$I$8/$B$24 | E38: =$J$8/$B$25 | F38: =$K$8*Assumptions!$B$10 | G38: =$B$8
A39: Scale | B39: =$B$9 | C39: =$H$9/$B$23 | D39: =$I$9/$B$24 | E39: =$J$9/$B$25 | F39: =$K$9*Assumptions!$B$10 | G39: =$B$9
A40: Corporate | B40: =$B$10 | C40: =$H$10/$B$23 | D40: =$I$10/$B$24 | E40: =$J$10/$B$25 | F40: =$K$10*Assumptions!$B$10 | G40: =$B$10
A41: Agency | B41: =$B$11 | C41: =$H$11/$B$23 | D41: =$I$11/$B$24 | E41: =$J$11/$B$25 | F41: =$K$11*Assumptions!$B$10 | G41: =$B$11
A42: Custom | B42: =$B$12 | C42: =$H$12/$B$23 | D42: =$I$12/$B$24 | E42: =$J$12/$B$25 | F42: =$K$12*Assumptions!$B$10 | G42: =$B$12
A43: Partner wholesale (Agency -30%) | B43: =$B$13 | C43: =$H$13/$B$23 | D43: =$I$13/$B$24 | E43: =$J$13/$B$25 | F43: =$K$13*Assumptions!$B$10 | G43: =$B$13

Sheet Revenue_Build
A1: Revenue Build
A2: Monthly, Oct 2026 - Sep 2031. Launch gates, FX & repricing, sign-ups, Free plan funnel, acquisition by market & segment with the marketing cap, cohorts, gross -> discounts -> net revenue.
A3: Month # | B3: Unit | C3: 1 | D3: 2 | E3: 3 | F3: 4 | G3: 5 | H3: 6 | I3: 7 | J3: 8 | K3: 9 | L3: 10 | M3: 11 | N3: 12 | O3: 13 | P3: 14 | Q3: 15 | R3: 16 | S3: 17 | T3: 18 | U3: 19 | V3: 20 | W3: 21 | X3: 22 | Y3: 23 | Z3: 24 | AA3: 25 | AB3: 26 | AC3: 27 | AD3: 28 | AE3: 29 | AF3: 30 | AG3: 31 | AH3: 32 | AI3: 33 | AJ3: 34 | AK3: 35 | AL3: 36 | AM3: 37 | AN3: 38 | AO3: 39 | AP3: 40 | AQ3: 41 | AR3: 42 | AS3: 43 | AT3: 44 | AU3: 45 | AV3: 46 | AW3: 47 | AX3: 48 | AY3: 49 | AZ3: 50 | BA3: 51 | BB3: 52 | BC3: 53 | BD3: 54 | BE3: 55 | BF3: 56 | BG3: 57 | BH3: 58 | BI3: 59 | BJ3: 60
A4: Month | C4: Oct 2026 | D4: Nov 2026 | E4: Dec 2026 | F4: Jan 2027 | G4: Feb 2027 | H4: Mar 2027 | I4: Apr 2027 | J4: May 2027 | K4: Jun 2027 | L4: Jul 2027 | M4: Aug 2027 | N4: Sep 2027 | O4: Oct 2027 | P4: Nov 2027 | Q4: Dec 2027 | R4: Jan 2028 | S4: Feb 2028 | T4: Mar 2028 | U4: Apr 2028 | V4: May 2028 | W4: Jun 2028 | X4: Jul 2028 | Y4: Aug 2028 | Z4: Sep 2028 | AA4: Oct 2028 | AB4: Nov 2028 | AC4: Dec 2028 | AD4: Jan 2029 | AE4: Feb 2029 | AF4: Mar 2029 | AG4: Apr 2029 | AH4: May 2029 | AI4: Jun 2029 | AJ4: Jul 2029 | AK4: Aug 2029 | AL4: Sep 2029 | AM4: Oct 2029 | AN4: Nov 2029 | AO4: Dec 2029 | AP4: Jan 2030 | AQ4: Feb 2030 | AR4: Mar 2030 | AS4: Apr 2030 | AT4: May 2030 | AU4: Jun 2030 | AV4: Jul 2030 | AW4: Aug 2030 | AX4: Sep 2030 | AY4: Oct 2030 | AZ4: Nov 2030 | BA4: Dec 2030 | BB4: Jan 2031 | BC4: Feb 2031 | BD4: Mar 2031 | BE4: Apr 2031 | BF4: May 2031 | BG4: Jun 2031 | BH4: Jul 2031 | BI4: Aug 2031 | BJ4: Sep 2031
A5: Fiscal year (Oct-Sep) | C5: 1 | D5: 1 | E5: 1 | F5: 1 | G5: 1 | H5: 1 | I5: 1 | J5: 1 | K5: 1 | L5: 1 | M5: 1 | N5: 1 | O5: 2 | P5: 2 | Q5: 2 | R5: 2 | S5: 2 | T5: 2 | U5: 2 | V5: 2 | W5: 2 | X5: 2 | Y5: 2 | Z5: 2 | AA5: 3 | AB5: 3 | AC5: 3 | AD5: 3 | AE5: 3 | AF5: 3 | AG5: 3 | AH5: 3 | AI5: 3 | AJ5: 3 | AK5: 3 | AL5: 3 | AM5: 4 | AN5: 4 | AO5: 4 | AP5: 4 | AQ5: 4 | AR5: 4 | AS5: 4 | AT5: 4 | AU5: 4 | AV5: 4 | AW5: 4 | AX5: 4 | AY5: 5 | AZ5: 5 | BA5: 5 | BB5: 5 | BC5: 5 | BD5: 5 | BE5: 5 | BF5: 5 | BG5: 5 | BH5: 5 | BI5: 5 | BJ5: 5
A7: Timeline: lean pre-seed mode, first group set up by hand, previous-month MRR (drives every gate and cap)
A8: Seed has landed (1) / lean pre-seed mode (0) | B8: flag | C8: =IF(C$3>=Assumptions!$B$14,1,0) | D8: =IF(D$3>=Assumptions!$B$14,1,0) | E8: =IF(E$3>=Assumptions!$B$14,1,0) | F8: =IF(F$3>=Assumptions!$B$14,1,0) | G8: =IF(G$3>=Assumptions!$B$14,1,0) | H8: =IF(H$3>=Assumptions!$B$14,1,0) | I8: =IF(I$3>=Assumptions!$B$14,1,0) | J8: =IF(J$3>=Assumptions!$B$14,1,0) | ... BJ8: =IF(BJ$3>=Assumptions!$B$14,1,0)
A9: First group being set up by hand (paying from day one) | B9: flag | C9: =IF(C$3<=Assumptions!$B$22,1,0) | D9: =IF(D$3<=Assumptions!$B$22,1,0) | E9: =IF(E$3<=Assumptions!$B$22,1,0) | F9: =IF(F$3<=Assumptions!$B$22,1,0) | G9: =IF(G$3<=Assumptions!$B$22,1,0) | H9: =IF(H$3<=Assumptions!$B$22,1,0) | I9: =IF(I$3<=Assumptions!$B$22,1,0) | J9: =IF(J$3<=Assumptions!$B$22,1,0) | ... BJ9: =IF(BJ$3<=Assumptions!$B$22,1,0)
A10: Net subscription MRR, previous month | B10: R | C10: =0 | D10: =C486 | E10: =D486 | F10: =E486 | G10: =F486 | H10: =G486 | I10: =H486 | J10: =I486 | K10: =J486 | ... BJ10: =BI486
A12: Market launches: decision needs month >= plan + shift - 2, the seed, and MRR >= gate; launch 2 months after decision
A13: Live: South Africa | B13: flag | C13: =IF(C$3>=Assumptions!$B$57,1,0) | D13: =IF(D$3>=Assumptions!$B$57,1,0) | E13: =IF(E$3>=Assumptions!$B$57,1,0) | F13: =IF(F$3>=Assumptions!$B$57,1,0) | G13: =IF(G$3>=Assumptions!$B$57,1,0) | H13: =IF(H$3>=Assumptions!$B$57,1,0) | I13: =IF(I$3>=Assumptions!$B$57,1,0) | J13: =IF(J$3>=Assumptions!$B$57,1,0) | ... BJ13: =IF(BJ$3>=Assumptions!$B$57,1,0)
A14: Launch decided (country lead hired): Nigeria | B14: flag | C14: =IF(AND(Assumptions!$B$59=1,C$3>=Assumptions!$B$60+Assumptions!$B$48-2,C$3>=Assumptions!$B$14,C10>=Assumptions!$B$61*Assumptions!$B$51),1,0) | D14: =IF(OR(C14=1,AND(Assumptions!$B$59=1,D$3>=Assumptions!$B$60+Assumptions!$B$48-2,D$3>=Assumptions!$B$14,D10>=Assumptions!$B$61*Assumptions!$B$51)),1,0) | E14: =IF(OR(D14=1,AND(Assumptions!$B$59=1,E$3>=Assumptions!$B$60+Assumptions!$B$48-2,E$3>=Assumptions!$B$14,E10>=Assumptions!$B$61*Assumptions!$B$51)),1,0) | F14: =IF(OR(E14=1,AND(Assumptions!$B$59=1,F$3>=Assumptions!$B$60+Assumptions!$B$48-2,F$3>=Assumptions!$B$14,F10>=Assumptions!$B$61*Assumptions!$B$51)),1,0) | G14: =IF(OR(F14=1,AND(Assumptions!$B$59=1,G$3>=Assumptions!$B$60+Assumptions!$B$48-2,G$3>=Assumptions!$B$14,G10>=Assumptions!$B$61*Assumptions!$B$51)),1,0) | H14: =IF(OR(G14=1,AND(Assumptions!$B$59=1,H$3>=Assumptions!$B$60+Assumptions!$B$48-2,H$3>=Assumptions!$B$14,H10>=Assumptions!$B$61*Assumptions!$B$51)),1,0) | I14: =IF(OR(H14=1,AND(Assumptions!$B$59=1,I$3>=Assumptions!$B$60+Assumptions!$B$48-2,I$3>=Assumptions!$B$14,I10>=Assumptions!$B$61*Assumptions!$B$51)),1,0) | J14: =IF(OR(I14=1,AND(Assumptions!$B$59=1,J$3>=Assumptions!$B$60+Assumptions!$B$48-2,J$3>=Assumptions!$B$14,J10>=Assumptions!$B$61*Assumptions!$B$51)),1,0) | K14: =IF(OR(J14=1,AND(Assumptions!$B$59=1,K$3>=Assumptions!$B$60+Assumptions!$B$48-2,K$3>=Assumptions!$B$14,K10>=Assumptions!$B$61*Assumptions!$B$51)),1,0) | ... BJ14: =IF(OR(BI14=1,AND(Assumptions!$B$59=1,BJ$3>=Assumptions!$B$60+Assumptions!$B$48-2,BJ$3>=Assumptions!$B$14,BJ10>=Assumptions!$B$61*Assumptions!$B$51)),1,0)
A15: Live: Nigeria | B15: flag | C15: =0 | D15: =0 | E15: =C14 | F15: =D14 | G15: =E14 | H15: =F14 | I15: =G14 | J15: =H14 | K15: =I14 | L15: =J14 | ... BJ15: =BH14
A16: Launch decided (country lead hired): Kenya | B16: flag | C16: =IF(AND(Assumptions!$B$69=1,C$3>=Assumptions!$B$70+Assumptions!$B$48-2,C$3>=Assumptions!$B$14,C10>=Assumptions!$B$71*Assumptions!$B$51),1,0) | D16: =IF(OR(C16=1,AND(Assumptions!$B$69=1,D$3>=Assumptions!$B$70+Assumptions!$B$48-2,D$3>=Assumptions!$B$14,D10>=Assumptions!$B$71*Assumptions!$B$51)),1,0) | E16: =IF(OR(D16=1,AND(Assumptions!$B$69=1,E$3>=Assumptions!$B$70+Assumptions!$B$48-2,E$3>=Assumptions!$B$14,E10>=Assumptions!$B$71*Assumptions!$B$51)),1,0) | F16: =IF(OR(E16=1,AND(Assumptions!$B$69=1,F$3>=Assumptions!$B$70+Assumptions!$B$48-2,F$3>=Assumptions!$B$14,F10>=Assumptions!$B$71*Assumptions!$B$51)),1,0) | G16: =IF(OR(F16=1,AND(Assumptions!$B$69=1,G$3>=Assumptions!$B$70+Assumptions!$B$48-2,G$3>=Assumptions!$B$14,G10>=Assumptions!$B$71*Assumptions!$B$51)),1,0) | H16: =IF(OR(G16=1,AND(Assumptions!$B$69=1,H$3>=Assumptions!$B$70+Assumptions!$B$48-2,H$3>=Assumptions!$B$14,H10>=Assumptions!$B$71*Assumptions!$B$51)),1,0) | I16: =IF(OR(H16=1,AND(Assumptions!$B$69=1,I$3>=Assumptions!$B$70+Assumptions!$B$48-2,I$3>=Assumptions!$B$14,I10>=Assumptions!$B$71*Assumptions!$B$51)),1,0) | J16: =IF(OR(I16=1,AND(Assumptions!$B$69=1,J$3>=Assumptions!$B$70+Assumptions!$B$48-2,J$3>=Assumptions!$B$14,J10>=Assumptions!$B$71*Assumptions!$B$51)),1,0) | K16: =IF(OR(J16=1,AND(Assumptions!$B$69=1,K$3>=Assumptions!$B$70+Assumptions!$B$48-2,K$3>=Assumptions!$B$14,K10>=Assumptions!$B$71*Assumptions!$B$51)),1,0) | ... BJ16: =IF(OR(BI16=1,AND(Assumptions!$B$69=1,BJ$3>=Assumptions!$B$70+Assumptions!$B$48-2,BJ$3>=Assumptions!$B$14,BJ10>=Assumptions!$B$71*Assumptions!$B$51)),1,0)
A17: Live: Kenya | B17: flag | C17: =0 | D17: =0 | E17: =C16 | F17: =D16 | G17: =E16 | H17: =F16 | I17: =G16 | J17: =H16 | K17: =I16 | L17: =J16 | ... BJ17: =BH16
A18: Launch decided (country lead hired): Ghana | B18: flag | C18: =IF(AND(Assumptions!$B$79=1,C$3>=Assumptions!$B$80+Assumptions!$B$48-2,C$3>=Assumptions!$B$14,C10>=Assumptions!$B$81*Assumptions!$B$51),1,0) | D18: =IF(OR(C18=1,AND(Assumptions!$B$79=1,D$3>=Assumptions!$B$80+Assumptions!$B$48-2,D$3>=Assumptions!$B$14,D10>=Assumptions!$B$81*Assumptions!$B$51)),1,0) | E18: =IF(OR(D18=1,AND(Assumptions!$B$79=1,E$3>=Assumptions!$B$80+Assumptions!$B$48-2,E$3>=Assumptions!$B$14,E10>=Assumptions!$B$81*Assumptions!$B$51)),1,0) | F18: =IF(OR(E18=1,AND(Assumptions!$B$79=1,F$3>=Assumptions!$B$80+Assumptions!$B$48-2,F$3>=Assumptions!$B$14,F10>=Assumptions!$B$81*Assumptions!$B$51)),1,0) | G18: =IF(OR(F18=1,AND(Assumptions!$B$79=1,G$3>=Assumptions!$B$80+Assumptions!$B$48-2,G$3>=Assumptions!$B$14,G10>=Assumptions!$B$81*Assumptions!$B$51)),1,0) | H18: =IF(OR(G18=1,AND(Assumptions!$B$79=1,H$3>=Assumptions!$B$80+Assumptions!$B$48-2,H$3>=Assumptions!$B$14,H10>=Assumptions!$B$81*Assumptions!$B$51)),1,0) | I18: =IF(OR(H18=1,AND(Assumptions!$B$79=1,I$3>=Assumptions!$B$80+Assumptions!$B$48-2,I$3>=Assumptions!$B$14,I10>=Assumptions!$B$81*Assumptions!$B$51)),1,0) | J18: =IF(OR(I18=1,AND(Assumptions!$B$79=1,J$3>=Assumptions!$B$80+Assumptions!$B$48-2,J$3>=Assumptions!$B$14,J10>=Assumptions!$B$81*Assumptions!$B$51)),1,0) | K18: =IF(OR(J18=1,AND(Assumptions!$B$79=1,K$3>=Assumptions!$B$80+Assumptions!$B$48-2,K$3>=Assumptions!$B$14,K10>=Assumptions!$B$81*Assumptions!$B$51)),1,0) | ... BJ18: =IF(OR(BI18=1,AND(Assumptions!$B$79=1,BJ$3>=Assumptions!$B$80+Assumptions!$B$48-2,BJ$3>=Assumptions!$B$14,BJ10>=Assumptions!$B$81*Assumptions!$B$51)),1,0)
A19: Live: Ghana | B19: flag | C19: =0 | D19: =0 | E19: =C18 | F19: =D18 | G19: =E18 | H19: =F18 | I19: =G18 | J19: =H18 | K19: =I18 | L19: =J18 | ... BJ19: =BH18
A20: Launch decided (country lead hired): Rest of Africa (USD) | B20: flag | C20: =IF(AND(Assumptions!$B$89=1,C$3>=Assumptions!$B$90+Assumptions!$B$48-2,C$3>=Assumptions!$B$14,C10>=Assumptions!$B$91*Assumptions!$B$51),1,0) | D20: =IF(OR(C20=1,AND(Assumptions!$B$89=1,D$3>=Assumptions!$B$90+Assumptions!$B$48-2,D$3>=Assumptions!$B$14,D10>=Assumptions!$B$91*Assumptions!$B$51)),1,0) | E20: =IF(OR(D20=1,AND(Assumptions!$B$89=1,E$3>=Assumptions!$B$90+Assumptions!$B$48-2,E$3>=Assumptions!$B$14,E10>=Assumptions!$B$91*Assumptions!$B$51)),1,0) | F20: =IF(OR(E20=1,AND(Assumptions!$B$89=1,F$3>=Assumptions!$B$90+Assumptions!$B$48-2,F$3>=Assumptions!$B$14,F10>=Assumptions!$B$91*Assumptions!$B$51)),1,0) | G20: =IF(OR(F20=1,AND(Assumptions!$B$89=1,G$3>=Assumptions!$B$90+Assumptions!$B$48-2,G$3>=Assumptions!$B$14,G10>=Assumptions!$B$91*Assumptions!$B$51)),1,0) | H20: =IF(OR(G20=1,AND(Assumptions!$B$89=1,H$3>=Assumptions!$B$90+Assumptions!$B$48-2,H$3>=Assumptions!$B$14,H10>=Assumptions!$B$91*Assumptions!$B$51)),1,0) | I20: =IF(OR(H20=1,AND(Assumptions!$B$89=1,I$3>=Assumptions!$B$90+Assumptions!$B$48-2,I$3>=Assumptions!$B$14,I10>=Assumptions!$B$91*Assumptions!$B$51)),1,0) | J20: =IF(OR(I20=1,AND(Assumptions!$B$89=1,J$3>=Assumptions!$B$90+Assumptions!$B$48-2,J$3>=Assumptions!$B$14,J10>=Assumptions!$B$91*Assumptions!$B$51)),1,0) | K20: =IF(OR(J20=1,AND(Assumptions!$B$89=1,K$3>=Assumptions!$B$90+Assumptions!$B$48-2,K$3>=Assumptions!$B$14,K10>=Assumptions!$B$91*Assumptions!$B$51)),1,0) | ... BJ20: =IF(OR(BI20=1,AND(Assumptions!$B$89=1,BJ$3>=Assumptions!$B$90+Assumptions!$B$48-2,BJ$3>=Assumptions!$B$14,BJ10>=Assumptions!$B$91*Assumptions!$B$51)),1,0)
A21: Live: Rest of Africa (USD) | B21: flag | C21: =0 | D21: =0 | E21: =C20 | F21: =D20 | G21: =E20 | H21: =F20 | I21: =G20 | J21: =H20 | K21: =I20 | L21: =J20 | ... BJ21: =BH20
A22: Launch decided (country lead hired): Botswana & Namibia | B22: flag | C22: =IF(AND(Assumptions!$B$97=1,C$3>=Assumptions!$B$98+Assumptions!$B$48-2,C$3>=Assumptions!$B$14,C10>=Assumptions!$B$99*Assumptions!$B$51),1,0) | D22: =IF(OR(C22=1,AND(Assumptions!$B$97=1,D$3>=Assumptions!$B$98+Assumptions!$B$48-2,D$3>=Assumptions!$B$14,D10>=Assumptions!$B$99*Assumptions!$B$51)),1,0) | E22: =IF(OR(D22=1,AND(Assumptions!$B$97=1,E$3>=Assumptions!$B$98+Assumptions!$B$48-2,E$3>=Assumptions!$B$14,E10>=Assumptions!$B$99*Assumptions!$B$51)),1,0) | F22: =IF(OR(E22=1,AND(Assumptions!$B$97=1,F$3>=Assumptions!$B$98+Assumptions!$B$48-2,F$3>=Assumptions!$B$14,F10>=Assumptions!$B$99*Assumptions!$B$51)),1,0) | G22: =IF(OR(F22=1,AND(Assumptions!$B$97=1,G$3>=Assumptions!$B$98+Assumptions!$B$48-2,G$3>=Assumptions!$B$14,G10>=Assumptions!$B$99*Assumptions!$B$51)),1,0) | H22: =IF(OR(G22=1,AND(Assumptions!$B$97=1,H$3>=Assumptions!$B$98+Assumptions!$B$48-2,H$3>=Assumptions!$B$14,H10>=Assumptions!$B$99*Assumptions!$B$51)),1,0) | I22: =IF(OR(H22=1,AND(Assumptions!$B$97=1,I$3>=Assumptions!$B$98+Assumptions!$B$48-2,I$3>=Assumptions!$B$14,I10>=Assumptions!$B$99*Assumptions!$B$51)),1,0) | J22: =IF(OR(I22=1,AND(Assumptions!$B$97=1,J$3>=Assumptions!$B$98+Assumptions!$B$48-2,J$3>=Assumptions!$B$14,J10>=Assumptions!$B$99*Assumptions!$B$51)),1,0) | K22: =IF(OR(J22=1,AND(Assumptions!$B$97=1,K$3>=Assumptions!$B$98+Assumptions!$B$48-2,K$3>=Assumptions!$B$14,K10>=Assumptions!$B$99*Assumptions!$B$51)),1,0) | ... BJ22: =IF(OR(BI22=1,AND(Assumptions!$B$97=1,BJ$3>=Assumptions!$B$98+Assumptions!$B$48-2,BJ$3>=Assumptions!$B$14,BJ10>=Assumptions!$B$99*Assumptions!$B$51)),1,0)
A23: Live: Botswana & Namibia | B23: flag | C23: =0 | D23: =0 | E23: =C22 | F23: =D22 | G23: =E22 | H23: =F22 | I23: =G22 | J23: =H22 | K23: =I22 | L23: =J22 | ... BJ23: =BH22
A24: Launch month: South Africa | B24: flag | C24: =C13-0 | D24: =D13-C13 | E24: =E13-D13 | F24: =F13-E13 | G24: =G13-F13 | H24: =H13-G13 | I24: =I13-H13 | J24: =J13-I13 | K24: =K13-J13 | ... BJ24: =BJ13-BI13
A25: Launch month: Nigeria | B25: flag | C25: =C15-0 | D25: =D15-C15 | E25: =E15-D15 | F25: =F15-E15 | G25: =G15-F15 | H25: =H15-G15 | I25: =I15-H15 | J25: =J15-I15 | K25: =K15-J15 | ... BJ25: =BJ15-BI15
A26: Launch month: Kenya | B26: flag | C26: =C17-0 | D26: =D17-C17 | E26: =E17-D17 | F26: =F17-E17 | G26: =G17-F17 | H26: =H17-G17 | I26: =I17-H17 | J26: =J17-I17 | K26: =K17-J17 | ... BJ26: =BJ17-BI17
A27: Launch month: Ghana | B27: flag | C27: =C19-0 | D27: =D19-C19 | E27: =E19-D19 | F27: =F19-E19 | G27: =G19-F19 | H27: =H19-G19 | I27: =I19-H19 | J27: =J19-I19 | K27: =K19-J19 | ... BJ27: =BJ19-BI19
A28: Launch month: Rest of Africa (USD) | B28: flag | C28: =C21-0 | D28: =D21-C21 | E28: =E21-D21 | F28: =F21-E21 | G28: =G21-F21 | H28: =H21-G21 | I28: =I21-H21 | J28: =J21-I21 | K28: =K21-J21 | ... BJ28: =BJ21-BI21
A29: Launch month: Botswana & Namibia | B29: flag | C29: =C23-0 | D29: =D23-C23 | E29: =E23-D23 | F29: =F23-E23 | G29: =G23-F23 | H29: =H23-G23 | I29: =I23-H23 | J29: =J23-I23 | K29: =K23-J23 | ... BJ29: =BJ23-BI23
A30: Founding Member offer running: South Africa | B30: flag | C30: =IF(AND(Assumptions!$B$31=1,C$3>=Assumptions!$B$33,C$3<=Assumptions!$B$34),C13,0) | D30: =IF(AND(Assumptions!$B$31=1,D$3>=Assumptions!$B$33,D$3<=Assumptions!$B$34),D13,0) | E30: =IF(AND(Assumptions!$B$31=1,E$3>=Assumptions!$B$33,E$3<=Assumptions!$B$34),E13,0) | F30: =IF(AND(Assumptions!$B$31=1,F$3>=Assumptions!$B$33,F$3<=Assumptions!$B$34),F13,0) | G30: =IF(AND(Assumptions!$B$31=1,G$3>=Assumptions!$B$33,G$3<=Assumptions!$B$34),G13,0) | H30: =IF(AND(Assumptions!$B$31=1,H$3>=Assumptions!$B$33,H$3<=Assumptions!$B$34),H13,0) | I30: =IF(AND(Assumptions!$B$31=1,I$3>=Assumptions!$B$33,I$3<=Assumptions!$B$34),I13,0) | J30: =IF(AND(Assumptions!$B$31=1,J$3>=Assumptions!$B$33,J$3<=Assumptions!$B$34),J13,0) | ... BJ30: =IF(AND(Assumptions!$B$31=1,BJ$3>=Assumptions!$B$33,BJ$3<=Assumptions!$B$34),BJ13,0)
A32: FX drift & quarterly repricing (ZAR value of fixed local / USD price points; 1.000 = parity at Sept 2026 rates)
A33: ZAR value of 1 unit of Nigeria currency (index) | B33: x | C33: =(1+Pricing!$B$26)^((C$3-1)/12)*IF(C$3>=Assumptions!$B$38,1/(1+Assumptions!$B$37),1) | D33: =(1+Pricing!$B$26)^((D$3-1)/12)*IF(D$3>=Assumptions!$B$38,1/(1+Assumptions!$B$37),1) | E33: =(1+Pricing!$B$26)^((E$3-1)/12)*IF(E$3>=Assumptions!$B$38,1/(1+Assumptions!$B$37),1) | F33: =(1+Pricing!$B$26)^((F$3-1)/12)*IF(F$3>=Assumptions!$B$38,1/(1+Assumptions!$B$37),1) | G33: =(1+Pricing!$B$26)^((G$3-1)/12)*IF(G$3>=Assumptions!$B$38,1/(1+Assumptions!$B$37),1) | H33: =(1+Pricing!$B$26)^((H$3-1)/12)*IF(H$3>=Assumptions!$B$38,1/(1+Assumptions!$B$37),1) | I33: =(1+Pricing!$B$26)^((I$3-1)/12)*IF(I$3>=Assumptions!$B$38,1/(1+Assumptions!$B$37),1) | J33: =(1+Pricing!$B$26)^((J$3-1)/12)*IF(J$3>=Assumptions!$B$38,1/(1+Assumptions!$B$37),1) | ... BJ33: =(1+Pricing!$B$26)^((BJ$3-1)/12)*IF(BJ$3>=Assumptions!$B$38,1/(1+Assumptions!$B$37),1)
A34: Local price level after repricing: Nigeria | B34: x | C34: =1 | D34: =C34 | E34: =D34 | F34: =IF(AND(Pricing!$B$31=1,MOD(F$3-1,3)=0,ABS(E34*C33-1)>Pricing!$B$30),1/C33,E34) | G34: =IF(AND(Pricing!$B$31=1,MOD(G$3-1,3)=0,ABS(F34*D33-1)>Pricing!$B$30),1/D33,F34) | H34: =IF(AND(Pricing!$B$31=1,MOD(H$3-1,3)=0,ABS(G34*E33-1)>Pricing!$B$30),1/E33,G34) | I34: =IF(AND(Pricing!$B$31=1,MOD(I$3-1,3)=0,ABS(H34*F33-1)>Pricing!$B$30),1/F33,H34) | J34: =IF(AND(Pricing!$B$31=1,MOD(J$3-1,3)=0,ABS(I34*G33-1)>Pricing!$B$30),1/G33,I34) | K34: =IF(AND(Pricing!$B$31=1,MOD(K$3-1,3)=0,ABS(J34*H33-1)>Pricing!$B$30),1/H33,J34) | L34: =IF(AND(Pricing!$B$31=1,MOD(L$3-1,3)=0,ABS(K34*I33-1)>Pricing!$B$30),1/I33,K34) | M34: =IF(AND(Pricing!$B$31=1,MOD(M$3-1,3)=0,ABS(L34*J33-1)>Pricing!$B$30),1/J33,L34) | ... BJ34: =IF(AND(Pricing!$B$31=1,MOD(BJ$3-1,3)=0,ABS(BI34*BG33-1)>Pricing!$B$30),1/BG33,BI34)
A35: ZAR value factor of local prices: Nigeria | B35: x | C35: =C34*C33 | D35: =D34*D33 | E35: =E34*E33 | F35: =F34*F33 | G35: =G34*G33 | H35: =H34*H33 | I35: =I34*I33 | J35: =J34*J33 | ... BJ35: =BJ34*BJ33
A36: ZAR value of 1 unit of Kenya currency (index) | B36: x | C36: =(1+Pricing!$B$27)^((C$3-1)/12)*IF(C$3>=Assumptions!$B$38,1/(1+Assumptions!$B$37),1) | D36: =(1+Pricing!$B$27)^((D$3-1)/12)*IF(D$3>=Assumptions!$B$38,1/(1+Assumptions!$B$37),1) | E36: =(1+Pricing!$B$27)^((E$3-1)/12)*IF(E$3>=Assumptions!$B$38,1/(1+Assumptions!$B$37),1) | F36: =(1+Pricing!$B$27)^((F$3-1)/12)*IF(F$3>=Assumptions!$B$38,1/(1+Assumptions!$B$37),1) | G36: =(1+Pricing!$B$27)^((G$3-1)/12)*IF(G$3>=Assumptions!$B$38,1/(1+Assumptions!$B$37),1) | H36: =(1+Pricing!$B$27)^((H$3-1)/12)*IF(H$3>=Assumptions!$B$38,1/(1+Assumptions!$B$37),1) | I36: =(1+Pricing!$B$27)^((I$3-1)/12)*IF(I$3>=Assumptions!$B$38,1/(1+Assumptions!$B$37),1) | J36: =(1+Pricing!$B$27)^((J$3-1)/12)*IF(J$3>=Assumptions!$B$38,1/(1+Assumptions!$B$37),1) | ... BJ36: =(1+Pricing!$B$27)^((BJ$3-1)/12)*IF(BJ$3>=Assumptions!$B$38,1/(1+Assumptions!$B$37),1)
A37: Local price level after repricing: Kenya | B37: x | C37: =1 | D37: =C37 | E37: =D37 | F37: =IF(AND(Pricing!$B$31=1,MOD(F$3-1,3)=0,ABS(E37*C36-1)>Pricing!$B$30),1/C36,E37) | G37: =IF(AND(Pricing!$B$31=1,MOD(G$3-1,3)=0,ABS(F37*D36-1)>Pricing!$B$30),1/D36,F37) | H37: =IF(AND(Pricing!$B$31=1,MOD(H$3-1,3)=0,ABS(G37*E36-1)>Pricing!$B$30),1/E36,G37) | I37: =IF(AND(Pricing!$B$31=1,MOD(I$3-1,3)=0,ABS(H37*F36-1)>Pricing!$B$30),1/F36,H37) | J37: =IF(AND(Pricing!$B$31=1,MOD(J$3-1,3)=0,ABS(I37*G36-1)>Pricing!$B$30),1/G36,I37) | K37: =IF(AND(Pricing!$B$31=1,MOD(K$3-1,3)=0,ABS(J37*H36-1)>Pricing!$B$30),1/H36,J37) | L37: =IF(AND(Pricing!$B$31=1,MOD(L$3-1,3)=0,ABS(K37*I36-1)>Pricing!$B$30),1/I36,K37) | M37: =IF(AND(Pricing!$B$31=1,MOD(M$3-1,3)=0,ABS(L37*J36-1)>Pricing!$B$30),1/J36,L37) | ... BJ37: =IF(AND(Pricing!$B$31=1,MOD(BJ$3-1,3)=0,ABS(BI37*BG36-1)>Pricing!$B$30),1/BG36,BI37)
A38: ZAR value factor of local prices: Kenya | B38: x | C38: =C37*C36 | D38: =D37*D36 | E38: =E37*E36 | F38: =F37*F36 | G38: =G37*G36 | H38: =H37*H36 | I38: =I37*I36 | J38: =J37*J36 | ... BJ38: =BJ37*BJ36
A39: ZAR value of 1 unit of Ghana currency (index) | B39: x | C39: =(1+Pricing!$B$28)^((C$3-1)/12)*IF(C$3>=Assumptions!$B$38,1/(1+Assumptions!$B$37),1) | D39: =(1+Pricing!$B$28)^((D$3-1)/12)*IF(D$3>=Assumptions!$B$38,1/(1+Assumptions!$B$37),1) | E39: =(1+Pricing!$B$28)^((E$3-1)/12)*IF(E$3>=Assumptions!$B$38,1/(1+Assumptions!$B$37),1) | F39: =(1+Pricing!$B$28)^((F$3-1)/12)*IF(F$3>=Assumptions!$B$38,1/(1+Assumptions!$B$37),1) | G39: =(1+Pricing!$B$28)^((G$3-1)/12)*IF(G$3>=Assumptions!$B$38,1/(1+Assumptions!$B$37),1) | H39: =(1+Pricing!$B$28)^((H$3-1)/12)*IF(H$3>=Assumptions!$B$38,1/(1+Assumptions!$B$37),1) | I39: =(1+Pricing!$B$28)^((I$3-1)/12)*IF(I$3>=Assumptions!$B$38,1/(1+Assumptions!$B$37),1) | J39: =(1+Pricing!$B$28)^((J$3-1)/12)*IF(J$3>=Assumptions!$B$38,1/(1+Assumptions!$B$37),1) | ... BJ39: =(1+Pricing!$B$28)^((BJ$3-1)/12)*IF(BJ$3>=Assumptions!$B$38,1/(1+Assumptions!$B$37),1)
A40: Local price level after repricing: Ghana | B40: x | C40: =1 | D40: =C40 | E40: =D40 | F40: =IF(AND(Pricing!$B$31=1,MOD(F$3-1,3)=0,ABS(E40*C39-1)>Pricing!$B$30),1/C39,E40) | G40: =IF(AND(Pricing!$B$31=1,MOD(G$3-1,3)=0,ABS(F40*D39-1)>Pricing!$B$30),1/D39,F40) | H40: =IF(AND(Pricing!$B$31=1,MOD(H$3-1,3)=0,ABS(G40*E39-1)>Pricing!$B$30),1/E39,G40) | I40: =IF(AND(Pricing!$B$31=1,MOD(I$3-1,3)=0,ABS(H40*F39-1)>Pricing!$B$30),1/F39,H40) | J40: =IF(AND(Pricing!$B$31=1,MOD(J$3-1,3)=0,ABS(I40*G39-1)>Pricing!$B$30),1/G39,I40) | K40: =IF(AND(Pricing!$B$31=1,MOD(K$3-1,3)=0,ABS(J40*H39-1)>Pricing!$B$30),1/H39,J40) | L40: =IF(AND(Pricing!$B$31=1,MOD(L$3-1,3)=0,ABS(K40*I39-1)>Pricing!$B$30),1/I39,K40) | M40: =IF(AND(Pricing!$B$31=1,MOD(M$3-1,3)=0,ABS(L40*J39-1)>Pricing!$B$30),1/J39,L40) | ... BJ40: =IF(AND(Pricing!$B$31=1,MOD(BJ$3-1,3)=0,ABS(BI40*BG39-1)>Pricing!$B$30),1/BG39,BI40)
A41: ZAR value factor of local prices: Ghana | B41: x | C41: =C40*C39 | D41: =D40*D39 | E41: =E40*E39 | F41: =F40*F39 | G41: =G40*G39 | H41: =H40*H39 | I41: =I40*I39 | J41: =J40*J39 | ... BJ41: =BJ40*BJ39
A42: ZAR value of 1 unit of Rest of Africa (USD) currency (index) | B42: x | C42: =(1+Pricing!$B$29)^((C$3-1)/12)*IF(C$3>=Assumptions!$B$38,1/(1+Assumptions!$B$37),1) | D42: =(1+Pricing!$B$29)^((D$3-1)/12)*IF(D$3>=Assumptions!$B$38,1/(1+Assumptions!$B$37),1) | E42: =(1+Pricing!$B$29)^((E$3-1)/12)*IF(E$3>=Assumptions!$B$38,1/(1+Assumptions!$B$37),1) | F42: =(1+Pricing!$B$29)^((F$3-1)/12)*IF(F$3>=Assumptions!$B$38,1/(1+Assumptions!$B$37),1) | G42: =(1+Pricing!$B$29)^((G$3-1)/12)*IF(G$3>=Assumptions!$B$38,1/(1+Assumptions!$B$37),1) | H42: =(1+Pricing!$B$29)^((H$3-1)/12)*IF(H$3>=Assumptions!$B$38,1/(1+Assumptions!$B$37),1) | I42: =(1+Pricing!$B$29)^((I$3-1)/12)*IF(I$3>=Assumptions!$B$38,1/(1+Assumptions!$B$37),1) | J42: =(1+Pricing!$B$29)^((J$3-1)/12)*IF(J$3>=Assumptions!$B$38,1/(1+Assumptions!$B$37),1) | ... BJ42: =(1+Pricing!$B$29)^((BJ$3-1)/12)*IF(BJ$3>=Assumptions!$B$38,1/(1+Assumptions!$B$37),1)
A43: Local price level after repricing: Rest of Africa (USD) | B43: x | C43: =1 | D43: =C43 | E43: =D43 | F43: =IF(AND(Pricing!$B$31=1,MOD(F$3-1,3)=0,ABS(E43*C42-1)>Pricing!$B$30),1/C42,E43) | G43: =IF(AND(Pricing!$B$31=1,MOD(G$3-1,3)=0,ABS(F43*D42-1)>Pricing!$B$30),1/D42,F43) | H43: =IF(AND(Pricing!$B$31=1,MOD(H$3-1,3)=0,ABS(G43*E42-1)>Pricing!$B$30),1/E42,G43) | I43: =IF(AND(Pricing!$B$31=1,MOD(I$3-1,3)=0,ABS(H43*F42-1)>Pricing!$B$30),1/F42,H43) | J43: =IF(AND(Pricing!$B$31=1,MOD(J$3-1,3)=0,ABS(I43*G42-1)>Pricing!$B$30),1/G42,I43) | K43: =IF(AND(Pricing!$B$31=1,MOD(K$3-1,3)=0,ABS(J43*H42-1)>Pricing!$B$30),1/H42,J43) | L43: =IF(AND(Pricing!$B$31=1,MOD(L$3-1,3)=0,ABS(K43*I42-1)>Pricing!$B$30),1/I42,K43) | M43: =IF(AND(Pricing!$B$31=1,MOD(M$3-1,3)=0,ABS(L43*J42-1)>Pricing!$B$30),1/J42,L43) | ... BJ43: =IF(AND(Pricing!$B$31=1,MOD(BJ$3-1,3)=0,ABS(BI43*BG42-1)>Pricing!$B$30),1/BG42,BI43)
A44: ZAR value factor of local prices: Rest of Africa (USD) | B44: x | C44: =C43*C42 | D44: =D43*D42 | E44: =E43*E42 | F44: =F43*F42 | G44: =G43*G42 | H44: =H43*H42 | I44: =I43*I42 | J44: =J43*J42 | ... BJ44: =BJ43*BJ42
A46: Self-serve sign-ups (Free + paid) by market (start in each market's launch month; no trials)
A47: Monthly sign-up growth rate (scenario, by fiscal year) | B47: % m/m | C47: =CHOOSE(C$5,Assumptions!$B$40,Assumptions!$B$41,Assumptions!$B$42,Assumptions!$B$43,Assumptions!$B$44) | D47: =CHOOSE(D$5,Assumptions!$B$40,Assumptions!$B$41,Assumptions!$B$42,Assumptions!$B$43,Assumptions!$B$44) | E47: =CHOOSE(E$5,Assumptions!$B$40,Assumptions!$B$41,Assumptions!$B$42,Assumptions!$B$43,Assumptions!$B$44) | F47: =CHOOSE(F$5,Assumptions!$B$40,Assumptions!$B$41,Assumptions!$B$42,Assumptions!$B$43,Assumptions!$B$44) | G47: =CHOOSE(G$5,Assumptions!$B$40,Assumptions!$B$41,Assumptions!$B$42,Assumptions!$B$43,Assumptions!$B$44) | H47: =CHOOSE(H$5,Assumptions!$B$40,Assumptions!$B$41,Assumptions!$B$42,Assumptions!$B$43,Assumptions!$B$44) | I47: =CHOOSE(I$5,Assumptions!$B$40,Assumptions!$B$41,Assumptions!$B$42,Assumptions!$B$43,Assumptions!$B$44) | J47: =CHOOSE(J$5,Assumptions!$B$40,Assumptions!$B$41,Assumptions!$B$42,Assumptions!$B$43,Assumptions!$B$44) | ... BJ47: =CHOOSE(BJ$5,Assumptions!$B$40,Assumptions!$B$41,Assumptions!$B$42,Assumptions!$B$43,Assumptions!$B$44)
A48: Self-serve sign-ups: South Africa | B48: sign-ups | C48: =IF(C13=0,0,Assumptions!$B$58*Assumptions!$B$29) | D48: =IF(D13=0,0,IF(C13=0,Assumptions!$B$58*Assumptions!$B$29,C48*(1+D47))) | E48: =IF(E13=0,0,IF(D13=0,Assumptions!$B$58*Assumptions!$B$29,D48*(1+E47))) | F48: =IF(F13=0,0,IF(E13=0,Assumptions!$B$58*Assumptions!$B$29,E48*(1+F47))) | G48: =IF(G13=0,0,IF(F13=0,Assumptions!$B$58*Assumptions!$B$29,F48*(1+G47))) | H48: =IF(H13=0,0,IF(G13=0,Assumptions!$B$58*Assumptions!$B$29,G48*(1+H47))) | I48: =IF(I13=0,0,IF(H13=0,Assumptions!$B$58*Assumptions!$B$29,H48*(1+I47))) | J48: =IF(J13=0,0,IF(I13=0,Assumptions!$B$58*Assumptions!$B$29,I48*(1+J47))) | K48: =IF(K13=0,0,IF(J13=0,Assumptions!$B$58*Assumptions!$B$29,J48*(1+K47))) | ... BJ48: =IF(BJ13=0,0,IF(BI13=0,Assumptions!$B$58*Assumptions!$B$29,BI48*(1+BJ47)))
A49: Self-serve sign-ups: Nigeria | B49: sign-ups | C49: =IF(C15=0,0,Assumptions!$B$62*Assumptions!$B$29) | D49: =IF(D15=0,0,IF(C15=0,Assumptions!$B$62*Assumptions!$B$29,C49*(1+D47))) | E49: =IF(E15=0,0,IF(D15=0,Assumptions!$B$62*Assumptions!$B$29,D49*(1+E47))) | F49: =IF(F15=0,0,IF(E15=0,Assumptions!$B$62*Assumptions!$B$29,E49*(1+F47))) | G49: =IF(G15=0,0,IF(F15=0,Assumptions!$B$62*Assumptions!$B$29,F49*(1+G47))) | H49: =IF(H15=0,0,IF(G15=0,Assumptions!$B$62*Assumptions!$B$29,G49*(1+H47))) | I49: =IF(I15=0,0,IF(H15=0,Assumptions!$B$62*Assumptions!$B$29,H49*(1+I47))) | J49: =IF(J15=0,0,IF(I15=0,Assumptions!$B$62*Assumptions!$B$29,I49*(1+J47))) | K49: =IF(K15=0,0,IF(J15=0,Assumptions!$B$62*Assumptions!$B$29,J49*(1+K47))) | ... BJ49: =IF(BJ15=0,0,IF(BI15=0,Assumptions!$B$62*Assumptions!$B$29,BI49*(1+BJ47)))
A50: Self-serve sign-ups: Kenya | B50: sign-ups | C50: =IF(C17=0,0,Assumptions!$B$72*Assumptions!$B$29) | D50: =IF(D17=0,0,IF(C17=0,Assumptions!$B$72*Assumptions!$B$29,C50*(1+D47))) | E50: =IF(E17=0,0,IF(D17=0,Assumptions!$B$72*Assumptions!$B$29,D50*(1+E47))) | F50: =IF(F17=0,0,IF(E17=0,Assumptions!$B$72*Assumptions!$B$29,E50*(1+F47))) | G50: =IF(G17=0,0,IF(F17=0,Assumptions!$B$72*Assumptions!$B$29,F50*(1+G47))) | H50: =IF(H17=0,0,IF(G17=0,Assumptions!$B$72*Assumptions!$B$29,G50*(1+H47))) | I50: =IF(I17=0,0,IF(H17=0,Assumptions!$B$72*Assumptions!$B$29,H50*(1+I47))) | J50: =IF(J17=0,0,IF(I17=0,Assumptions!$B$72*Assumptions!$B$29,I50*(1+J47))) | K50: =IF(K17=0,0,IF(J17=0,Assumptions!$B$72*Assumptions!$B$29,J50*(1+K47))) | ... BJ50: =IF(BJ17=0,0,IF(BI17=0,Assumptions!$B$72*Assumptions!$B$29,BI50*(1+BJ47)))
A51: Self-serve sign-ups: Ghana | B51: sign-ups | C51: =IF(C19=0,0,Assumptions!$B$82*Assumptions!$B$29) | D51: =IF(D19=0,0,IF(C19=0,Assumptions!$B$82*Assumptions!$B$29,C51*(1+D47))) | E51: =IF(E19=0,0,IF(D19=0,Assumptions!$B$82*Assumptions!$B$29,D51*(1+E47))) | F51: =IF(F19=0,0,IF(E19=0,Assumptions!$B$82*Assumptions!$B$29,E51*(1+F47))) | G51: =IF(G19=0,0,IF(F19=0,Assumptions!$B$82*Assumptions!$B$29,F51*(1+G47))) | H51: =IF(H19=0,0,IF(G19=0,Assumptions!$B$82*Assumptions!$B$29,G51*(1+H47))) | I51: =IF(I19=0,0,IF(H19=0,Assumptions!$B$82*Assumptions!$B$29,H51*(1+I47))) | J51: =IF(J19=0,0,IF(I19=0,Assumptions!$B$82*Assumptions!$B$29,I51*(1+J47))) | K51: =IF(K19=0,0,IF(J19=0,Assumptions!$B$82*Assumptions!$B$29,J51*(1+K47))) | ... BJ51: =IF(BJ19=0,0,IF(BI19=0,Assumptions!$B$82*Assumptions!$B$29,BI51*(1+BJ47)))
A52: Self-serve sign-ups: Rest of Africa (USD) | B52: sign-ups | C52: =IF(C21=0,0,Assumptions!$B$92*Assumptions!$B$29) | D52: =IF(D21=0,0,IF(C21=0,Assumptions!$B$92*Assumptions!$B$29,C52*(1+D47))) | E52: =IF(E21=0,0,IF(D21=0,Assumptions!$B$92*Assumptions!$B$29,D52*(1+E47))) | F52: =IF(F21=0,0,IF(E21=0,Assumptions!$B$92*Assumptions!$B$29,E52*(1+F47))) | G52: =IF(G21=0,0,IF(F21=0,Assumptions!$B$92*Assumptions!$B$29,F52*(1+G47))) | H52: =IF(H21=0,0,IF(G21=0,Assumptions!$B$92*Assumptions!$B$29,G52*(1+H47))) | I52: =IF(I21=0,0,IF(H21=0,Assumptions!$B$92*Assumptions!$B$29,H52*(1+I47))) | J52: =IF(J21=0,0,IF(I21=0,Assumptions!$B$92*Assumptions!$B$29,I52*(1+J47))) | K52: =IF(K21=0,0,IF(J21=0,Assumptions!$B$92*Assumptions!$B$29,J52*(1+K47))) | ... BJ52: =IF(BJ21=0,0,IF(BI21=0,Assumptions!$B$92*Assumptions!$B$29,BI52*(1+BJ47)))
A53: Self-serve sign-ups: Botswana & Namibia | B53: sign-ups | C53: =IF(C23=0,0,Assumptions!$B$100*Assumptions!$B$29) | D53: =IF(D23=0,0,IF(C23=0,Assumptions!$B$100*Assumptions!$B$29,C53*(1+D47))) | E53: =IF(E23=0,0,IF(D23=0,Assumptions!$B$100*Assumptions!$B$29,D53*(1+E47))) | F53: =IF(F23=0,0,IF(E23=0,Assumptions!$B$100*Assumptions!$B$29,E53*(1+F47))) | G53: =IF(G23=0,0,IF(F23=0,Assumptions!$B$100*Assumptions!$B$29,F53*(1+G47))) | H53: =IF(H23=0,0,IF(G23=0,Assumptions!$B$100*Assumptions!$B$29,G53*(1+H47))) | I53: =IF(I23=0,0,IF(H23=0,Assumptions!$B$100*Assumptions!$B$29,H53*(1+I47))) | J53: =IF(J23=0,0,IF(I23=0,Assumptions!$B$100*Assumptions!$B$29,I53*(1+J47))) | K53: =IF(K23=0,0,IF(J23=0,Assumptions!$B$100*Assumptions!$B$29,J53*(1+K47))) | ... BJ53: =IF(BJ23=0,0,IF(BI23=0,Assumptions!$B$100*Assumptions!$B$29,BI53*(1+BJ47)))
A54: Total self-serve sign-ups | B54: sign-ups | C54: =C48+C49+C50+C51+C52+C53 | D54: =D48+D49+D50+D51+D52+D53 | E54: =E48+E49+E50+E51+E52+E53 | F54: =F48+F49+F50+F51+F52+F53 | G54: =G48+G49+G50+G51+G52+G53 | H54: =H48+H49+H50+H51+H52+H53 | I54: =I48+I49+I50+I51+I52+I53 | J54: =J48+J49+J50+J51+J52+J53 | ... BJ54: =BJ48+BJ49+BJ50+BJ51+BJ52+BJ53
A56: Direct paid sign-ups wanted before the marketing cap (sign-ups x segment share x pay-at-sign-up rate x Founding Member uplift)
A57: Solo direct paid sign-ups wanted: South Africa | B57: workspaces | C57: =C48*Assumptions!$B$116*Assumptions!$B$117*Assumptions!$B$45*(1+Assumptions!$B$55*C30) | D57: =D48*Assumptions!$B$116*Assumptions!$B$117*Assumptions!$B$45*(1+Assumptions!$B$55*D30) | E57: =E48*Assumptions!$B$116*Assumptions!$B$117*Assumptions!$B$45*(1+Assumptions!$B$55*E30) | F57: =F48*Assumptions!$B$116*Assumptions!$B$117*Assumptions!$B$45*(1+Assumptions!$B$55*F30) | G57: =G48*Assumptions!$B$116*Assumptions!$B$117*Assumptions!$B$45*(1+Assumptions!$B$55*G30) | H57: =H48*Assumptions!$B$116*Assumptions!$B$117*Assumptions!$B$45*(1+Assumptions!$B$55*H30) | I57: =I48*Assumptions!$B$116*Assumptions!$B$117*Assumptions!$B$45*(1+Assumptions!$B$55*I30) | J57: =J48*Assumptions!$B$116*Assumptions!$B$117*Assumptions!$B$45*(1+Assumptions!$B$55*J30) | ... BJ57: =BJ48*Assumptions!$B$116*Assumptions!$B$117*Assumptions!$B$45*(1+Assumptions!$B$55*BJ30)
A58: SME direct paid sign-ups wanted: South Africa | B58: workspaces | C58: =C48*(1-Assumptions!$B$116)*Assumptions!$B$118*Assumptions!$B$45*(1+Assumptions!$B$55*C30) | D58: =D48*(1-Assumptions!$B$116)*Assumptions!$B$118*Assumptions!$B$45*(1+Assumptions!$B$55*D30) | E58: =E48*(1-Assumptions!$B$116)*Assumptions!$B$118*Assumptions!$B$45*(1+Assumptions!$B$55*E30) | F58: =F48*(1-Assumptions!$B$116)*Assumptions!$B$118*Assumptions!$B$45*(1+Assumptions!$B$55*F30) | G58: =G48*(1-Assumptions!$B$116)*Assumptions!$B$118*Assumptions!$B$45*(1+Assumptions!$B$55*G30) | H58: =H48*(1-Assumptions!$B$116)*Assumptions!$B$118*Assumptions!$B$45*(1+Assumptions!$B$55*H30) | I58: =I48*(1-Assumptions!$B$116)*Assumptions!$B$118*Assumptions!$B$45*(1+Assumptions!$B$55*I30) | J58: =J48*(1-Assumptions!$B$116)*Assumptions!$B$118*Assumptions!$B$45*(1+Assumptions!$B$55*J30) | ... BJ58: =BJ48*(1-Assumptions!$B$116)*Assumptions!$B$118*Assumptions!$B$45*(1+Assumptions!$B$55*BJ30)
A59: Solo direct paid sign-ups wanted: Nigeria | B59: workspaces | C59: =C49*Assumptions!$B$116*Assumptions!$B$117*Assumptions!$B$45 | D59: =D49*Assumptions!$B$116*Assumptions!$B$117*Assumptions!$B$45 | E59: =E49*Assumptions!$B$116*Assumptions!$B$117*Assumptions!$B$45 | F59: =F49*Assumptions!$B$116*Assumptions!$B$117*Assumptions!$B$45 | G59: =G49*Assumptions!$B$116*Assumptions!$B$117*Assumptions!$B$45 | H59: =H49*Assumptions!$B$116*Assumptions!$B$117*Assumptions!$B$45 | I59: =I49*Assumptions!$B$116*Assumptions!$B$117*Assumptions!$B$45 | J59: =J49*Assumptions!$B$116*Assumptions!$B$117*Assumptions!$B$45 | ... BJ59: =BJ49*Assumptions!$B$116*Assumptions!$B$117*Assumptions!$B$45
A60: SME direct paid sign-ups wanted: Nigeria | B60: workspaces | C60: =C49*(1-Assumptions!$B$116)*Assumptions!$B$118*Assumptions!$B$45 | D60: =D49*(1-Assumptions!$B$116)*Assumptions!$B$118*Assumptions!$B$45 | E60: =E49*(1-Assumptions!$B$116)*Assumptions!$B$118*Assumptions!$B$45 | F60: =F49*(1-Assumptions!$B$116)*Assumptions!$B$118*Assumptions!$B$45 | G60: =G49*(1-Assumptions!$B$116)*Assumptions!$B$118*Assumptions!$B$45 | H60: =H49*(1-Assumptions!$B$116)*Assumptions!$B$118*Assumptions!$B$45 | I60: =I49*(1-Assumptions!$B$116)*Assumptions!$B$118*Assumptions!$B$45 | J60: =J49*(1-Assumptions!$B$116)*Assumptions!$B$118*Assumptions!$B$45 | ... BJ60: =BJ49*(1-Assumptions!$B$116)*Assumptions!$B$118*Assumptions!$B$45
A61: Solo direct paid sign-ups wanted: Kenya | B61: workspaces | C61: =C50*Assumptions!$B$116*Assumptions!$B$117*Assumptions!$B$45 | D61: =D50*Assumptions!$B$116*Assumptions!$B$117*Assumptions!$B$45 | E61: =E50*Assumptions!$B$116*Assumptions!$B$117*Assumptions!$B$45 | F61: =F50*Assumptions!$B$116*Assumptions!$B$117*Assumptions!$B$45 | G61: =G50*Assumptions!$B$116*Assumptions!$B$117*Assumptions!$B$45 | H61: =H50*Assumptions!$B$116*Assumptions!$B$117*Assumptions!$B$45 | I61: =I50*Assumptions!$B$116*Assumptions!$B$117*Assumptions!$B$45 | J61: =J50*Assumptions!$B$116*Assumptions!$B$117*Assumptions!$B$45 | ... BJ61: =BJ50*Assumptions!$B$116*Assumptions!$B$117*Assumptions!$B$45
A62: SME direct paid sign-ups wanted: Kenya | B62: workspaces | C62: =C50*(1-Assumptions!$B$116)*Assumptions!$B$118*Assumptions!$B$45 | D62: =D50*(1-Assumptions!$B$116)*Assumptions!$B$118*Assumptions!$B$45 | E62: =E50*(1-Assumptions!$B$116)*Assumptions!$B$118*Assumptions!$B$45 | F62: =F50*(1-Assumptions!$B$116)*Assumptions!$B$118*Assumptions!$B$45 | G62: =G50*(1-Assumptions!$B$116)*Assumptions!$B$118*Assumptions!$B$45 | H62: =H50*(1-Assumptions!$B$116)*Assumptions!$B$118*Assumptions!$B$45 | I62: =I50*(1-Assumptions!$B$116)*Assumptions!$B$118*Assumptions!$B$45 | J62: =J50*(1-Assumptions!$B$116)*Assumptions!$B$118*Assumptions!$B$45 | ... BJ62: =BJ50*(1-Assumptions!$B$116)*Assumptions!$B$118*Assumptions!$B$45
A63: Solo direct paid sign-ups wanted: Ghana | B63: workspaces | C63: =C51*Assumptions!$B$116*Assumptions!$B$117*Assumptions!$B$45 | D63: =D51*Assumptions!$B$116*Assumptions!$B$117*Assumptions!$B$45 | E63: =E51*Assumptions!$B$116*Assumptions!$B$117*Assumptions!$B$45 | F63: =F51*Assumptions!$B$116*Assumptions!$B$117*Assumptions!$B$45 | G63: =G51*Assumptions!$B$116*Assumptions!$B$117*Assumptions!$B$45 | H63: =H51*Assumptions!$B$116*Assumptions!$B$117*Assumptions!$B$45 | I63: =I51*Assumptions!$B$116*Assumptions!$B$117*Assumptions!$B$45 | J63: =J51*Assumptions!$B$116*Assumptions!$B$117*Assumptions!$B$45 | ... BJ63: =BJ51*Assumptions!$B$116*Assumptions!$B$117*Assumptions!$B$45
A64: SME direct paid sign-ups wanted: Ghana | B64: workspaces | C64: =C51*(1-Assumptions!$B$116)*Assumptions!$B$118*Assumptions!$B$45 | D64: =D51*(1-Assumptions!$B$116)*Assumptions!$B$118*Assumptions!$B$45 | E64: =E51*(1-Assumptions!$B$116)*Assumptions!$B$118*Assumptions!$B$45 | F64: =F51*(1-Assumptions!$B$116)*Assumptions!$B$118*Assumptions!$B$45 | G64: =G51*(1-Assumptions!$B$116)*Assumptions!$B$118*Assumptions!$B$45 | H64: =H51*(1-Assumptions!$B$116)*Assumptions!$B$118*Assumptions!$B$45 | I64: =I51*(1-Assumptions!$B$116)*Assumptions!$B$118*Assumptions!$B$45 | J64: =J51*(1-Assumptions!$B$116)*Assumptions!$B$118*Assumptions!$B$45 | ... BJ64: =BJ51*(1-Assumptions!$B$116)*Assumptions!$B$118*Assumptions!$B$45
A65: Solo direct paid sign-ups wanted: Rest of Africa (USD) | B65: workspaces | C65: =C52*Assumptions!$B$116*Assumptions!$B$117*Assumptions!$B$45 | D65: =D52*Assumptions!$B$116*Assumptions!$B$117*Assumptions!$B$45 | E65: =E52*Assumptions!$B$116*Assumptions!$B$117*Assumptions!$B$45 | F65: =F52*Assumptions!$B$116*Assumptions!$B$117*Assumptions!$B$45 | G65: =G52*Assumptions!$B$116*Assumptions!$B$117*Assumptions!$B$45 | H65: =H52*Assumptions!$B$116*Assumptions!$B$117*Assumptions!$B$45 | I65: =I52*Assumptions!$B$116*Assumptions!$B$117*Assumptions!$B$45 | J65: =J52*Assumptions!$B$116*Assumptions!$B$117*Assumptions!$B$45 | ... BJ65: =BJ52*Assumptions!$B$116*Assumptions!$B$117*Assumptions!$B$45
A66: SME direct paid sign-ups wanted: Rest of Africa (USD) | B66: workspaces | C66: =C52*(1-Assumptions!$B$116)*Assumptions!$B$118*Assumptions!$B$45 | D66: =D52*(1-Assumptions!$B$116)*Assumptions!$B$118*Assumptions!$B$45 | E66: =E52*(1-Assumptions!$B$116)*Assumptions!$B$118*Assumptions!$B$45 | F66: =F52*(1-Assumptions!$B$116)*Assumptions!$B$118*Assumptions!$B$45 | G66: =G52*(1-Assumptions!$B$116)*Assumptions!$B$118*Assumptions!$B$45 | H66: =H52*(1-Assumptions!$B$116)*Assumptions!$B$118*Assumptions!$B$45 | I66: =I52*(1-Assumptions!$B$116)*Assumptions!$B$118*Assumptions!$B$45 | J66: =J52*(1-Assumptions!$B$116)*Assumptions!$B$118*Assumptions!$B$45 | ... BJ66: =BJ52*(1-Assumptions!$B$116)*Assumptions!$B$118*Assumptions!$B$45
A67: Solo direct paid sign-ups wanted: Botswana & Namibia | B67: workspaces | C67: =C53*Assumptions!$B$116*Assumptions!$B$117*Assumptions!$B$45 | D67: =D53*Assumptions!$B$116*Assumptions!$B$117*Assumptions!$B$45 | E67: =E53*Assumptions!$B$116*Assumptions!$B$117*Assumptions!$B$45 | F67: =F53*Assumptions!$B$116*Assumptions!$B$117*Assumptions!$B$45 | G67: =G53*Assumptions!$B$116*Assumptions!$B$117*Assumptions!$B$45 | H67: =H53*Assumptions!$B$116*Assumptions!$B$117*Assumptions!$B$45 | I67: =I53*Assumptions!$B$116*Assumptions!$B$117*Assumptions!$B$45 | J67: =J53*Assumptions!$B$116*Assumptions!$B$117*Assumptions!$B$45 | ... BJ67: =BJ53*Assumptions!$B$116*Assumptions!$B$117*Assumptions!$B$45
A68: SME direct paid sign-ups wanted: Botswana & Namibia | B68: workspaces | C68: =C53*(1-Assumptions!$B$116)*Assumptions!$B$118*Assumptions!$B$45 | D68: =D53*(1-Assumptions!$B$116)*Assumptions!$B$118*Assumptions!$B$45 | E68: =E53*(1-Assumptions!$B$116)*Assumptions!$B$118*Assumptions!$B$45 | F68: =F53*(1-Assumptions!$B$116)*Assumptions!$B$118*Assumptions!$B$45 | G68: =G53*(1-Assumptions!$B$116)*Assumptions!$B$118*Assumptions!$B$45 | H68: =H53*(1-Assumptions!$B$116)*Assumptions!$B$118*Assumptions!$B$45 | I68: =I53*(1-Assumptions!$B$116)*Assumptions!$B$118*Assumptions!$B$45 | J68: =J53*(1-Assumptions!$B$116)*Assumptions!$B$118*Assumptions!$B$45 | ... BJ68: =BJ53*(1-Assumptions!$B$116)*Assumptions!$B$118*Assumptions!$B$45
A70: Free plan funnel: sign-ups who don't pay join Free (60 AI credits/month); active Free users upgrade or go dormant
A71: Active Free users: South Africa: opening | B71: users | C71: =0 | D71: =C75 | E71: =D75 | F71: =E75 | G71: =F75 | H71: =G75 | I71: =H75 | J71: =I75 | K71: =J75 | ... BJ71: =BI75
A72: New Free users: South Africa | B72: users | C72: =C48*(1-Assumptions!$B$119) | D72: =D48*(1-Assumptions!$B$119) | E72: =E48*(1-Assumptions!$B$119) | F72: =F48*(1-Assumptions!$B$119) | G72: =G48*(1-Assumptions!$B$119) | H72: =H48*(1-Assumptions!$B$119) | I72: =I48*(1-Assumptions!$B$119) | J72: =J48*(1-Assumptions!$B$119) | ... BJ72: =BJ48*(1-Assumptions!$B$119)
A73: Free users upgrading to a paid plan: South Africa | B73: workspaces | C73: =C71*Assumptions!$B$120*Assumptions!$B$45 | D73: =D71*Assumptions!$B$120*Assumptions!$B$45 | E73: =E71*Assumptions!$B$120*Assumptions!$B$45 | F73: =F71*Assumptions!$B$120*Assumptions!$B$45 | G73: =G71*Assumptions!$B$120*Assumptions!$B$45 | H73: =H71*Assumptions!$B$120*Assumptions!$B$45 | I73: =I71*Assumptions!$B$120*Assumptions!$B$45 | J73: =J71*Assumptions!$B$120*Assumptions!$B$45 | ... BJ73: =BJ71*Assumptions!$B$120*Assumptions!$B$45
A74: Free users going dormant: South Africa | B74: users | C74: =C71*Assumptions!$B$121 | D74: =D71*Assumptions!$B$121 | E74: =E71*Assumptions!$B$121 | F74: =F71*Assumptions!$B$121 | G74: =G71*Assumptions!$B$121 | H74: =H71*Assumptions!$B$121 | I74: =I71*Assumptions!$B$121 | J74: =J71*Assumptions!$B$121 | ... BJ74: =BJ71*Assumptions!$B$121
A75: Active Free users: South Africa: closing | B75: users | C75: =C71+C72-C73-C74 | D75: =D71+D72-D73-D74 | E75: =E71+E72-E73-E74 | F75: =F71+F72-F73-F74 | G75: =G71+G72-G73-G74 | H75: =H71+H72-H73-H74 | I75: =I71+I72-I73-I74 | J75: =J71+J72-J73-J74 | ... BJ75: =BJ71+BJ72-BJ73-BJ74
A76: Active Free users: Nigeria: opening | B76: users | C76: =0 | D76: =C80 | E76: =D80 | F76: =E80 | G76: =F80 | H76: =G80 | I76: =H80 | J76: =I80 | K76: =J80 | ... BJ76: =BI80
A77: New Free users: Nigeria | B77: users | C77: =C49*(1-Assumptions!$B$119) | D77: =D49*(1-Assumptions!$B$119) | E77: =E49*(1-Assumptions!$B$119) | F77: =F49*(1-Assumptions!$B$119) | G77: =G49*(1-Assumptions!$B$119) | H77: =H49*(1-Assumptions!$B$119) | I77: =I49*(1-Assumptions!$B$119) | J77: =J49*(1-Assumptions!$B$119) | ... BJ77: =BJ49*(1-Assumptions!$B$119)
A78: Free users upgrading to a paid plan: Nigeria | B78: workspaces | C78: =C76*Assumptions!$B$120*Assumptions!$B$45 | D78: =D76*Assumptions!$B$120*Assumptions!$B$45 | E78: =E76*Assumptions!$B$120*Assumptions!$B$45 | F78: =F76*Assumptions!$B$120*Assumptions!$B$45 | G78: =G76*Assumptions!$B$120*Assumptions!$B$45 | H78: =H76*Assumptions!$B$120*Assumptions!$B$45 | I78: =I76*Assumptions!$B$120*Assumptions!$B$45 | J78: =J76*Assumptions!$B$120*Assumptions!$B$45 | ... BJ78: =BJ76*Assumptions!$B$120*Assumptions!$B$45
A79: Free users going dormant: Nigeria | B79: users | C79: =C76*Assumptions!$B$121 | D79: =D76*Assumptions!$B$121 | E79: =E76*Assumptions!$B$121 | F79: =F76*Assumptions!$B$121 | G79: =G76*Assumptions!$B$121 | H79: =H76*Assumptions!$B$121 | I79: =I76*Assumptions!$B$121 | J79: =J76*Assumptions!$B$121 | ... BJ79: =BJ76*Assumptions!$B$121
A80: Active Free users: Nigeria: closing | B80: users | C80: =C76+C77-C78-C79 | D80: =D76+D77-D78-D79 | E80: =E76+E77-E78-E79 | F80: =F76+F77-F78-F79 | G80: =G76+G77-G78-G79 | H80: =H76+H77-H78-H79 | I80: =I76+I77-I78-I79 | J80: =J76+J77-J78-J79 | ... BJ80: =BJ76+BJ77-BJ78-BJ79
A81: Active Free users: Kenya: opening | B81: users | C81: =0 | D81: =C85 | E81: =D85 | F81: =E85 | G81: =F85 | H81: =G85 | I81: =H85 | J81: =I85 | K81: =J85 | ... BJ81: =BI85
A82: New Free users: Kenya | B82: users | C82: =C50*(1-Assumptions!$B$119) | D82: =D50*(1-Assumptions!$B$119) | E82: =E50*(1-Assumptions!$B$119) | F82: =F50*(1-Assumptions!$B$119) | G82: =G50*(1-Assumptions!$B$119) | H82: =H50*(1-Assumptions!$B$119) | I82: =I50*(1-Assumptions!$B$119) | J82: =J50*(1-Assumptions!$B$119) | ... BJ82: =BJ50*(1-Assumptions!$B$119)
A83: Free users upgrading to a paid plan: Kenya | B83: workspaces | C83: =C81*Assumptions!$B$120*Assumptions!$B$45 | D83: =D81*Assumptions!$B$120*Assumptions!$B$45 | E83: =E81*Assumptions!$B$120*Assumptions!$B$45 | F83: =F81*Assumptions!$B$120*Assumptions!$B$45 | G83: =G81*Assumptions!$B$120*Assumptions!$B$45 | H83: =H81*Assumptions!$B$120*Assumptions!$B$45 | I83: =I81*Assumptions!$B$120*Assumptions!$B$45 | J83: =J81*Assumptions!$B$120*Assumptions!$B$45 | ... BJ83: =BJ81*Assumptions!$B$120*Assumptions!$B$45
A84: Free users going dormant: Kenya | B84: users | C84: =C81*Assumptions!$B$121 | D84: =D81*Assumptions!$B$121 | E84: =E81*Assumptions!$B$121 | F84: =F81*Assumptions!$B$121 | G84: =G81*Assumptions!$B$121 | H84: =H81*Assumptions!$B$121 | I84: =I81*Assumptions!$B$121 | J84: =J81*Assumptions!$B$121 | ... BJ84: =BJ81*Assumptions!$B$121
A85: Active Free users: Kenya: closing | B85: users | C85: =C81+C82-C83-C84 | D85: =D81+D82-D83-D84 | E85: =E81+E82-E83-E84 | F85: =F81+F82-F83-F84 | G85: =G81+G82-G83-G84 | H85: =H81+H82-H83-H84 | I85: =I81+I82-I83-I84 | J85: =J81+J82-J83-J84 | ... BJ85: =BJ81+BJ82-BJ83-BJ84
A86: Active Free users: Ghana: opening | B86: users | C86: =0 | D86: =C90 | E86: =D90 | F86: =E90 | G86: =F90 | H86: =G90 | I86: =H90 | J86: =I90 | K86: =J90 | ... BJ86: =BI90
A87: New Free users: Ghana | B87: users | C87: =C51*(1-Assumptions!$B$119) | D87: =D51*(1-Assumptions!$B$119) | E87: =E51*(1-Assumptions!$B$119) | F87: =F51*(1-Assumptions!$B$119) | G87: =G51*(1-Assumptions!$B$119) | H87: =H51*(1-Assumptions!$B$119) | I87: =I51*(1-Assumptions!$B$119) | J87: =J51*(1-Assumptions!$B$119) | ... BJ87: =BJ51*(1-Assumptions!$B$119)
A88: Free users upgrading to a paid plan: Ghana | B88: workspaces | C88: =C86*Assumptions!$B$120*Assumptions!$B$45 | D88: =D86*Assumptions!$B$120*Assumptions!$B$45 | E88: =E86*Assumptions!$B$120*Assumptions!$B$45 | F88: =F86*Assumptions!$B$120*Assumptions!$B$45 | G88: =G86*Assumptions!$B$120*Assumptions!$B$45 | H88: =H86*Assumptions!$B$120*Assumptions!$B$45 | I88: =I86*Assumptions!$B$120*Assumptions!$B$45 | J88: =J86*Assumptions!$B$120*Assumptions!$B$45 | ... BJ88: =BJ86*Assumptions!$B$120*Assumptions!$B$45
A89: Free users going dormant: Ghana | B89: users | C89: =C86*Assumptions!$B$121 | D89: =D86*Assumptions!$B$121 | E89: =E86*Assumptions!$B$121 | F89: =F86*Assumptions!$B$121 | G89: =G86*Assumptions!$B$121 | H89: =H86*Assumptions!$B$121 | I89: =I86*Assumptions!$B$121 | J89: =J86*Assumptions!$B$121 | ... BJ89: =BJ86*Assumptions!$B$121
A90: Active Free users: Ghana: closing | B90: users | C90: =C86+C87-C88-C89 | D90: =D86+D87-D88-D89 | E90: =E86+E87-E88-E89 | F90: =F86+F87-F88-F89 | G90: =G86+G87-G88-G89 | H90: =H86+H87-H88-H89 | I90: =I86+I87-I88-I89 | J90: =J86+J87-J88-J89 | ... BJ90: =BJ86+BJ87-BJ88-BJ89
A91: Active Free users: Rest of Africa (USD): opening | B91: users | C91: =0 | D91: =C95 | E91: =D95 | F91: =E95 | G91: =F95 | H91: =G95 | I91: =H95 | J91: =I95 | K91: =J95 | ... BJ91: =BI95
A92: New Free users: Rest of Africa (USD) | B92: users | C92: =C52*(1-Assumptions!$B$119) | D92: =D52*(1-Assumptions!$B$119) | E92: =E52*(1-Assumptions!$B$119) | F92: =F52*(1-Assumptions!$B$119) | G92: =G52*(1-Assumptions!$B$119) | H92: =H52*(1-Assumptions!$B$119) | I92: =I52*(1-Assumptions!$B$119) | J92: =J52*(1-Assumptions!$B$119) | ... BJ92: =BJ52*(1-Assumptions!$B$119)
A93: Free users upgrading to a paid plan: Rest of Africa (USD) | B93: workspaces | C93: =C91*Assumptions!$B$120*Assumptions!$B$45 | D93: =D91*Assumptions!$B$120*Assumptions!$B$45 | E93: =E91*Assumptions!$B$120*Assumptions!$B$45 | F93: =F91*Assumptions!$B$120*Assumptions!$B$45 | G93: =G91*Assumptions!$B$120*Assumptions!$B$45 | H93: =H91*Assumptions!$B$120*Assumptions!$B$45 | I93: =I91*Assumptions!$B$120*Assumptions!$B$45 | J93: =J91*Assumptions!$B$120*Assumptions!$B$45 | ... BJ93: =BJ91*Assumptions!$B$120*Assumptions!$B$45
A94: Free users going dormant: Rest of Africa (USD) | B94: users | C94: =C91*Assumptions!$B$121 | D94: =D91*Assumptions!$B$121 | E94: =E91*Assumptions!$B$121 | F94: =F91*Assumptions!$B$121 | G94: =G91*Assumptions!$B$121 | H94: =H91*Assumptions!$B$121 | I94: =I91*Assumptions!$B$121 | J94: =J91*Assumptions!$B$121 | ... BJ94: =BJ91*Assumptions!$B$121
A95: Active Free users: Rest of Africa (USD): closing | B95: users | C95: =C91+C92-C93-C94 | D95: =D91+D92-D93-D94 | E95: =E91+E92-E93-E94 | F95: =F91+F92-F93-F94 | G95: =G91+G92-G93-G94 | H95: =H91+H92-H93-H94 | I95: =I91+I92-I93-I94 | J95: =J91+J92-J93-J94 | ... BJ95: =BJ91+BJ92-BJ93-BJ94
A96: Active Free users: Botswana & Namibia: opening | B96: users | C96: =0 | D96: =C100 | E96: =D100 | F96: =E100 | G96: =F100 | H96: =G100 | I96: =H100 | J96: =I100 | K96: =J100 | ... BJ96: =BI100
A97: New Free users: Botswana & Namibia | B97: users | C97: =C53*(1-Assumptions!$B$119) | D97: =D53*(1-Assumptions!$B$119) | E97: =E53*(1-Assumptions!$B$119) | F97: =F53*(1-Assumptions!$B$119) | G97: =G53*(1-Assumptions!$B$119) | H97: =H53*(1-Assumptions!$B$119) | I97: =I53*(1-Assumptions!$B$119) | J97: =J53*(1-Assumptions!$B$119) | ... BJ97: =BJ53*(1-Assumptions!$B$119)
A98: Free users upgrading to a paid plan: Botswana & Namibia | B98: workspaces | C98: =C96*Assumptions!$B$120*Assumptions!$B$45 | D98: =D96*Assumptions!$B$120*Assumptions!$B$45 | E98: =E96*Assumptions!$B$120*Assumptions!$B$45 | F98: =F96*Assumptions!$B$120*Assumptions!$B$45 | G98: =G96*Assumptions!$B$120*Assumptions!$B$45 | H98: =H96*Assumptions!$B$120*Assumptions!$B$45 | I98: =I96*Assumptions!$B$120*Assumptions!$B$45 | J98: =J96*Assumptions!$B$120*Assumptions!$B$45 | ... BJ98: =BJ96*Assumptions!$B$120*Assumptions!$B$45
A99: Free users going dormant: Botswana & Namibia | B99: users | C99: =C96*Assumptions!$B$121 | D99: =D96*Assumptions!$B$121 | E99: =E96*Assumptions!$B$121 | F99: =F96*Assumptions!$B$121 | G99: =G96*Assumptions!$B$121 | H99: =H96*Assumptions!$B$121 | I99: =I96*Assumptions!$B$121 | J99: =J96*Assumptions!$B$121 | ... BJ99: =BJ96*Assumptions!$B$121
A100: Active Free users: Botswana & Namibia: closing | B100: users | C100: =C96+C97-C98-C99 | D100: =D96+D97-D98-D99 | E100: =E96+E97-E98-E99 | F100: =F96+F97-F98-F99 | G100: =G96+G97-G98-G99 | H100: =H96+H97-H98-H99 | I100: =I96+I97-I98-I99 | J100: =J96+J97-J98-J99 | ... BJ100: =BJ96+BJ97-BJ98-BJ99
A101: Active Free users: all markets | B101: users | C101: =C75+C80+C85+C90+C95+C100 | D101: =D75+D80+D85+D90+D95+D100 | E101: =E75+E80+E85+E90+E95+E100 | F101: =F75+F80+F85+F90+F95+F100 | G101: =G75+G80+G85+G90+G95+G100 | H101: =H75+H80+H85+H90+H95+H100 | I101: =I75+I80+I85+I90+I95+I100 | J101: =J75+J80+J85+J90+J95+J100 | ... BJ101: =BJ75+BJ80+BJ85+BJ90+BJ95+BJ100
A102: New Free users: all markets | B102: users | C102: =C72+C77+C82+C87+C92+C97 | D102: =D72+D77+D82+D87+D92+D97 | E102: =E72+E77+E82+E87+E92+E97 | F102: =F72+F77+F82+F87+F92+F97 | G102: =G72+G77+G82+G87+G92+G97 | H102: =H72+H77+H82+H87+H92+H97 | I102: =I72+I77+I82+I87+I92+I97 | J102: =J72+J77+J82+J87+J92+J97 | ... BJ102: =BJ72+BJ77+BJ82+BJ87+BJ92+BJ97
A103: Free users upgrading to paid: all markets | B103: workspaces | C103: =C73+C78+C83+C88+C93+C98 | D103: =D73+D78+D83+D88+D93+D98 | E103: =E73+E78+E83+E88+E93+E98 | F103: =F73+F78+F83+F88+F93+F98 | G103: =G73+G78+G83+G88+G93+G98 | H103: =H73+H78+H83+H88+H93+H98 | I103: =I73+I78+I83+I88+I93+I98 | J103: =J73+J78+J83+J88+J93+J98 | ... BJ103: =BJ73+BJ78+BJ83+BJ88+BJ93+BJ98
A105: COST DISCIPLINE: paid acquisition budget = MIN(desired, floor + cap % x last month's MRR); zero before the seed
A106: Share of sign-ups needing paid acquisition | B106: % | C106: =CHOOSE(C$5,Assumptions!$B$111,Assumptions!$B$112,Assumptions!$B$113,Assumptions!$B$114,Assumptions!$B$115) | D106: =CHOOSE(D$5,Assumptions!$B$111,Assumptions!$B$112,Assumptions!$B$113,Assumptions!$B$114,Assumptions!$B$115) | E106: =CHOOSE(E$5,Assumptions!$B$111,Assumptions!$B$112,Assumptions!$B$113,Assumptions!$B$114,Assumptions!$B$115) | F106: =CHOOSE(F$5,Assumptions!$B$111,Assumptions!$B$112,Assumptions!$B$113,Assumptions!$B$114,Assumptions!$B$115) | G106: =CHOOSE(G$5,Assumptions!$B$111,Assumptions!$B$112,Assumptions!$B$113,Assumptions!$B$114,Assumptions!$B$115) | H106: =CHOOSE(H$5,Assumptions!$B$111,Assumptions!$B$112,Assumptions!$B$113,Assumptions!$B$114,Assumptions!$B$115) | I106: =CHOOSE(I$5,Assumptions!$B$111,Assumptions!$B$112,Assumptions!$B$113,Assumptions!$B$114,Assumptions!$B$115) | J106: =CHOOSE(J$5,Assumptions!$B$111,Assumptions!$B$112,Assumptions!$B$113,Assumptions!$B$114,Assumptions!$B$115) | ... BJ106: =CHOOSE(BJ$5,Assumptions!$B$111,Assumptions!$B$112,Assumptions!$B$113,Assumptions!$B$114,Assumptions!$B$115)
A107: CAC inflation factor | B107: x | C107: =(1+Assumptions!$B$194)^(C$5-1) | D107: =(1+Assumptions!$B$194)^(D$5-1) | E107: =(1+Assumptions!$B$194)^(E$5-1) | F107: =(1+Assumptions!$B$194)^(F$5-1) | G107: =(1+Assumptions!$B$194)^(G$5-1) | H107: =(1+Assumptions!$B$194)^(H$5-1) | I107: =(1+Assumptions!$B$194)^(I$5-1) | J107: =(1+Assumptions!$B$194)^(J$5-1) | ... BJ107: =(1+Assumptions!$B$194)^(BJ$5-1)
...

Sheet Costs
A1: Costs
A2: Monthly MRR-gated headcount plan, COGS (incl. Free plan AI cost) and operating expenses (lean pre-seed mode until the seed lands).
A3: Month # | B3: Unit | C3: 1 | D3: 2 | E3: 3 | F3: 4 | G3: 5 | H3: 6 | I3: 7 | J3: 8 | K3: 9 | L3: 10 | M3: 11 | N3: 12 | O3: 13 | P3: 14 | Q3: 15 | R3: 16 | S3: 17 | T3: 18 | U3: 19 | V3: 20 | W3: 21 | X3: 22 | Y3: 23 | Z3: 24 | AA3: 25 | AB3: 26 | AC3: 27 | AD3: 28 | AE3: 29 | AF3: 30 | AG3: 31 | AH3: 32 | AI3: 33 | AJ3: 34 | AK3: 35 | AL3: 36 | AM3: 37 | AN3: 38 | AO3: 39 | AP3: 40 | AQ3: 41 | AR3: 42 | AS3: 43 | AT3: 44 | AU3: 45 | AV3: 46 | AW3: 47 | AX3: 48 | AY3: 49 | AZ3: 50 | BA3: 51 | BB3: 52 | BC3: 53 | BD3: 54 | BE3: 55 | BF3: 56 | BG3: 57 | BH3: 58 | BI3: 59 | BJ3: 60
A4: Month | C4: Oct 2026 | D4: Nov 2026 | E4: Dec 2026 | F4: Jan 2027 | G4: Feb 2027 | H4: Mar 2027 | I4: Apr 2027 | J4: May 2027 | K4: Jun 2027 | L4: Jul 2027 | M4: Aug 2027 | N4: Sep 2027 | O4: Oct 2027 | P4: Nov 2027 | Q4: Dec 2027 | R4: Jan 2028 | S4: Feb 2028 | T4: Mar 2028 | U4: Apr 2028 | V4: May 2028 | W4: Jun 2028 | X4: Jul 2028 | Y4: Aug 2028 | Z4: Sep 2028 | AA4: Oct 2028 | AB4: Nov 2028 | AC4: Dec 2028 | AD4: Jan 2029 | AE4: Feb 2029 | AF4: Mar 2029 | AG4: Apr 2029 | AH4: May 2029 | AI4: Jun 2029 | AJ4: Jul 2029 | AK4: Aug 2029 | AL4: Sep 2029 | AM4: Oct 2029 | AN4: Nov 2029 | AO4: Dec 2029 | AP4: Jan 2030 | AQ4: Feb 2030 | AR4: Mar 2030 | AS4: Apr 2030 | AT4: May 2030 | AU4: Jun 2030 | AV4: Jul 2030 | AW4: Aug 2030 | AX4: Sep 2030 | AY4: Oct 2030 | AZ4: Nov 2030 | BA4: Dec 2030 | BB4: Jan 2031 | BC4: Feb 2031 | BD4: Mar 2031 | BE4: Apr 2031 | BF4: May 2031 | BG4: Jun 2031 | BH4: Jul 2031 | BI4: Aug 2031 | BJ4: Sep 2031
A5: Fiscal year (Oct-Sep) | C5: 1 | D5: 1 | E5: 1 | F5: 1 | G5: 1 | H5: 1 | I5: 1 | J5: 1 | K5: 1 | L5: 1 | M5: 1 | N5: 1 | O5: 2 | P5: 2 | Q5: 2 | R5: 2 | S5: 2 | T5: 2 | U5: 2 | V5: 2 | W5: 2 | X5: 2 | Y5: 2 | Z5: 2 | AA5: 3 | AB5: 3 | AC5: 3 | AD5: 3 | AE5: 3 | AF5: 3 | AG5: 3 | AH5: 3 | AI5: 3 | AJ5: 3 | AK5: 3 | AL5: 3 | AM5: 4 | AN5: 4 | AO5: 4 | AP5: 4 | AQ5: 4 | AR5: 4 | AS5: 4 | AT5: 4 | AU5: 4 | AV5: 4 | AW5: 4 | AX5: 4 | AY5: 5 | AZ5: 5 | BA5: 5 | BB5: 5 | BC5: 5 | BD5: 5 | BE5: 5 | BF5: 5 | BG5: 5 | BH5: 5 | BI5: 5 | BJ5: 5
A7: Headcount: FTEs by role. Non-founder roles need month >= earliest hire, the seed, and last month's MRR >= gate x multiplier
A8: Founder & CEO (reduced salary) | B8: FTE | C8: =IF(C$3>=Assumptions!$E$223,Assumptions!$D$223,0) | D8: =IF(D$3>=Assumptions!$E$223,Assumptions!$D$223,0) | E8: =IF(E$3>=Assumptions!$E$223,Assumptions!$D$223,0) | F8: =IF(F$3>=Assumptions!$E$223,Assumptions!$D$223,0) | G8: =IF(G$3>=Assumptions!$E$223,Assumptions!$D$223,0) | H8: =IF(H$3>=Assumptions!$E$223,Assumptions!$D$223,0) | I8: =IF(I$3>=Assumptions!$E$223,Assumptions!$D$223,0) | J8: =IF(J$3>=Assumptions!$E$223,Assumptions!$D$223,0) | ... BJ8: =IF(BJ$3>=Assumptions!$E$223,Assumptions!$D$223,0)
A9: CTO / founding engineer (reduced salary) | B9: FTE | C9: =IF(C$3>=Assumptions!$E$224,Assumptions!$D$224,0) | D9: =IF(D$3>=Assumptions!$E$224,Assumptions!$D$224,0) | E9: =IF(E$3>=Assumptions!$E$224,Assumptions!$D$224,0) | F9: =IF(F$3>=Assumptions!$E$224,Assumptions!$D$224,0) | G9: =IF(G$3>=Assumptions!$E$224,Assumptions!$D$224,0) | H9: =IF(H$3>=Assumptions!$E$224,Assumptions!$D$224,0) | I9: =IF(I$3>=Assumptions!$E$224,Assumptions!$D$224,0) | J9: =IF(J$3>=Assumptions!$E$224,Assumptions!$D$224,0) | ... BJ9: =IF(BJ$3>=Assumptions!$E$224,Assumptions!$D$224,0)
A10: Senior full-stack engineers | B10: FTE | C10: =IF(AND(C$3>=Assumptions!$E$225,C$3>=Assumptions!$B$14,Revenue_Build!C10>=Assumptions!$F$225*Assumptions!$B$51),Assumptions!$D$225,0) | D10: =IF(OR(C10>0,AND(D$3>=Assumptions!$E$225,D$3>=Assumptions!$B$14,Revenue_Build!D10>=Assumptions!$F$225*Assumptions!$B$51)),Assumptions!$D$225,0) | E10: =IF(OR(D10>0,AND(E$3>=Assumptions!$E$225,E$3>=Assumptions!$B$14,Revenue_Build!E10>=Assumptions!$F$225*Assumptions!$B$51)),Assumptions!$D$225,0) | F10: =IF(OR(E10>0,AND(F$3>=Assumptions!$E$225,F$3>=Assumptions!$B$14,Revenue_Build!F10>=Assumptions!$F$225*Assumptions!$B$51)),Assumptions!$D$225,0) | G10: =IF(OR(F10>0,AND(G$3>=Assumptions!$E$225,G$3>=Assumptions!$B$14,Revenue_Build!G10>=Assumptions!$F$225*Assumptions!$B$51)),Assumptions!$D$225,0) | H10: =IF(OR(G10>0,AND(H$3>=Assumptions!$E$225,H$3>=Assumptions!$B$14,Revenue_Build!H10>=Assumptions!$F$225*Assumptions!$B$51)),Assumptions!$D$225,0) | I10: =IF(OR(H10>0,AND(I$3>=Assumptions!$E$225,I$3>=Assumptions!$B$14,Revenue_Build!I10>=Assumptions!$F$225*Assumptions!$B$51)),Assumptions!$D$225,0) | J10: =IF(OR(I10>0,AND(J$3>=Assumptions!$E$225,J$3>=Assumptions!$B$14,Revenue_Build!J10>=Assumptions!$F$225*Assumptions!$B$51)),Assumptions!$D$225,0) | K10: =IF(OR(J10>0,AND(K$3>=Assumptions!$E$225,K$3>=Assumptions!$B$14,Revenue_Build!K10>=Assumptions!$F$225*Assumptions!$B$51)),Assumptions!$D$225,0) | ... BJ10: =IF(OR(BI10>0,AND(BJ$3>=Assumptions!$E$225,BJ$3>=Assumptions!$B$14,Revenue_Build!BJ10>=Assumptions!$F$225*Assumptions!$B$51)),Assumptions!$D$225,0)
A11: AI / ML engineer | B11: FTE | C11: =IF(AND(C$3>=Assumptions!$E$226,C$3>=Assumptions!$B$14,Revenue_Build!C10>=Assumptions!$F$226*Assumptions!$B$51),Assumptions!$D$226,0) | D11: =IF(OR(C11>0,AND(D$3>=Assumptions!$E$226,D$3>=Assumptions!$B$14,Revenue_Build!D10>=Assumptions!$F$226*Assumptions!$B$51)),Assumptions!$D$226,0) | E11: =IF(OR(D11>0,AND(E$3>=Assumptions!$E$226,E$3>=Assumptions!$B$14,Revenue_Build!E10>=Assumptions!$F$226*Assumptions!$B$51)),Assumptions!$D$226,0) | F11: =IF(OR(E11>0,AND(F$3>=Assumptions!$E$226,F$3>=Assumptions!$B$14,Revenue_Build!F10>=Assumptions!$F$226*Assumptions!$B$51)),Assumptions!$D$226,0) | G11: =IF(OR(F11>0,AND(G$3>=Assumptions!$E$226,G$3>=Assumptions!$B$14,Revenue_Build!G10>=Assumptions!$F$226*Assumptions!$B$51)),Assumptions!$D$226,0) | H11: =IF(OR(G11>0,AND(H$3>=Assumptions!$E$226,H$3>=Assumptions!$B$14,Revenue_Build!H10>=Assumptions!$F$226*Assumptions!$B$51)),Assumptions!$D$226,0) | I11: =IF(OR(H11>0,AND(I$3>=Assumptions!$E$226,I$3>=Assumptions!$B$14,Revenue_Build!I10>=Assumptions!$F$226*Assumptions!$B$51)),Assumptions!$D$226,0) | J11: =IF(OR(I11>0,AND(J$3>=Assumptions!$E$226,J$3>=Assumptions!$B$14,Revenue_Build!J10>=Assumptions!$F$226*Assumptions!$B$51)),Assumptions!$D$226,0) | K11: =IF(OR(J11>0,AND(K$3>=Assumptions!$E$226,K$3>=Assumptions!$B$14,Revenue_Build!K10>=Assumptions!$F$226*Assumptions!$B$51)),Assumptions!$D$226,0) | ... BJ11: =IF(OR(BI11>0,AND(BJ$3>=Assumptions!$E$226,BJ$3>=Assumptions!$B$14,Revenue_Build!BJ10>=Assumptions!$F$226*Assumptions!$B$51)),Assumptions!$D$226,0)
A12: Product designer (UX) | B12: FTE | C12: =IF(AND(C$3>=Assumptions!$E$227,C$3>=Assumptions!$B$14,Revenue_Build!C10>=Assumptions!$F$227*Assumptions!$B$51),Assumptions!$D$227,0) | D12: =IF(OR(C12>0,AND(D$3>=Assumptions!$E$227,D$3>=Assumptions!$B$14,Revenue_Build!D10>=Assumptions!$F$227*Assumptions!$B$51)),Assumptions!$D$227,0) | E12: =IF(OR(D12>0,AND(E$3>=Assumptions!$E$227,E$3>=Assumptions!$B$14,Revenue_Build!E10>=Assumptions!$F$227*Assumptions!$B$51)),Assumptions!$D$227,0) | F12: =IF(OR(E12>0,AND(F$3>=Assumptions!$E$227,F$3>=Assumptions!$B$14,Revenue_Build!F10>=Assumptions!$F$227*Assumptions!$B$51)),Assumptions!$D$227,0) | G12: =IF(OR(F12>0,AND(G$3>=Assumptions!$E$227,G$3>=Assumptions!$B$14,Revenue_Build!G10>=Assumptions!$F$227*Assumptions!$B$51)),Assumptions!$D$227,0) | H12: =IF(OR(G12>0,AND(H$3>=Assumptions!$E$227,H$3>=Assumptions!$B$14,Revenue_Build!H10>=Assumptions!$F$227*Assumptions!$B$51)),Assumptions!$D$227,0) | I12: =IF(OR(H12>0,AND(I$3>=Assumptions!$E$227,I$3>=Assumptions!$B$14,Revenue_Build!I10>=Assumptions!$F$227*Assumptions!$B$51)),Assumptions!$D$227,0) | J12: =IF(OR(I12>0,AND(J$3>=Assumptions!$E$227,J$3>=Assumptions!$B$14,Revenue_Build!J10>=Assumptions!$F$227*Assumptions!$B$51)),Assumptions!$D$227,0) | K12: =IF(OR(J12>0,AND(K$3>=Assumptions!$E$227,K$3>=Assumptions!$B$14,Revenue_Build!K10>=Assumptions!$F$227*Assumptions!$B$51)),Assumptions!$D$227,0) | ... BJ12: =IF(OR(BI12>0,AND(BJ$3>=Assumptions!$E$227,BJ$3>=Assumptions!$B$14,Revenue_Build!BJ10>=Assumptions!$F$227*Assumptions!$B$51)),Assumptions!$D$227,0)
A13: Full-stack engineers | B13: FTE | C13: =IF(AND(C$3>=Assumptions!$E$228,C$3>=Assumptions!$B$14,Revenue_Build!C10>=Assumptions!$F$228*Assumptions!$B$51),Assumptions!$D$228,0) | D13: =IF(OR(C13>0,AND(D$3>=Assumptions!$E$228,D$3>=Assumptions!$B$14,Revenue_Build!D10>=Assumptions!$F$228*Assumptions!$B$51)),Assumptions!$D$228,0) | E13: =IF(OR(D13>0,AND(E$3>=Assumptions!$E$228,E$3>=Assumptions!$B$14,Revenue_Build!E10>=Assumptions!$F$228*Assumptions!$B$51)),Assumptions!$D$228,0) | F13: =IF(OR(E13>0,AND(F$3>=Assumptions!$E$228,F$3>=Assumptions!$B$14,Revenue_Build!F10>=Assumptions!$F$228*Assumptions!$B$51)),Assumptions!$D$228,0) | G13: =IF(OR(F13>0,AND(G$3>=Assumptions!$E$228,G$3>=Assumptions!$B$14,Revenue_Build!G10>=Assumptions!$F$228*Assumptions!$B$51)),Assumptions!$D$228,0) | H13: =IF(OR(G13>0,AND(H$3>=Assumptions!$E$228,H$3>=Assumptions!$B$14,Revenue_Build!H10>=Assumptions!$F$228*Assumptions!$B$51)),Assumptions!$D$228,0) | I13: =IF(OR(H13>0,AND(I$3>=Assumptions!$E$228,I$3>=Assumptions!$B$14,Revenue_Build!I10>=Assumptions!$F$228*Assumptions!$B$51)),Assumptions!$D$228,0) | J13: =IF(OR(I13>0,AND(J$3>=Assumptions!$E$228,J$3>=Assumptions!$B$14,Revenue_Build!J10>=Assumptions!$F$228*Assumptions!$B$51)),Assumptions!$D$228,0) | K13: =IF(OR(J13>0,AND(K$3>=Assumptions!$E$228,K$3>=Assumptions!$B$14,Revenue_Build!K10>=Assumptions!$F$228*Assumptions!$B$51)),Assumptions!$D$228,0) | ... BJ13: =IF(OR(BI13>0,AND(BJ$3>=Assumptions!$E$228,BJ$3>=Assumptions!$B$14,Revenue_Build!BJ10>=Assumptions!$F$228*Assumptions!$B$51)),Assumptions!$D$228,0)
A14: DevOps / QA engineer | B14: FTE | C14: =IF(AND(C$3>=Assumptions!$E$229,C$3>=Assumptions!$B$14,Revenue_Build!C10>=Assumptions!$F$229*Assumptions!$B$51),Assumptions!$D$229,0) | D14: =IF(OR(C14>0,AND(D$3>=Assumptions!$E$229,D$3>=Assumptions!$B$14,Revenue_Build!D10>=Assumptions!$F$229*Assumptions!$B$51)),Assumptions!$D$229,0) | E14: =IF(OR(D14>0,AND(E$3>=Assumptions!$E$229,E$3>=Assumptions!$B$14,Revenue_Build!E10>=Assumptions!$F$229*Assumptions!$B$51)),Assumptions!$D$229,0) | F14: =IF(OR(E14>0,AND(F$3>=Assumptions!$E$229,F$3>=Assumptions!$B$14,Revenue_Build!F10>=Assumptions!$F$229*Assumptions!$B$51)),Assumptions!$D$229,0) | G14: =IF(OR(F14>0,AND(G$3>=Assumptions!$E$229,G$3>=Assumptions!$B$14,Revenue_Build!G10>=Assumptions!$F$229*Assumptions!$B$51)),Assumptions!$D$229,0) | H14: =IF(OR(G14>0,AND(H$3>=Assumptions!$E$229,H$3>=Assumptions!$B$14,Revenue_Build!H10>=Assumptions!$F$229*Assumptions!$B$51)),Assumptions!$D$229,0) | I14: =IF(OR(H14>0,AND(I$3>=Assumptions!$E$229,I$3>=Assumptions!$B$14,Revenue_Build!I10>=Assumptions!$F$229*Assumptions!$B$51)),Assumptions!$D$229,0) | J14: =IF(OR(I14>0,AND(J$3>=Assumptions!$E$229,J$3>=Assumptions!$B$14,Revenue_Build!J10>=Assumptions!$F$229*Assumptions!$B$51)),Assumptions!$D$229,0) | K14: =IF(OR(J14>0,AND(K$3>=Assumptions!$E$229,K$3>=Assumptions!$B$14,Revenue_Build!K10>=Assumptions!$F$229*Assumptions!$B$51)),Assumptions!$D$229,0) | ... BJ14: =IF(OR(BI14>0,AND(BJ$3>=Assumptions!$E$229,BJ$3>=Assumptions!$B$14,Revenue_Build!BJ10>=Assumptions!$F$229*Assumptions!$B$51)),Assumptions!$D$229,0)
A15: Integrations engineers (social adapters, commerce, CRM) | B15: FTE | C15: =IF(AND(C$3>=Assumptions!$E$230,C$3>=Assumptions!$B$14,Revenue_Build!C10>=Assumptions!$F$230*Assumptions!$B$51),Assumptions!$D$230,0) | D15: =IF(OR(C15>0,AND(D$3>=Assumptions!$E$230,D$3>=Assumptions!$B$14,Revenue_Build!D10>=Assumptions!$F$230*Assumptions!$B$51)),Assumptions!$D$230,0) | E15: =IF(OR(D15>0,AND(E$3>=Assumptions!$E$230,E$3>=Assumptions!$B$14,Revenue_Build!E10>=Assumptions!$F$230*Assumptions!$B$51)),Assumptions!$D$230,0) | F15: =IF(OR(E15>0,AND(F$3>=Assumptions!$E$230,F$3>=Assumptions!$B$14,Revenue_Build!F10>=Assumptions!$F$230*Assumptions!$B$51)),Assumptions!$D$230,0) | G15: =IF(OR(F15>0,AND(G$3>=Assumptions!$E$230,G$3>=Assumptions!$B$14,Revenue_Build!G10>=Assumptions!$F$230*Assumptions!$B$51)),Assumptions!$D$230,0) | H15: =IF(OR(G15>0,AND(H$3>=Assumptions!$E$230,H$3>=Assumptions!$B$14,Revenue_Build!H10>=Assumptions!$F$230*Assumptions!$B$51)),Assumptions!$D$230,0) | I15: =IF(OR(H15>0,AND(I$3>=Assumptions!$E$230,I$3>=Assumptions!$B$14,Revenue_Build!I10>=Assumptions!$F$230*Assumptions!$B$51)),Assumptions!$D$230,0) | J15: =IF(OR(I15>0,AND(J$3>=Assumptions!$E$230,J$3>=Assumptions!$B$14,Revenue_Build!J10>=Assumptions!$F$230*Assumptions!$B$51)),Assumptions!$D$230,0) | K15: =IF(OR(J15>0,AND(K$3>=Assumptions!$E$230,K$3>=Assumptions!$B$14,Revenue_Build!K10>=Assumptions!$F$230*Assumptions!$B$51)),Assumptions!$D$230,0) | ... BJ15: =IF(OR(BI15>0,AND(BJ$3>=Assumptions!$E$230,BJ$3>=Assumptions!$B$14,Revenue_Build!BJ10>=Assumptions!$F$230*Assumptions!$B$51)),Assumptions!$D$230,0)
A16: Product manager | B16: FTE | C16: =IF(AND(C$3>=Assumptions!$E$231,C$3>=Assumptions!$B$14,Revenue_Build!C10>=Assumptions!$F$231*Assumptions!$B$51),Assumptions!$D$231,0) | D16: =IF(OR(C16>0,AND(D$3>=Assumptions!$E$231,D$3>=Assumptions!$B$14,Revenue_Build!D10>=Assumptions!$F$231*Assumptions!$B$51)),Assumptions!$D$231,0) | E16: =IF(OR(D16>0,AND(E$3>=Assumptions!$E$231,E$3>=Assumptions!$B$14,Revenue_Build!E10>=Assumptions!$F$231*Assumptions!$B$51)),Assumptions!$D$231,0) | F16: =IF(OR(E16>0,AND(F$3>=Assumptions!$E$231,F$3>=Assumptions!$B$14,Revenue_Build!F10>=Assumptions!$F$231*Assumptions!$B$51)),Assumptions!$D$231,0) | G16: =IF(OR(F16>0,AND(G$3>=Assumptions!$E$231,G$3>=Assumptions!$B$14,Revenue_Build!G10>=Assumptions!$F$231*Assumptions!$B$51)),Assumptions!$D$231,0) | H16: =IF(OR(G16>0,AND(H$3>=Assumptions!$E$231,H$3>=Assumptions!$B$14,Revenue_Build!H10>=Assumptions!$F$231*Assumptions!$B$51)),Assumptions!$D$231,0) | I16: =IF(OR(H16>0,AND(I$3>=Assumptions!$E$231,I$3>=Assumptions!$B$14,Revenue_Build!I10>=Assumptions!$F$231*Assumptions!$B$51)),Assumptions!$D$231,0) | J16: =IF(OR(I16>0,AND(J$3>=Assumptions!$E$231,J$3>=Assumptions!$B$14,Revenue_Build!J10>=Assumptions!$F$231*Assumptions!$B$51)),Assumptions!$D$231,0) | K16: =IF(OR(J16>0,AND(K$3>=Assumptions!$E$231,K$3>=Assumptions!$B$14,Revenue_Build!K10>=Assumptions!$F$231*Assumptions!$B$51)),Assumptions!$D$231,0) | ... BJ16: =IF(OR(BI16>0,AND(BJ$3>=Assumptions!$E$231,BJ$3>=Assumptions!$B$14,Revenue_Build!BJ10>=Assumptions!$F$231*Assumptions!$B$51)),Assumptions!$D$231,0)
A17: Security & compliance engineer | B17: FTE | C17: =IF(AND(C$3>=Assumptions!$E$232,C$3>=Assumptions!$B$14,Revenue_Build!C10>=Assumptions!$F$232*Assumptions!$B$51),Assumptions!$D$232,0) | D17: =IF(OR(C17>0,AND(D$3>=Assumptions!$E$232,D$3>=Assumptions!$B$14,Revenue_Build!D10>=Assumptions!$F$232*Assumptions!$B$51)),Assumptions!$D$232,0) | E17: =IF(OR(D17>0,AND(E$3>=Assumptions!$E$232,E$3>=Assumptions!$B$14,Revenue_Build!E10>=Assumptions!$F$232*Assumptions!$B$51)),Assumptions!$D$232,0) | F17: =IF(OR(E17>0,AND(F$3>=Assumptions!$E$232,F$3>=Assumptions!$B$14,Revenue_Build!F10>=Assumptions!$F$232*Assumptions!$B$51)),Assumptions!$D$232,0) | G17: =IF(OR(F17>0,AND(G$3>=Assumptions!$E$232,G$3>=Assumptions!$B$14,Revenue_Build!G10>=Assumptions!$F$232*Assumptions!$B$51)),Assumptions!$D$232,0) | H17: =IF(OR(G17>0,AND(H$3>=Assumptions!$E$232,H$3>=Assumptions!$B$14,Revenue_Build!H10>=Assumptions!$F$232*Assumptions!$B$51)),Assumptions!$D$232,0) | I17: =IF(OR(H17>0,AND(I$3>=Assumptions!$E$232,I$3>=Assumptions!$B$14,Revenue_Build!I10>=Assumptions!$F$232*Assumptions!$B$51)),Assumptions!$D$232,0) | J17: =IF(OR(I17>0,AND(J$3>=Assumptions!$E$232,J$3>=Assumptions!$B$14,Revenue_Build!J10>=Assumptions!$F$232*Assumptions!$B$51)),Assumptions!$D$232,0) | K17: =IF(OR(J17>0,AND(K$3>=Assumptions!$E$232,K$3>=Assumptions!$B$14,Revenue_Build!K10>=Assumptions!$F$232*Assumptions!$B$51)),Assumptions!$D$232,0) | ... BJ17: =IF(OR(BI17>0,AND(BJ$3>=Assumptions!$E$232,BJ$3>=Assumptions!$B$14,Revenue_Build!BJ10>=Assumptions!$F$232*Assumptions!$B$51)),Assumptions!$D$232,0)
A18: Payments & data engineers | B18: FTE | C18: =IF(AND(C$3>=Assumptions!$E$233,C$3>=Assumptions!$B$14,Revenue_Build!C10>=Assumptions!$F$233*Assumptions!$B$51),Assumptions!$D$233,0) | D18: =IF(OR(C18>0,AND(D$3>=Assumptions!$E$233,D$3>=Assumptions!$B$14,Revenue_Build!D10>=Assumptions!$F$233*Assumptions!$B$51)),Assumptions!$D$233,0) | E18: =IF(OR(D18>0,AND(E$3>=Assumptions!$E$233,E$3>=Assumptions!$B$14,Revenue_Build!E10>=Assumptions!$F$233*Assumptions!$B$51)),Assumptions!$D$233,0) | F18: =IF(OR(E18>0,AND(F$3>=Assumptions!$E$233,F$3>=Assumptions!$B$14,Revenue_Build!F10>=Assumptions!$F$233*Assumptions!$B$51)),Assumptions!$D$233,0) | G18: =IF(OR(F18>0,AND(G$3>=Assumptions!$E$233,G$3>=Assumptions!$B$14,Revenue_Build!G10>=Assumptions!$F$233*Assumptions!$B$51)),Assumptions!$D$233,0) | H18: =IF(OR(G18>0,AND(H$3>=Assumptions!$E$233,H$3>=Assumptions!$B$14,Revenue_Build!H10>=Assumptions!$F$233*Assumptions!$B$51)),Assumptions!$D$233,0) | I18: =IF(OR(H18>0,AND(I$3>=Assumptions!$E$233,I$3>=Assumptions!$B$14,Revenue_Build!I10>=Assumptions!$F$233*Assumptions!$B$51)),Assumptions!$D$233,0) | J18: =IF(OR(I18>0,AND(J$3>=Assumptions!$E$233,J$3>=Assumptions!$B$14,Revenue_Build!J10>=Assumptions!$F$233*Assumptions!$B$51)),Assumptions!$D$233,0) | K18: =IF(OR(J18>0,AND(K$3>=Assumptions!$E$233,K$3>=Assumptions!$B$14,Revenue_Build!K10>=Assumptions!$F$233*Assumptions!$B$51)),Assumptions!$D$233,0) | ... BJ18: =IF(OR(BI18>0,AND(BJ$3>=Assumptions!$E$233,BJ$3>=Assumptions!$B$14,Revenue_Build!BJ10>=Assumptions!$F$233*Assumptions!$B$51)),Assumptions!$D$233,0)
A19: Engineers (scale-up I) | B19: FTE | C19: =IF(AND(C$3>=Assumptions!$E$234,C$3>=Assumptions!$B$14,Revenue_Build!C10>=Assumptions!$F$234*Assumptions!$B$51),Assumptions!$D$234,0) | D19: =IF(OR(C19>0,AND(D$3>=Assumptions!$E$234,D$3>=Assumptions!$B$14,Revenue_Build!D10>=Assumptions!$F$234*Assumptions!$B$51)),Assumptions!$D$234,0) | E19: =IF(OR(D19>0,AND(E$3>=Assumptions!$E$234,E$3>=Assumptions!$B$14,Revenue_Build!E10>=Assumptions!$F$234*Assumptions!$B$51)),Assumptions!$D$234,0) | F19: =IF(OR(E19>0,AND(F$3>=Assumptions!$E$234,F$3>=Assumptions!$B$14,Revenue_Build!F10>=Assumptions!$F$234*Assumptions!$B$51)),Assumptions!$D$234,0) | G19: =IF(OR(F19>0,AND(G$3>=Assumptions!$E$234,G$3>=Assumptions!$B$14,Revenue_Build!G10>=Assumptions!$F$234*Assumptions!$B$51)),Assumptions!$D$234,0) | H19: =IF(OR(G19>0,AND(H$3>=Assumptions!$E$234,H$3>=Assumptions!$B$14,Revenue_Build!H10>=Assumptions!$F$234*Assumptions!$B$51)),Assumptions!$D$234,0) | I19: =IF(OR(H19>0,AND(I$3>=Assumptions!$E$234,I$3>=Assumptions!$B$14,Revenue_Build!I10>=Assumptions!$F$234*Assumptions!$B$51)),Assumptions!$D$234,0) | J19: =IF(OR(I19>0,AND(J$3>=Assumptions!$E$234,J$3>=Assumptions!$B$14,Revenue_Build!J10>=Assumptions!$F$234*Assumptions!$B$51)),Assumptions!$D$234,0) | K19: =IF(OR(J19>0,AND(K$3>=Assumptions!$E$234,K$3>=Assumptions!$B$14,Revenue_Build!K10>=Assumptions!$F$234*Assumptions!$B$51)),Assumptions!$D$234,0) | ... BJ19: =IF(OR(BI19>0,AND(BJ$3>=Assumptions!$E$234,BJ$3>=Assumptions!$B$14,Revenue_Build!BJ10>=Assumptions!$F$234*Assumptions!$B$51)),Assumptions!$D$234,0)
A20: VP Engineering | B20: FTE | C20: =IF(AND(C$3>=Assumptions!$E$235,C$3>=Assumptions!$B$14,Revenue_Build!C10>=Assumptions!$F$235*Assumptions!$B$51),Assumptions!$D$235,0) | D20: =IF(OR(C20>0,AND(D$3>=Assumptions!$E$235,D$3>=Assumptions!$B$14,Revenue_Build!D10>=Assumptions!$F$235*Assumptions!$B$51)),Assumptions!$D$235,0) | E20: =IF(OR(D20>0,AND(E$3>=Assumptions!$E$235,E$3>=Assumptions!$B$14,Revenue_Build!E10>=Assumptions!$F$235*Assumptions!$B$51)),Assumptions!$D$235,0) | F20: =IF(OR(E20>0,AND(F$3>=Assumptions!$E$235,F$3>=Assumptions!$B$14,Revenue_Build!F10>=Assumptions!$F$235*Assumptions!$B$51)),Assumptions!$D$235,0) | G20: =IF(OR(F20>0,AND(G$3>=Assumptions!$E$235,G$3>=Assumptions!$B$14,Revenue_Build!G10>=Assumptions!$F$235*Assumptions!$B$51)),Assumptions!$D$235,0) | H20: =IF(OR(G20>0,AND(H$3>=Assumptions!$E$235,H$3>=Assumptions!$B$14,Revenue_Build!H10>=Assumptions!$F$235*Assumptions!$B$51)),Assumptions!$D$235,0) | I20: =IF(OR(H20>0,AND(I$3>=Assumptions!$E$235,I$3>=Assumptions!$B$14,Revenue_Build!I10>=Assumptions!$F$235*Assumptions!$B$51)),Assumptions!$D$235,0) | J20: =IF(OR(I20>0,AND(J$3>=Assumptions!$E$235,J$3>=Assumptions!$B$14,Revenue_Build!J10>=Assumptions!$F$235*Assumptions!$B$51)),Assumptions!$D$235,0) | K20: =IF(OR(J20>0,AND(K$3>=Assumptions!$E$235,K$3>=Assumptions!$B$14,Revenue_Build!K10>=Assumptions!$F$235*Assumptions!$B$51)),Assumptions!$D$235,0) | ... BJ20: =IF(OR(BI20>0,AND(BJ$3>=Assumptions!$E$235,BJ$3>=Assumptions!$B$14,Revenue_Build!BJ10>=Assumptions!$F$235*Assumptions!$B$51)),Assumptions!$D$235,0)
A21: Product manager #2 | B21: FTE | C21: =IF(AND(C$3>=Assumptions!$E$236,C$3>=Assumptions!$B$14,Revenue_Build!C10>=Assumptions!$F$236*Assumptions!$B$51),Assumptions!$D$236,0) | D21: =IF(OR(C21>0,AND(D$3>=Assumptions!$E$236,D$3>=Assumptions!$B$14,Revenue_Build!D10>=Assumptions!$F$236*Assumptions!$B$51)),Assumptions!$D$236,0) | E21: =IF(OR(D21>0,AND(E$3>=Assumptions!$E$236,E$3>=Assumptions!$B$14,Revenue_Build!E10>=Assumptions!$F$236*Assumptions!$B$51)),Assumptions!$D$236,0) | F21: =IF(OR(E21>0,AND(F$3>=Assumptions!$E$236,F$3>=Assumptions!$B$14,Revenue_Build!F10>=Assumptions!$F$236*Assumptions!$B$51)),Assumptions!$D$236,0) | G21: =IF(OR(F21>0,AND(G$3>=Assumptions!$E$236,G$3>=Assumptions!$B$14,Revenue_Build!G10>=Assumptions!$F$236*Assumptions!$B$51)),Assumptions!$D$236,0) | H21: =IF(OR(G21>0,AND(H$3>=Assumptions!$E$236,H$3>=Assumptions!$B$14,Revenue_Build!H10>=Assumptions!$F$236*Assumptions!$B$51)),Assumptions!$D$236,0) | I21: =IF(OR(H21>0,AND(I$3>=Assumptions!$E$236,I$3>=Assumptions!$B$14,Revenue_Build!I10>=Assumptions!$F$236*Assumptions!$B$51)),Assumptions!$D$236,0) | J21: =IF(OR(I21>0,AND(J$3>=Assumptions!$E$236,J$3>=Assumptions!$B$14,Revenue_Build!J10>=Assumptions!$F$236*Assumptions!$B$51)),Assumptions!$D$236,0) | K21: =IF(OR(J21>0,AND(K$3>=Assumptions!$E$236,K$3>=Assumptions!$B$14,Revenue_Build!K10>=Assumptions!$F$236*Assumptions!$B$51)),Assumptions!$D$236,0) | ... BJ21: =IF(OR(BI21>0,AND(BJ$3>=Assumptions!$E$236,BJ$3>=Assumptions!$B$14,Revenue_Build!BJ10>=Assumptions!$F$236*Assumptions!$B$51)),Assumptions!$D$236,0)
A22: Engineers (scale-up II) | B22: FTE | C22: =IF(AND(C$3>=Assumptions!$E$237,C$3>=Assumptions!$B$14,Revenue_Build!C10>=Assumptions!$F$237*Assumptions!$B$51),Assumptions!$D$237,0) | D22: =IF(OR(C22>0,AND(D$3>=Assumptions!$E$237,D$3>=Assumptions!$B$14,Revenue_Build!D10>=Assumptions!$F$237*Assumptions!$B$51)),Assumptions!$D$237,0) | E22: =IF(OR(D22>0,AND(E$3>=Assumptions!$E$237,E$3>=Assumptions!$B$14,Revenue_Build!E10>=Assumptions!$F$237*Assumptions!$B$51)),Assumptions!$D$237,0) | F22: =IF(OR(E22>0,AND(F$3>=Assumptions!$E$237,F$3>=Assumptions!$B$14,Revenue_Build!F10>=Assumptions!$F$237*Assumptions!$B$51)),Assumptions!$D$237,0) | G22: =IF(OR(F22>0,AND(G$3>=Assumptions!$E$237,G$3>=Assumptions!$B$14,Revenue_Build!G10>=Assumptions!$F$237*Assumptions!$B$51)),Assumptions!$D$237,0) | H22: =IF(OR(G22>0,AND(H$3>=Assumptions!$E$237,H$3>=Assumptions!$B$14,Revenue_Build!H10>=Assumptions!$F$237*Assumptions!$B$51)),Assumptions!$D$237,0) | I22: =IF(OR(H22>0,AND(I$3>=Assumptions!$E$237,I$3>=Assumptions!$B$14,Revenue_Build!I10>=Assumptions!$F$237*Assumptions!$B$51)),Assumptions!$D$237,0) | J22: =IF(OR(I22>0,AND(J$3>=Assumptions!$E$237,J$3>=Assumptions!$B$14,Revenue_Build!J10>=Assumptions!$F$237*Assumptions!$B$51)),Assumptions!$D$237,0) | K22: =IF(OR(J22>0,AND(K$3>=Assumptions!$E$237,K$3>=Assumptions!$B$14,Revenue_Build!K10>=Assumptions!$F$237*Assumptions!$B$51)),Assumptions!$D$237,0) | ... BJ22: =IF(OR(BI22>0,AND(BJ$3>=Assumptions!$E$237,BJ$3>=Assumptions!$B$14,Revenue_Build!BJ10>=Assumptions!$F$237*Assumptions!$B$51)),Assumptions!$D$237,0)
A23: Data / AI engineers | B23: FTE | C23: =IF(AND(C$3>=Assumptions!$E$238,C$3>=Assumptions!$B$14,Revenue_Build!C10>=Assumptions!$F$238*Assumptions!$B$51),Assumptions!$D$238,0) | D23: =IF(OR(C23>0,AND(D$3>=Assumptions!$E$238,D$3>=Assumptions!$B$14,Revenue_Build!D10>=Assumptions!$F$238*Assumptions!$B$51)),Assumptions!$D$238,0) | E23: =IF(OR(D23>0,AND(E$3>=Assumptions!$E$238,E$3>=Assumptions!$B$14,Revenue_Build!E10>=Assumptions!$F$238*Assumptions!$B$51)),Assumptions!$D$238,0) | F23: =IF(OR(E23>0,AND(F$3>=Assumptions!$E$238,F$3>=Assumptions!$B$14,Revenue_Build!F10>=Assumptions!$F$238*Assumptions!$B$51)),Assumptions!$D$238,0) | G23: =IF(OR(F23>0,AND(G$3>=Assumptions!$E$238,G$3>=Assumptions!$B$14,Revenue_Build!G10>=Assumptions!$F$238*Assumptions!$B$51)),Assumptions!$D$238,0) | H23: =IF(OR(G23>0,AND(H$3>=Assumptions!$E$238,H$3>=Assumptions!$B$14,Revenue_Build!H10>=Assumptions!$F$238*Assumptions!$B$51)),Assumptions!$D$238,0) | I23: =IF(OR(H23>0,AND(I$3>=Assumptions!$E$238,I$3>=Assumptions!$B$14,Revenue_Build!I10>=Assumptions!$F$238*Assumptions!$B$51)),Assumptions!$D$238,0) | J23: =IF(OR(I23>0,AND(J$3>=Assumptions!$E$238,J$3>=Assumptions!$B$14,Revenue_Build!J10>=Assumptions!$F$238*Assumptions!$B$51)),Assumptions!$D$238,0) | K23: =IF(OR(J23>0,AND(K$3>=Assumptions!$E$238,K$3>=Assumptions!$B$14,Revenue_Build!K10>=Assumptions!$F$238*Assumptions!$B$51)),Assumptions!$D$238,0) | ... BJ23: =IF(OR(BI23>0,AND(BJ$3>=Assumptions!$E$238,BJ$3>=Assumptions!$B$14,Revenue_Build!BJ10>=Assumptions!$F$238*Assumptions!$B$51)),Assumptions!$D$238,0)
A24: Engineers (scale-up III) | B24: FTE | C24: =IF(AND(C$3>=Assumptions!$E$239,C$3>=Assumptions!$B$14,Revenue_Build!C10>=Assumptions!$F$239*Assumptions!$B$51),Assumptions!$D$239,0) | D24: =IF(OR(C24>0,AND(D$3>=Assumptions!$E$239,D$3>=Assumptions!$B$14,Revenue_Build!D10>=Assumptions!$F$239*Assumptions!$B$51)),Assumptions!$D$239,0) | E24: =IF(OR(D24>0,AND(E$3>=Assumptions!$E$239,E$3>=Assumptions!$B$14,Revenue_Build!E10>=Assumptions!$F$239*Assumptions!$B$51)),Assumptions!$D$239,0) | F24: =IF(OR(E24>0,AND(F$3>=Assumptions!$E$239,F$3>=Assumptions!$B$14,Revenue_Build!F10>=Assumptions!$F$239*Assumptions!$B$51)),Assumptions!$D$239,0) | G24: =IF(OR(F24>0,AND(G$3>=Assumptions!$E$239,G$3>=Assumptions!$B$14,Revenue_Build!G10>=Assumptions!$F$239*Assumptions!$B$51)),Assumptions!$D$239,0) | H24: =IF(OR(G24>0,AND(H$3>=Assumptions!$E$239,H$3>=Assumptions!$B$14,Revenue_Build!H10>=Assumptions!$F$239*Assumptions!$B$51)),Assumptions!$D$239,0) | I24: =IF(OR(H24>0,AND(I$3>=Assumptions!$E$239,I$3>=Assumptions!$B$14,Revenue_Build!I10>=Assumptions!$F$239*Assumptions!$B$51)),Assumptions!$D$239,0) | J24: =IF(OR(I24>0,AND(J$3>=Assumptions!$E$239,J$3>=Assumptions!$B$14,Revenue_Build!J10>=Assumptions!$F$239*Assumptions!$B$51)),Assumptions!$D$239,0) | K24: =IF(OR(J24>0,AND(K$3>=Assumptions!$E$239,K$3>=Assumptions!$B$14,Revenue_Build!K10>=Assumptions!$F$239*Assumptions!$B$51)),Assumptions!$D$239,0) | ... BJ24: =IF(OR(BI24>0,AND(BJ$3>=Assumptions!$E$239,BJ$3>=Assumptions!$B$14,Revenue_Build!BJ10>=Assumptions!$F$239*Assumptions!$B$51)),Assumptions!$D$239,0)
A25: Engineers (scale-up IV: social adapters & integrations at scale) | B25: FTE | C25: =IF(AND(C$3>=Assumptions!$E$240,C$3>=Assumptions!$B$14,Revenue_Build!C10>=Assumptions!$F$240*Assumptions!$B$51),Assumptions!$D$240,0) | D25: =IF(OR(C25>0,AND(D$3>=Assumptions!$E$240,D$3>=Assumptions!$B$14,Revenue_Build!D10>=Assumptions!$F$240*Assumptions!$B$51)),Assumptions!$D$240,0) | E25: =IF(OR(D25>0,AND(E$3>=Assumptions!$E$240,E$3>=Assumptions!$B$14,Revenue_Build!E10>=Assumptions!$F$240*Assumptions!$B$51)),Assumptions!$D$240,0) | F25: =IF(OR(E25>0,AND(F$3>=Assumptions!$E$240,F$3>=Assumptions!$B$14,Revenue_Build!F10>=Assumptions!$F$240*Assumptions!$B$51)),Assumptions!$D$240,0) | G25: =IF(OR(F25>0,AND(G$3>=Assumptions!$E$240,G$3>=Assumptions!$B$14,Revenue_Build!G10>=Assumptions!$F$240*Assumptions!$B$51)),Assumptions!$D$240,0) | H25: =IF(OR(G25>0,AND(H$3>=Assumptions!$E$240,H$3>=Assumptions!$B$14,Revenue_Build!H10>=Assumptions!$F$240*Assumptions!$B$51)),Assumptions!$D$240,0) | I25: =IF(OR(H25>0,AND(I$3>=Assumptions!$E$240,I$3>=Assumptions!$B$14,Revenue_Build!I10>=Assumptions!$F$240*Assumptions!$B$51)),Assumptions!$D$240,0) | J25: =IF(OR(I25>0,AND(J$3>=Assumptions!$E$240,J$3>=Assumptions!$B$14,Revenue_Build!J10>=Assumptions!$F$240*Assumptions!$B$51)),Assumptions!$D$240,0) | K25: =IF(OR(J25>0,AND(K$3>=Assumptions!$E$240,K$3>=Assumptions!$B$14,Revenue_Build!K10>=Assumptions!$F$240*Assumptions!$B$51)),Assumptions!$D$240,0) | ... BJ25: =IF(OR(BI25>0,AND(BJ$3>=Assumptions!$E$240,BJ$3>=Assumptions!$B$14,Revenue_Build!BJ10>=Assumptions!$F$240*Assumptions!$B$51)),Assumptions!$D$240,0)
A26: Data & AI team II | B26: FTE | C26: =IF(AND(C$3>=Assumptions!$E$241,C$3>=Assumptions!$B$14,Revenue_Build!C10>=Assumptions!$F$241*Assumptions!$B$51),Assumptions!$D$241,0) | D26: =IF(OR(C26>0,AND(D$3>=Assumptions!$E$241,D$3>=Assumptions!$B$14,Revenue_Build!D10>=Assumptions!$F$241*Assumptions!$B$51)),Assumptions!$D$241,0) | E26: =IF(OR(D26>0,AND(E$3>=Assumptions!$E$241,E$3>=Assumptions!$B$14,Revenue_Build!E10>=Assumptions!$F$241*Assumptions!$B$51)),Assumptions!$D$241,0) | F26: =IF(OR(E26>0,AND(F$3>=Assumptions!$E$241,F$3>=Assumptions!$B$14,Revenue_Build!F10>=Assumptions!$F$241*Assumptions!$B$51)),Assumptions!$D$241,0) | G26: =IF(OR(F26>0,AND(G$3>=Assumptions!$E$241,G$3>=Assumptions!$B$14,Revenue_Build!G10>=Assumptions!$F$241*Assumptions!$B$51)),Assumptions!$D$241,0) | H26: =IF(OR(G26>0,AND(H$3>=Assumptions!$E$241,H$3>=Assumptions!$B$14,Revenue_Build!H10>=Assumptions!$F$241*Assumptions!$B$51)),Assumptions!$D$241,0) | I26: =IF(OR(H26>0,AND(I$3>=Assumptions!$E$241,I$3>=Assumptions!$B$14,Revenue_Build!I10>=Assumptions!$F$241*Assumptions!$B$51)),Assumptions!$D$241,0) | J26: =IF(OR(I26>0,AND(J$3>=Assumptions!$E$241,J$3>=Assumptions!$B$14,Revenue_Build!J10>=Assumptions!$F$241*Assumptions!$B$51)),Assumptions!$D$241,0) | K26: =IF(OR(J26>0,AND(K$3>=Assumptions!$E$241,K$3>=Assumptions!$B$14,Revenue_Build!K10>=Assumptions!$F$241*Assumptions!$B$51)),Assumptions!$D$241,0) | ... BJ26: =IF(OR(BI26>0,AND(BJ$3>=Assumptions!$E$241,BJ$3>=Assumptions!$B$14,Revenue_Build!BJ10>=Assumptions!$F$241*Assumptions!$B$51)),Assumptions!$D$241,0)
A27: Head of Growth | B27: FTE | C27: =IF(AND(C$3>=Assumptions!$E$242,C$3>=Assumptions!$B$14,Revenue_Build!C10>=Assumptions!$F$242*Assumptions!$B$51),Assumptions!$D$242,0) | D27: =IF(OR(C27>0,AND(D$3>=Assumptions!$E$242,D$3>=Assumptions!$B$14,Revenue_Build!D10>=Assumptions!$F$242*Assumptions!$B$51)),Assumptions!$D$242,0) | E27: =IF(OR(D27>0,AND(E$3>=Assumptions!$E$242,E$3>=Assumptions!$B$14,Revenue_Build!E10>=Assumptions!$F$242*Assumptions!$B$51)),Assumptions!$D$242,0) | F27: =IF(OR(E27>0,AND(F$3>=Assumptions!$E$242,F$3>=Assumptions!$B$14,Revenue_Build!F10>=Assumptions!$F$242*Assumptions!$B$51)),Assumptions!$D$242,0) | G27: =IF(OR(F27>0,AND(G$3>=Assumptions!$E$242,G$3>=Assumptions!$B$14,Revenue_Build!G10>=Assumptions!$F$242*Assumptions!$B$51)),Assumptions!$D$242,0) | H27: =IF(OR(G27>0,AND(H$3>=Assumptions!$E$242,H$3>=Assumptions!$B$14,Revenue_Build!H10>=Assumptions!$F$242*Assumptions!$B$51)),Assumptions!$D$242,0) | I27: =IF(OR(H27>0,AND(I$3>=Assumptions!$E$242,I$3>=Assumptions!$B$14,Revenue_Build!I10>=Assumptions!$F$242*Assumptions!$B$51)),Assumptions!$D$242,0) | J27: =IF(OR(I27>0,AND(J$3>=Assumptions!$E$242,J$3>=Assumptions!$B$14,Revenue_Build!J10>=Assumptions!$F$242*Assumptions!$B$51)),Assumptions!$D$242,0) | K27: =IF(OR(J27>0,AND(K$3>=Assumptions!$E$242,K$3>=Assumptions!$B$14,Revenue_Build!K10>=Assumptions!$F$242*Assumptions!$B$51)),Assumptions!$D$242,0) | ... BJ27: =IF(OR(BI27>0,AND(BJ$3>=Assumptions!$E$242,BJ$3>=Assumptions!$B$14,Revenue_Build!BJ10>=Assumptions!$F$242*Assumptions!$B$51)),Assumptions!$D$242,0)
A28: Performance marketer | B28: FTE | C28: =IF(AND(C$3>=Assumptions!$E$243,C$3>=Assumptions!$B$14,Revenue_Build!C10>=Assumptions!$F$243*Assumptions!$B$51),Assumptions!$D$243,0) | D28: =IF(OR(C28>0,AND(D$3>=Assumptions!$E$243,D$3>=Assumptions!$B$14,Revenue_Build!D10>=Assumptions!$F$243*Assumptions!$B$51)),Assumptions!$D$243,0) | E28: =IF(OR(D28>0,AND(E$3>=Assumptions!$E$243,E$3>=Assumptions!$B$14,Revenue_Build!E10>=Assumptions!$F$243*Assumptions!$B$51)),Assumptions!$D$243,0) | F28: =IF(OR(E28>0,AND(F$3>=Assumptions!$E$243,F$3>=Assumptions!$B$14,Revenue_Build!F10>=Assumptions!$F$243*Assumptions!$B$51)),Assumptions!$D$243,0) | G28: =IF(OR(F28>0,AND(G$3>=Assumptions!$E$243,G$3>=Assumptions!$B$14,Revenue_Build!G10>=Assumptions!$F$243*Assumptions!$B$51)),Assumptions!$D$243,0) | H28: =IF(OR(G28>0,AND(H$3>=Assumptions!$E$243,H$3>=Assumptions!$B$14,Revenue_Build!H10>=Assumptions!$F$243*Assumptions!$B$51)),Assumptions!$D$243,0) | I28: =IF(OR(H28>0,AND(I$3>=Assumptions!$E$243,I$3>=Assumptions!$B$14,Revenue_Build!I10>=Assumptions!$F$243*Assumptions!$B$51)),Assumptions!$D$243,0) | J28: =IF(OR(I28>0,AND(J$3>=Assumptions!$E$243,J$3>=Assumptions!$B$14,Revenue_Build!J10>=Assumptions!$F$243*Assumptions!$B$51)),Assumptions!$D$243,0) | K28: =IF(OR(J28>0,AND(K$3>=Assumptions!$E$243,K$3>=Assumptions!$B$14,Revenue_Build!K10>=Assumptions!$F$243*Assumptions!$B$51)),Assumptions!$D$243,0) | ... BJ28: =IF(OR(BI28>0,AND(BJ$3>=Assumptions!$E$243,BJ$3>=Assumptions!$B$14,Revenue_Build!BJ10>=Assumptions!$F$243*Assumptions!$B$51)),Assumptions!$D$243,0)
A29: Multilingual content & community | B29: FTE | C29: =IF(AND(C$3>=Assumptions!$E$244,C$3>=Assumptions!$B$14,Revenue_Build!C10>=Assumptions!$F$244*Assumptions!$B$51),Assumptions!$D$244,0) | D29: =IF(OR(C29>0,AND(D$3>=Assumptions!$E$244,D$3>=Assumptions!$B$14,Revenue_Build!D10>=Assumptions!$F$244*Assumptions!$B$51)),Assumptions!$D$244,0) | E29: =IF(OR(D29>0,AND(E$3>=Assumptions!$E$244,E$3>=Assumptions!$B$14,Revenue_Build!E10>=Assumptions!$F$244*Assumptions!$B$51)),Assumptions!$D$244,0) | F29: =IF(OR(E29>0,AND(F$3>=Assumptions!$E$244,F$3>=Assumptions!$B$14,Revenue_Build!F10>=Assumptions!$F$244*Assumptions!$B$51)),Assumptions!$D$244,0) | G29: =IF(OR(F29>0,AND(G$3>=Assumptions!$E$244,G$3>=Assumptions!$B$14,Revenue_Build!G10>=Assumptions!$F$244*Assumptions!$B$51)),Assumptions!$D$244,0) | H29: =IF(OR(G29>0,AND(H$3>=Assumptions!$E$244,H$3>=Assumptions!$B$14,Revenue_Build!H10>=Assumptions!$F$244*Assumptions!$B$51)),Assumptions!$D$244,0) | I29: =IF(OR(H29>0,AND(I$3>=Assumptions!$E$244,I$3>=Assumptions!$B$14,Revenue_Build!I10>=Assumptions!$F$244*Assumptions!$B$51)),Assumptions!$D$244,0) | J29: =IF(OR(I29>0,AND(J$3>=Assumptions!$E$244,J$3>=Assumptions!$B$14,Revenue_Build!J10>=Assumptions!$F$244*Assumptions!$B$51)),Assumptions!$D$244,0) | K29: =IF(OR(J29>0,AND(K$3>=Assumptions!$E$244,K$3>=Assumptions!$B$14,Revenue_Build!K10>=Assumptions!$F$244*Assumptions!$B$51)),Assumptions!$D$244,0) | ... BJ29: =IF(OR(BI29>0,AND(BJ$3>=Assumptions!$E$244,BJ$3>=Assumptions!$B$14,Revenue_Build!BJ10>=Assumptions!$F$244*Assumptions!$B$51)),Assumptions!$D$244,0)
A30: Lifecycle & growth marketers | B30: FTE | C30: =IF(AND(C$3>=Assumptions!$E$245,C$3>=Assumptions!$B$14,Revenue_Build!C10>=Assumptions!$F$245*Assumptions!$B$51),Assumptions!$D$245,0) | D30: =IF(OR(C30>0,AND(D$3>=Assumptions!$E$245,D$3>=Assumptions!$B$14,Revenue_Build!D10>=Assumptions!$F$245*Assumptions!$B$51)),Assumptions!$D$245,0) | E30: =IF(OR(D30>0,AND(E$3>=Assumptions!$E$245,E$3>=Assumptions!$B$14,Revenue_Build!E10>=Assumptions!$F$245*Assumptions!$B$51)),Assumptions!$D$245,0) | F30: =IF(OR(E30>0,AND(F$3>=Assumptions!$E$245,F$3>=Assumptions!$B$14,Revenue_Build!F10>=Assumptions!$F$245*Assumptions!$B$51)),Assumptions!$D$245,0) | G30: =IF(OR(F30>0,AND(G$3>=Assumptions!$E$245,G$3>=Assumptions!$B$14,Revenue_Build!G10>=Assumptions!$F$245*Assumptions!$B$51)),Assumptions!$D$245,0) | H30: =IF(OR(G30>0,AND(H$3>=Assumptions!$E$245,H$3>=Assumptions!$B$14,Revenue_Build!H10>=Assumptions!$F$245*Assumptions!$B$51)),Assumptions!$D$245,0) | I30: =IF(OR(H30>0,AND(I$3>=Assumptions!$E$245,I$3>=Assumptions!$B$14,Revenue_Build!I10>=Assumptions!$F$245*Assumptions!$B$51)),Assumptions!$D$245,0) | J30: =IF(OR(I30>0,AND(J$3>=Assumptions!$E$245,J$3>=Assumptions!$B$14,Revenue_Build!J10>=Assumptions!$F$245*Assumptions!$B$51)),Assumptions!$D$245,0) | K30: =IF(OR(J30>0,AND(K$3>=Assumptions!$E$245,K$3>=Assumptions!$B$14,Revenue_Build!K10>=Assumptions!$F$245*Assumptions!$B$51)),Assumptions!$D$245,0) | ... BJ30: =IF(OR(BI30>0,AND(BJ$3>=Assumptions!$E$245,BJ$3>=Assumptions!$B$14,Revenue_Build!BJ10>=Assumptions!$F$245*Assumptions!$B$51)),Assumptions!$D$245,0)
A31: Marketing team expansion I | B31: FTE | C31: =IF(AND(C$3>=Assumptions!$E$246,C$3>=Assumptions!$B$14,Revenue_Build!C10>=Assumptions!$F$246*Assumptions!$B$51),Assumptions!$D$246,0) | D31: =IF(OR(C31>0,AND(D$3>=Assumptions!$E$246,D$3>=Assumptions!$B$14,Revenue_Build!D10>=Assumptions!$F$246*Assumptions!$B$51)),Assumptions!$D$246,0) | E31: =IF(OR(D31>0,AND(E$3>=Assumptions!$E$246,E$3>=Assumptions!$B$14,Revenue_Build!E10>=Assumptions!$F$246*Assumptions!$B$51)),Assumptions!$D$246,0) | F31: =IF(OR(E31>0,AND(F$3>=Assumptions!$E$246,F$3>=Assumptions!$B$14,Revenue_Build!F10>=Assumptions!$F$246*Assumptions!$B$51)),Assumptions!$D$246,0) | G31: =IF(OR(F31>0,AND(G$3>=Assumptions!$E$246,G$3>=Assumptions!$B$14,Revenue_Build!G10>=Assumptions!$F$246*Assumptions!$B$51)),Assumptions!$D$246,0) | H31: =IF(OR(G31>0,AND(H$3>=Assumptions!$E$246,H$3>=Assumptions!$B$14,Revenue_Build!H10>=Assumptions!$F$246*Assumptions!$B$51)),Assumptions!$D$246,0) | I31: =IF(OR(H31>0,AND(I$3>=Assumptions!$E$246,I$3>=Assumptions!$B$14,Revenue_Build!I10>=Assumptions!$F$246*Assumptions!$B$51)),Assumptions!$D$246,0) | J31: =IF(OR(I31>0,AND(J$3>=Assumptions!$E$246,J$3>=Assumptions!$B$14,Revenue_Build!J10>=Assumptions!$F$246*Assumptions!$B$51)),Assumptions!$D$246,0) | K31: =IF(OR(J31>0,AND(K$3>=Assumptions!$E$246,K$3>=Assumptions!$B$14,Revenue_Build!K10>=Assumptions!$F$246*Assumptions!$B$51)),Assumptions!$D$246,0) | ... BJ31: =IF(OR(BI31>0,AND(BJ$3>=Assumptions!$E$246,BJ$3>=Assumptions!$B$14,Revenue_Build!BJ10>=Assumptions!$F$246*Assumptions!$B$51)),Assumptions!$D$246,0)
A32: Marketing team expansion II | B32: FTE | C32: =IF(AND(C$3>=Assumptions!$E$247,C$3>=Assumptions!$B$14,Revenue_Build!C10>=Assumptions!$F$247*Assumptions!$B$51),Assumptions!$D$247,0) | D32: =IF(OR(C32>0,AND(D$3>=Assumptions!$E$247,D$3>=Assumptions!$B$14,Revenue_Build!D10>=Assumptions!$F$247*Assumptions!$B$51)),Assumptions!$D$247,0) | E32: =IF(OR(D32>0,AND(E$3>=Assumptions!$E$247,E$3>=Assumptions!$B$14,Revenue_Build!E10>=Assumptions!$F$247*Assumptions!$B$51)),Assumptions!$D$247,0) | F32: =IF(OR(E32>0,AND(F$3>=Assumptions!$E$247,F$3>=Assumptions!$B$14,Revenue_Build!F10>=Assumptions!$F$247*Assumptions!$B$51)),Assumptions!$D$247,0) | G32: =IF(OR(F32>0,AND(G$3>=Assumptions!$E$247,G$3>=Assumptions!$B$14,Revenue_Build!G10>=Assumptions!$F$247*Assumptions!$B$51)),Assumptions!$D$247,0) | H32: =IF(OR(G32>0,AND(H$3>=Assumptions!$E$247,H$3>=Assumptions!$B$14,Revenue_Build!H10>=Assumptions!$F$247*Assumptions!$B$51)),Assumptions!$D$247,0) | I32: =IF(OR(H32>0,AND(I$3>=Assumptions!$E$247,I$3>=Assumptions!$B$14,Revenue_Build!I10>=Assumptions!$F$247*Assumptions!$B$51)),Assumptions!$D$247,0) | J32: =IF(OR(I32>0,AND(J$3>=Assumptions!$E$247,J$3>=Assumptions!$B$14,Revenue_Build!J10>=Assumptions!$F$247*Assumptions!$B$51)),Assumptions!$D$247,0) | K32: =IF(OR(J32>0,AND(K$3>=Assumptions!$E$247,K$3>=Assumptions!$B$14,Revenue_Build!K10>=Assumptions!$F$247*Assumptions!$B$51)),Assumptions!$D$247,0) | ... BJ32: =IF(OR(BI32>0,AND(BJ$3>=Assumptions!$E$247,BJ$3>=Assumptions!$B$14,Revenue_Build!BJ10>=Assumptions!$F$247*Assumptions!$B$51)),Assumptions!$D$247,0)
A33: Marketing team expansion III | B33: FTE | C33: =IF(AND(C$3>=Assumptions!$E$248,C$3>=Assumptions!$B$14,Revenue_Build!C10>=Assumptions!$F$248*Assumptions!$B$51),Assumptions!$D$248,0) | D33: =IF(OR(C33>0,AND(D$3>=Assumptions!$E$248,D$3>=Assumptions!$B$14,Revenue_Build!D10>=Assumptions!$F$248*Assumptions!$B$51)),Assumptions!$D$248,0) | E33: =IF(OR(D33>0,AND(E$3>=Assumptions!$E$248,E$3>=Assumptions!$B$14,Revenue_Build!E10>=Assumptions!$F$248*Assumptions!$B$51)),Assumptions!$D$248,0) | F33: =IF(OR(E33>0,AND(F$3>=Assumptions!$E$248,F$3>=Assumptions!$B$14,Revenue_Build!F10>=Assumptions!$F$248*Assumptions!$B$51)),Assumptions!$D$248,0) | G33: =IF(OR(F33>0,AND(G$3>=Assumptions!$E$248,G$3>=Assumptions!$B$14,Revenue_Build!G10>=Assumptions!$F$248*Assumptions!$B$51)),Assumptions!$D$248,0) | H33: =IF(OR(G33>0,AND(H$3>=Assumptions!$E$248,H$3>=Assumptions!$B$14,Revenue_Build!H10>=Assumptions!$F$248*Assumptions!$B$51)),Assumptions!$D$248,0) | I33: =IF(OR(H33>0,AND(I$3>=Assumptions!$E$248,I$3>=Assumptions!$B$14,Revenue_Build!I10>=Assumptions!$F$248*Assumptions!$B$51)),Assumptions!$D$248,0) | J33: =IF(OR(I33>0,AND(J$3>=Assumptions!$E$248,J$3>=Assumptions!$B$14,Revenue_Build!J10>=Assumptions!$F$248*Assumptions!$B$51)),Assumptions!$D$248,0) | K33: =IF(OR(J33>0,AND(K$3>=Assumptions!$E$248,K$3>=Assumptions!$B$14,Revenue_Build!K10>=Assumptions!$F$248*Assumptions!$B$51)),Assumptions!$D$248,0) | ... BJ33: =IF(OR(BI33>0,AND(BJ$3>=Assumptions!$E$248,BJ$3>=Assumptions!$B$14,Revenue_Build!BJ10>=Assumptions!$F$248*Assumptions!$B$51)),Assumptions!$D$248,0)
A34: Partnerships manager #1 (agency programme) | B34: FTE | C34: =IF(AND(C$3>=Assumptions!$E$249,C$3>=Assumptions!$B$14,Revenue_Build!C10>=Assumptions!$F$249*Assumptions!$B$51),Assumptions!$D$249,0) | D34: =IF(OR(C34>0,AND(D$3>=Assumptions!$E$249,D$3>=Assumptions!$B$14,Revenue_Build!D10>=Assumptions!$F$249*Assumptions!$B$51)),Assumptions!$D$249,0) | E34: =IF(OR(D34>0,AND(E$3>=Assumptions!$E$249,E$3>=Assumptions!$B$14,Revenue_Build!E10>=Assumptions!$F$249*Assumptions!$B$51)),Assumptions!$D$249,0) | F34: =IF(OR(E34>0,AND(F$3>=Assumptions!$E$249,F$3>=Assumptions!$B$14,Revenue_Build!F10>=Assumptions!$F$249*Assumptions!$B$51)),Assumptions!$D$249,0) | G34: =IF(OR(F34>0,AND(G$3>=Assumptions!$E$249,G$3>=Assumptions!$B$14,Revenue_Build!G10>=Assumptions!$F$249*Assumptions!$B$51)),Assumptions!$D$249,0) | H34: =IF(OR(G34>0,AND(H$3>=Assumptions!$E$249,H$3>=Assumptions!$B$14,Revenue_Build!H10>=Assumptions!$F$249*Assumptions!$B$51)),Assumptions!$D$249,0) | I34: =IF(OR(H34>0,AND(I$3>=Assumptions!$E$249,I$3>=Assumptions!$B$14,Revenue_Build!I10>=Assumptions!$F$249*Assumptions!$B$51)),Assumptions!$D$249,0) | J34: =IF(OR(I34>0,AND(J$3>=Assumptions!$E$249,J$3>=Assumptions!$B$14,Revenue_Build!J10>=Assumptions!$F$249*Assumptions!$B$51)),Assumptions!$D$249,0) | K34: =IF(OR(J34>0,AND(K$3>=Assumptions!$E$249,K$3>=Assumptions!$B$14,Revenue_Build!K10>=Assumptions!$F$249*Assumptions!$B$51)),Assumptions!$D$249,0) | ... BJ34: =IF(OR(BI34>0,AND(BJ$3>=Assumptions!$E$249,BJ$3>=Assumptions!$B$14,Revenue_Build!BJ10>=Assumptions!$F$249*Assumptions!$B$51)),Assumptions!$D$249,0)
A35: Partnerships manager #2 | B35: FTE | C35: =IF(AND(C$3>=Assumptions!$E$250,C$3>=Assumptions!$B$14,Revenue_Build!C10>=Assumptions!$F$250*Assumptions!$B$51),Assumptions!$D$250,0) | D35: =IF(OR(C35>0,AND(D$3>=Assumptions!$E$250,D$3>=Assumptions!$B$14,Revenue_Build!D10>=Assumptions!$F$250*Assumptions!$B$51)),Assumptions!$D$250,0) | E35: =IF(OR(D35>0,AND(E$3>=Assumptions!$E$250,E$3>=Assumptions!$B$14,Revenue_Build!E10>=Assumptions!$F$250*Assumptions!$B$51)),Assumptions!$D$250,0) | F35: =IF(OR(E35>0,AND(F$3>=Assumptions!$E$250,F$3>=Assumptions!$B$14,Revenue_Build!F10>=Assumptions!$F$250*Assumptions!$B$51)),Assumptions!$D$250,0) | G35: =IF(OR(F35>0,AND(G$3>=Assumptions!$E$250,G$3>=Assumptions!$B$14,Revenue_Build!G10>=Assumptions!$F$250*Assumptions!$B$51)),Assumptions!$D$250,0) | H35: =IF(OR(G35>0,AND(H$3>=Assumptions!$E$250,H$3>=Assumptions!$B$14,Revenue_Build!H10>=Assumptions!$F$250*Assumptions!$B$51)),Assumptions!$D$250,0) | I35: =IF(OR(H35>0,AND(I$3>=Assumptions!$E$250,I$3>=Assumptions!$B$14,Revenue_Build!I10>=Assumptions!$F$250*Assumptions!$B$51)),Assumptions!$D$250,0) | J35: =IF(OR(I35>0,AND(J$3>=Assumptions!$E$250,J$3>=Assumptions!$B$14,Revenue_Build!J10>=Assumptions!$F$250*Assumptions!$B$51)),Assumptions!$D$250,0) | K35: =IF(OR(J35>0,AND(K$3>=Assumptions!$E$250,K$3>=Assumptions!$B$14,Revenue_Build!K10>=Assumptions!$F$250*Assumptions!$B$51)),Assumptions!$D$250,0) | ... BJ35: =IF(OR(BI35>0,AND(BJ$3>=Assumptions!$E$250,BJ$3>=Assumptions!$B$14,Revenue_Build!BJ10>=Assumptions!$F$250*Assumptions!$B$51)),Assumptions!$D$250,0)
A36: Partnerships managers (scale-up I) | B36: FTE | C36: =IF(AND(C$3>=Assumptions!$E$251,C$3>=Assumptions!$B$14,Revenue_Build!C10>=Assumptions!$F$251*Assumptions!$B$51),Assumptions!$D$251,0) | D36: =IF(OR(C36>0,AND(D$3>=Assumptions!$E$251,D$3>=Assumptions!$B$14,Revenue_Build!D10>=Assumptions!$F$251*Assumptions!$B$51)),Assumptions!$D$251,0) | E36: =IF(OR(D36>0,AND(E$3>=Assumptions!$E$251,E$3>=Assumptions!$B$14,Revenue_Build!E10>=Assumptions!$F$251*Assumptions!$B$51)),Assumptions!$D$251,0) | F36: =IF(OR(E36>0,AND(F$3>=Assumptions!$E$251,F$3>=Assumptions!$B$14,Revenue_Build!F10>=Assumptions!$F$251*Assumptions!$B$51)),Assumptions!$D$251,0) | G36: =IF(OR(F36>0,AND(G$3>=Assumptions!$E$251,G$3>=Assumptions!$B$14,Revenue_Build!G10>=Assumptions!$F$251*Assumptions!$B$51)),Assumptions!$D$251,0) | H36: =IF(OR(G36>0,AND(H$3>=Assumptions!$E$251,H$3>=Assumptions!$B$14,Revenue_Build!H10>=Assumptions!$F$251*Assumptions!$B$51)),Assumptions!$D$251,0) | I36: =IF(OR(H36>0,AND(I$3>=Assumptions!$E$251,I$3>=Assumptions!$B$14,Revenue_Build!I10>=Assumptions!$F$251*Assumptions!$B$51)),Assumptions!$D$251,0) | J36: =IF(OR(I36>0,AND(J$3>=Assumptions!$E$251,J$3>=Assumptions!$B$14,Revenue_Build!J10>=Assumptions!$F$251*Assumptions!$B$51)),Assumptions!$D$251,0) | K36: =IF(OR(J36>0,AND(K$3>=Assumptions!$E$251,K$3>=Assumptions!$B$14,Revenue_Build!K10>=Assumptions!$F$251*Assumptions!$B$51)),Assumptions!$D$251,0) | ... BJ36: =IF(OR(BI36>0,AND(BJ$3>=Assumptions!$E$251,BJ$3>=Assumptions!$B$14,Revenue_Build!BJ10>=Assumptions!$F$251*Assumptions!$B$51)),Assumptions!$D$251,0)
A37: Partnerships managers (scale-up II) | B37: FTE | C37: =IF(AND(C$3>=Assumptions!$E$252,C$3>=Assumptions!$B$14,Revenue_Build!C10>=Assumptions!$F$252*Assumptions!$B$51),Assumptions!$D$252,0) | D37: =IF(OR(C37>0,AND(D$3>=Assumptions!$E$252,D$3>=Assumptions!$B$14,Revenue_Build!D10>=Assumptions!$F$252*Assumptions!$B$51)),Assumptions!$D$252,0) | E37: =IF(OR(D37>0,AND(E$3>=Assumptions!$E$252,E$3>=Assumptions!$B$14,Revenue_Build!E10>=Assumptions!$F$252*Assumptions!$B$51)),Assumptions!$D$252,0) | F37: =IF(OR(E37>0,AND(F$3>=Assumptions!$E$252,F$3>=Assumptions!$B$14,Revenue_Build!F10>=Assumptions!$F$252*Assumptions!$B$51)),Assumptions!$D$252,0) | G37: =IF(OR(F37>0,AND(G$3>=Assumptions!$E$252,G$3>=Assumptions!$B$14,Revenue_Build!G10>=Assumptions!$F$252*Assumptions!$B$51)),Assumptions!$D$252,0) | H37: =IF(OR(G37>0,AND(H$3>=Assumptions!$E$252,H$3>=Assumptions!$B$14,Revenue_Build!H10>=Assumptions!$F$252*Assumptions!$B$51)),Assumptions!$D$252,0) | I37: =IF(OR(H37>0,AND(I$3>=Assumptions!$E$252,I$3>=Assumptions!$B$14,Revenue_Build!I10>=Assumptions!$F$252*Assumptions!$B$51)),Assumptions!$D$252,0) | J37: =IF(OR(I37>0,AND(J$3>=Assumptions!$E$252,J$3>=Assumptions!$B$14,Revenue_Build!J10>=Assumptions!$F$252*Assumptions!$B$51)),Assumptions!$D$252,0) | K37: =IF(OR(J37>0,AND(K$3>=Assumptions!$E$252,K$3>=Assumptions!$B$14,Revenue_Build!K10>=Assumptions!$F$252*Assumptions!$B$51)),Assumptions!$D$252,0) | ... BJ37: =IF(OR(BI37>0,AND(BJ$3>=Assumptions!$E$252,BJ$3>=Assumptions!$B$14,Revenue_Build!BJ10>=Assumptions!$F$252*Assumptions!$B$51)),Assumptions!$D$252,0)
A38: SME onboarding & sales-assist | B38: FTE | C38: =IF(AND(C$3>=Assumptions!$E$253,C$3>=Assumptions!$B$14,Revenue_Build!C10>=Assumptions!$F$253*Assumptions!$B$51),Assumptions!$D$253,0) | D38: =IF(OR(C38>0,AND(D$3>=Assumptions!$E$253,D$3>=Assumptions!$B$14,Revenue_Build!D10>=Assumptions!$F$253*Assumptions!$B$51)),Assumptions!$D$253,0) | E38: =IF(OR(D38>0,AND(E$3>=Assumptions!$E$253,E$3>=Assumptions!$B$14,Revenue_Build!E10>=Assumptions!$F$253*Assumptions!$B$51)),Assumptions!$D$253,0) | F38: =IF(OR(E38>0,AND(F$3>=Assumptions!$E$253,F$3>=Assumptions!$B$14,Revenue_Build!F10>=Assumptions!$F$253*Assumptions!$B$51)),Assumptions!$D$253,0) | G38: =IF(OR(F38>0,AND(G$3>=Assumptions!$E$253,G$3>=Assumptions!$B$14,Revenue_Build!G10>=Assumptions!$F$253*Assumptions!$B$51)),Assumptions!$D$253,0) | H38: =IF(OR(G38>0,AND(H$3>=Assumptions!$E$253,H$3>=Assumptions!$B$14,Revenue_Build!H10>=Assumptions!$F$253*Assumptions!$B$51)),Assumptions!$D$253,0) | I38: =IF(OR(H38>0,AND(I$3>=Assumptions!$E$253,I$3>=Assumptions!$B$14,Revenue_Build!I10>=Assumptions!$F$253*Assumptions!$B$51)),Assumptions!$D$253,0) | J38: =IF(OR(I38>0,AND(J$3>=Assumptions!$E$253,J$3>=Assumptions!$B$14,Revenue_Build!J10>=Assumptions!$F$253*Assumptions!$B$51)),Assumptions!$D$253,0) | K38: =IF(OR(J38>0,AND(K$3>=Assumptions!$E$253,K$3>=Assumptions!$B$14,Revenue_Build!K10>=Assumptions!$F$253*Assumptions!$B$51)),Assumptions!$D$253,0) | ... BJ38: =IF(OR(BI38>0,AND(BJ$3>=Assumptions!$E$253,BJ$3>=Assumptions!$B$14,Revenue_Build!BJ10>=Assumptions!$F$253*Assumptions!$B$51)),Assumptions!$D$253,0)
A39: Head of Sales & Partnerships | B39: FTE | C39: =IF(AND(C$3>=Assumptions!$E$254,C$3>=Assumptions!$B$14,Revenue_Build!C10>=Assumptions!$F$254*Assumptions!$B$51),Assumptions!$D$254,0) | D39: =IF(OR(C39>0,AND(D$3>=Assumptions!$E$254,D$3>=Assumptions!$B$14,Revenue_Build!D10>=Assumptions!$F$254*Assumptions!$B$51)),Assumptions!$D$254,0) | E39: =IF(OR(D39>0,AND(E$3>=Assumptions!$E$254,E$3>=Assumptions!$B$14,Revenue_Build!E10>=Assumptions!$F$254*Assumptions!$B$51)),Assumptions!$D$254,0) | F39: =IF(OR(E39>0,AND(F$3>=Assumptions!$E$254,F$3>=Assumptions!$B$14,Revenue_Build!F10>=Assumptions!$F$254*Assumptions!$B$51)),Assumptions!$D$254,0) | G39: =IF(OR(F39>0,AND(G$3>=Assumptions!$E$254,G$3>=Assumptions!$B$14,Revenue_Build!G10>=Assumptions!$F$254*Assumptions!$B$51)),Assumptions!$D$254,0) | H39: =IF(OR(G39>0,AND(H$3>=Assumptions!$E$254,H$3>=Assumptions!$B$14,Revenue_Build!H10>=Assumptions!$F$254*Assumptions!$B$51)),Assumptions!$D$254,0) | I39: =IF(OR(H39>0,AND(I$3>=Assumptions!$E$254,I$3>=Assumptions!$B$14,Revenue_Build!I10>=Assumptions!$F$254*Assumptions!$B$51)),Assumptions!$D$254,0) | J39: =IF(OR(I39>0,AND(J$3>=Assumptions!$E$254,J$3>=Assumptions!$B$14,Revenue_Build!J10>=Assumptions!$F$254*Assumptions!$B$51)),Assumptions!$D$254,0) | K39: =IF(OR(J39>0,AND(K$3>=Assumptions!$E$254,K$3>=Assumptions!$B$14,Revenue_Build!K10>=Assumptions!$F$254*Assumptions!$B$51)),Assumptions!$D$254,0) | ... BJ39: =IF(OR(BI39>0,AND(BJ$3>=Assumptions!$E$254,BJ$3>=Assumptions!$B$14,Revenue_Build!BJ10>=Assumptions!$F$254*Assumptions!$B$51)),Assumptions!$D$254,0)
A40: SME account managers | B40: FTE | C40: =IF(AND(C$3>=Assumptions!$E$255,C$3>=Assumptions!$B$14,Revenue_Build!C10>=Assumptions!$F$255*Assumptions!$B$51),Assumptions!$D$255,0) | D40: =IF(OR(C40>0,AND(D$3>=Assumptions!$E$255,D$3>=Assumptions!$B$14,Revenue_Build!D10>=Assumptions!$F$255*Assumptions!$B$51)),Assumptions!$D$255,0) | E40: =IF(OR(D40>0,AND(E$3>=Assumptions!$E$255,E$3>=Assumptions!$B$14,Revenue_Build!E10>=Assumptions!$F$255*Assumptions!$B$51)),Assumptions!$D$255,0) | F40: =IF(OR(E40>0,AND(F$3>=Assumptions!$E$255,F$3>=Assumptions!$B$14,Revenue_Build!F10>=Assumptions!$F$255*Assumptions!$B$51)),Assumptions!$D$255,0) | G40: =IF(OR(F40>0,AND(G$3>=Assumptions!$E$255,G$3>=Assumptions!$B$14,Revenue_Build!G10>=Assumptions!$F$255*Assumptions!$B$51)),Assumptions!$D$255,0) | H40: =IF(OR(G40>0,AND(H$3>=Assumptions!$E$255,H$3>=Assumptions!$B$14,Revenue_Build!H10>=Assumptions!$F$255*Assumptions!$B$51)),Assumptions!$D$255,0) | I40: =IF(OR(H40>0,AND(I$3>=Assumptions!$E$255,I$3>=Assumptions!$B$14,Revenue_Build!I10>=Assumptions!$F$255*Assumptions!$B$51)),Assumptions!$D$255,0) | J40: =IF(OR(I40>0,AND(J$3>=Assumptions!$E$255,J$3>=Assumptions!$B$14,Revenue_Build!J10>=Assumptions!$F$255*Assumptions!$B$51)),Assumptions!$D$255,0) | K40: =IF(OR(J40>0,AND(K$3>=Assumptions!$E$255,K$3>=Assumptions!$B$14,Revenue_Build!K10>=Assumptions!$F$255*Assumptions!$B$51)),Assumptions!$D$255,0) | ... BJ40: =IF(OR(BI40>0,AND(BJ$3>=Assumptions!$E$255,BJ$3>=Assumptions!$B$14,Revenue_Build!BJ10>=Assumptions!$F$255*Assumptions!$B$51)),Assumptions!$D$255,0)
A41: Partnerships managers (scale-up III) | B41: FTE | C41: =IF(AND(C$3>=Assumptions!$E$256,C$3>=Assumptions!$B$14,Revenue_Build!C10>=Assumptions!$F$256*Assumptions!$B$51),Assumptions!$D$256,0) | D41: =IF(OR(C41>0,AND(D$3>=Assumptions!$E$256,D$3>=Assumptions!$B$14,Revenue_Build!D10>=Assumptions!$F$256*Assumptions!$B$51)),Assumptions!$D$256,0) | E41: =IF(OR(D41>0,AND(E$3>=Assumptions!$E$256,E$3>=Assumptions!$B$14,Revenue_Build!E10>=Assumptions!$F$256*Assumptions!$B$51)),Assumptions!$D$256,0) | F41: =IF(OR(E41>0,AND(F$3>=Assumptions!$E$256,F$3>=Assumptions!$B$14,Revenue_Build!F10>=Assumptions!$F$256*Assumptions!$B$51)),Assumptions!$D$256,0) | G41: =IF(OR(F41>0,AND(G$3>=Assumptions!$E$256,G$3>=Assumptions!$B$14,Revenue_Build!G10>=Assumptions!$F$256*Assumptions!$B$51)),Assumptions!$D$256,0) | H41: =IF(OR(G41>0,AND(H$3>=Assumptions!$E$256,H$3>=Assumptions!$B$14,Revenue_Build!H10>=Assumptions!$F$256*Assumptions!$B$51)),Assumptions!$D$256,0) | I41: =IF(OR(H41>0,AND(I$3>=Assumptions!$E$256,I$3>=Assumptions!$B$14,Revenue_Build!I10>=Assumptions!$F$256*Assumptions!$B$51)),Assumptions!$D$256,0) | J41: =IF(OR(I41>0,AND(J$3>=Assumptions!$E$256,J$3>=Assumptions!$B$14,Revenue_Build!J10>=Assumptions!$F$256*Assumptions!$B$51)),Assumptions!$D$256,0) | K41: =IF(OR(J41>0,AND(K$3>=Assumptions!$E$256,K$3>=Assumptions!$B$14,Revenue_Build!K10>=Assumptions!$F$256*Assumptions!$B$51)),Assumptions!$D$256,0) | ... BJ41: =IF(OR(BI41>0,AND(BJ$3>=Assumptions!$E$256,BJ$3>=Assumptions!$B$14,Revenue_Build!BJ10>=Assumptions!$F$256*Assumptions!$B$51)),Assumptions!$D$256,0)
A42: SME account managers II | B42: FTE | C42: =IF(AND(C$3>=Assumptions!$E$257,C$3>=Assumptions!$B$14,Revenue_Build!C10>=Assumptions!$F$257*Assumptions!$B$51),Assumptions!$D$257,0) | D42: =IF(OR(C42>0,AND(D$3>=Assumptions!$E$257,D$3>=Assumptions!$B$14,Revenue_Build!D10>=Assumptions!$F$257*Assumptions!$B$51)),Assumptions!$D$257,0) | E42: =IF(OR(D42>0,AND(E$3>=Assumptions!$E$257,E$3>=Assumptions!$B$14,Revenue_Build!E10>=Assumptions!$F$257*Assumptions!$B$51)),Assumptions!$D$257,0) | F42: =IF(OR(E42>0,AND(F$3>=Assumptions!$E$257,F$3>=Assumptions!$B$14,Revenue_Build!F10>=Assumptions!$F$257*Assumptions!$B$51)),Assumptions!$D$257,0) | G42: =IF(OR(F42>0,AND(G$3>=Assumptions!$E$257,G$3>=Assumptions!$B$14,Revenue_Build!G10>=Assumptions!$F$257*Assumptions!$B$51)),Assumptions!$D$257,0) | H42: =IF(OR(G42>0,AND(H$3>=Assumptions!$E$257,H$3>=Assumptions!$B$14,Revenue_Build!H10>=Assumptions!$F$257*Assumptions!$B$51)),Assumptions!$D$257,0) | I42: =IF(OR(H42>0,AND(I$3>=Assumptions!$E$257,I$3>=Assumptions!$B$14,Revenue_Build!I10>=Assumptions!$F$257*Assumptions!$B$51)),Assumptions!$D$257,0) | J42: =IF(OR(I42>0,AND(J$3>=Assumptions!$E$257,J$3>=Assumptions!$B$14,Revenue_Build!J10>=Assumptions!$F$257*Assumptions!$B$51)),Assumptions!$D$257,0) | K42: =IF(OR(J42>0,AND(K$3>=Assumptions!$E$257,K$3>=Assumptions!$B$14,Revenue_Build!K10>=Assumptions!$F$257*Assumptions!$B$51)),Assumptions!$D$257,0) | ... BJ42: =IF(OR(BI42>0,AND(BJ$3>=Assumptions!$E$257,BJ$3>=Assumptions!$B$14,Revenue_Build!BJ10>=Assumptions!$F$257*Assumptions!$B$51)),Assumptions!$D$257,0)
A43: Customer success lead | B43: FTE | C43: =IF(AND(C$3>=Assumptions!$E$258,C$3>=Assumptions!$B$14,Revenue_Build!C10>=Assumptions!$F$258*Assumptions!$B$51),Assumptions!$D$258,0) | D43: =IF(OR(C43>0,AND(D$3>=Assumptions!$E$258,D$3>=Assumptions!$B$14,Revenue_Build!D10>=Assumptions!$F$258*Assumptions!$B$51)),Assumptions!$D$258,0) | E43: =IF(OR(D43>0,AND(E$3>=Assumptions!$E$258,E$3>=Assumptions!$B$14,Revenue_Build!E10>=Assumptions!$F$258*Assumptions!$B$51)),Assumptions!$D$258,0) | F43: =IF(OR(E43>0,AND(F$3>=Assumptions!$E$258,F$3>=Assumptions!$B$14,Revenue_Build!F10>=Assumptions!$F$258*Assumptions!$B$51)),Assumptions!$D$258,0) | G43: =IF(OR(F43>0,AND(G$3>=Assumptions!$E$258,G$3>=Assumptions!$B$14,Revenue_Build!G10>=Assumptions!$F$258*Assumptions!$B$51)),Assumptions!$D$258,0) | H43: =IF(OR(G43>0,AND(H$3>=Assumptions!$E$258,H$3>=Assumptions!$B$14,Revenue_Build!H10>=Assumptions!$F$258*Assumptions!$B$51)),Assumptions!$D$258,0) | I43: =IF(OR(H43>0,AND(I$3>=Assumptions!$E$258,I$3>=Assumptions!$B$14,Revenue_Build!I10>=Assumptions!$F$258*Assumptions!$B$51)),Assumptions!$D$258,0) | J43: =IF(OR(I43>0,AND(J$3>=Assumptions!$E$258,J$3>=Assumptions!$B$14,Revenue_Build!J10>=Assumptions!$F$258*Assumptions!$B$51)),Assumptions!$D$258,0) | K43: =IF(OR(J43>0,AND(K$3>=Assumptions!$E$258,K$3>=Assumptions!$B$14,Revenue_Build!K10>=Assumptions!$F$258*Assumptions!$B$51)),Assumptions!$D$258,0) | ... BJ43: =IF(OR(BI43>0,AND(BJ$3>=Assumptions!$E$258,BJ$3>=Assumptions!$B$14,Revenue_Build!BJ10>=Assumptions!$F$258*Assumptions!$B$51)),Assumptions!$D$258,0)
A44: CS & onboarding agents | B44: FTE | C44: =IF(AND(C$3>=Assumptions!$E$259,C$3>=Assumptions!$B$14,Revenue_Build!C10>=Assumptions!$F$259*Assumptions!$B$51),Assumptions!$D$259,0) | D44: =IF(OR(C44>0,AND(D$3>=Assumptions!$E$259,D$3>=Assumptions!$B$14,Revenue_Build!D10>=Assumptions!$F$259*Assumptions!$B$51)),Assumptions!$D$259,0) | E44: =IF(OR(D44>0,AND(E$3>=Assumptions!$E$259,E$3>=Assumptions!$B$14,Revenue_Build!E10>=Assumptions!$F$259*Assumptions!$B$51)),Assumptions!$D$259,0) | F44: =IF(OR(E44>0,AND(F$3>=Assumptions!$E$259,F$3>=Assumptions!$B$14,Revenue_Build!F10>=Assumptions!$F$259*Assumptions!$B$51)),Assumptions!$D$259,0) | G44: =IF(OR(F44>0,AND(G$3>=Assumptions!$E$259,G$3>=Assumptions!$B$14,Revenue_Build!G10>=Assumptions!$F$259*Assumptions!$B$51)),Assumptions!$D$259,0) | H44: =IF(OR(G44>0,AND(H$3>=Assumptions!$E$259,H$3>=Assumptions!$B$14,Revenue_Build!H10>=Assumptions!$F$259*Assumptions!$B$51)),Assumptions!$D$259,0) | I44: =IF(OR(H44>0,AND(I$3>=Assumptions!$E$259,I$3>=Assumptions!$B$14,Revenue_Build!I10>=Assumptions!$F$259*Assumptions!$B$51)),Assumptions!$D$259,0) | J44: =IF(OR(I44>0,AND(J$3>=Assumptions!$E$259,J$3>=Assumptions!$B$14,Revenue_Build!J10>=Assumptions!$F$259*Assumptions!$B$51)),Assumptions!$D$259,0) | K44: =IF(OR(J44>0,AND(K$3>=Assumptions!$E$259,K$3>=Assumptions!$B$14,Revenue_Build!K10>=Assumptions!$F$259*Assumptions!$B$51)),Assumptions!$D$259,0) | ... BJ44: =IF(OR(BI44>0,AND(BJ$3>=Assumptions!$E$259,BJ$3>=Assumptions!$B$14,Revenue_Build!BJ10>=Assumptions!$F$259*Assumptions!$B$51)),Assumptions!$D$259,0)
A45: CS agents II | B45: FTE | C45: =IF(AND(C$3>=Assumptions!$E$260,C$3>=Assumptions!$B$14,Revenue_Build!C10>=Assumptions!$F$260*Assumptions!$B$51),Assumptions!$D$260,0) | D45: =IF(OR(C45>0,AND(D$3>=Assumptions!$E$260,D$3>=Assumptions!$B$14,Revenue_Build!D10>=Assumptions!$F$260*Assumptions!$B$51)),Assumptions!$D$260,0) | E45: =IF(OR(D45>0,AND(E$3>=Assumptions!$E$260,E$3>=Assumptions!$B$14,Revenue_Build!E10>=Assumptions!$F$260*Assumptions!$B$51)),Assumptions!$D$260,0) | F45: =IF(OR(E45>0,AND(F$3>=Assumptions!$E$260,F$3>=Assumptions!$B$14,Revenue_Build!F10>=Assumptions!$F$260*Assumptions!$B$51)),Assumptions!$D$260,0) | G45: =IF(OR(F45>0,AND(G$3>=Assumptions!$E$260,G$3>=Assumptions!$B$14,Revenue_Build!G10>=Assumptions!$F$260*Assumptions!$B$51)),Assumptions!$D$260,0) | H45: =IF(OR(G45>0,AND(H$3>=Assumptions!$E$260,H$3>=Assumptions!$B$14,Revenue_Build!H10>=Assumptions!$F$260*Assumptions!$B$51)),Assumptions!$D$260,0) | I45: =IF(OR(H45>0,AND(I$3>=Assumptions!$E$260,I$3>=Assumptions!$B$14,Revenue_Build!I10>=Assumptions!$F$260*Assumptions!$B$51)),Assumptions!$D$260,0) | J45: =IF(OR(I45>0,AND(J$3>=Assumptions!$E$260,J$3>=Assumptions!$B$14,Revenue_Build!J10>=Assumptions!$F$260*Assumptions!$B$51)),Assumptions!$D$260,0) | K45: =IF(OR(J45>0,AND(K$3>=Assumptions!$E$260,K$3>=Assumptions!$B$14,Revenue_Build!K10>=Assumptions!$F$260*Assumptions!$B$51)),Assumptions!$D$260,0) | ... BJ45: =IF(OR(BI45>0,AND(BJ$3>=Assumptions!$E$260,BJ$3>=Assumptions!$B$14,Revenue_Build!BJ10>=Assumptions!$F$260*Assumptions!$B$51)),Assumptions!$D$260,0)
A46: CS agents III | B46: FTE | C46: =IF(AND(C$3>=Assumptions!$E$261,C$3>=Assumptions!$B$14,Revenue_Build!C10>=Assumptions!$F$261*Assumptions!$B$51),Assumptions!$D$261,0) | D46: =IF(OR(C46>0,AND(D$3>=Assumptions!$E$261,D$3>=Assumptions!$B$14,Revenue_Build!D10>=Assumptions!$F$261*Assumptions!$B$51)),Assumptions!$D$261,0) | E46: =IF(OR(D46>0,AND(E$3>=Assumptions!$E$261,E$3>=Assumptions!$B$14,Revenue_Build!E10>=Assumptions!$F$261*Assumptions!$B$51)),Assumptions!$D$261,0) | F46: =IF(OR(E46>0,AND(F$3>=Assumptions!$E$261,F$3>=Assumptions!$B$14,Revenue_Build!F10>=Assumptions!$F$261*Assumptions!$B$51)),Assumptions!$D$261,0) | G46: =IF(OR(F46>0,AND(G$3>=Assumptions!$E$261,G$3>=Assumptions!$B$14,Revenue_Build!G10>=Assumptions!$F$261*Assumptions!$B$51)),Assumptions!$D$261,0) | H46: =IF(OR(G46>0,AND(H$3>=Assumptions!$E$261,H$3>=Assumptions!$B$14,Revenue_Build!H10>=Assumptions!$F$261*Assumptions!$B$51)),Assumptions!$D$261,0) | I46: =IF(OR(H46>0,AND(I$3>=Assumptions!$E$261,I$3>=Assumptions!$B$14,Revenue_Build!I10>=Assumptions!$F$261*Assumptions!$B$51)),Assumptions!$D$261,0) | J46: =IF(OR(I46>0,AND(J$3>=Assumptions!$E$261,J$3>=Assumptions!$B$14,Revenue_Build!J10>=Assumptions!$F$261*Assumptions!$B$51)),Assumptions!$D$261,0) | K46: =IF(OR(J46>0,AND(K$3>=Assumptions!$E$261,K$3>=Assumptions!$B$14,Revenue_Build!K10>=Assumptions!$F$261*Assumptions!$B$51)),Assumptions!$D$261,0) | ... BJ46: =IF(OR(BI46>0,AND(BJ$3>=Assumptions!$E$261,BJ$3>=Assumptions!$B$14,Revenue_Build!BJ10>=Assumptions!$F$261*Assumptions!$B$51)),Assumptions!$D$261,0)
A47: CS agents IV | B47: FTE | C47: =IF(AND(C$3>=Assumptions!$E$262,C$3>=Assumptions!$B$14,Revenue_Build!C10>=Assumptions!$F$262*Assumptions!$B$51),Assumptions!$D$262,0) | D47: =IF(OR(C47>0,AND(D$3>=Assumptions!$E$262,D$3>=Assumptions!$B$14,Revenue_Build!D10>=Assumptions!$F$262*Assumptions!$B$51)),Assumptions!$D$262,0) | E47: =IF(OR(D47>0,AND(E$3>=Assumptions!$E$262,E$3>=Assumptions!$B$14,Revenue_Build!E10>=Assumptions!$F$262*Assumptions!$B$51)),Assumptions!$D$262,0) | F47: =IF(OR(E47>0,AND(F$3>=Assumptions!$E$262,F$3>=Assumptions!$B$14,Revenue_Build!F10>=Assumptions!$F$262*Assumptions!$B$51)),Assumptions!$D$262,0) | G47: =IF(OR(F47>0,AND(G$3>=Assumptions!$E$262,G$3>=Assumptions!$B$14,Revenue_Build!G10>=Assumptions!$F$262*Assumptions!$B$51)),Assumptions!$D$262,0) | H47: =IF(OR(G47>0,AND(H$3>=Assumptions!$E$262,H$3>=Assumptions!$B$14,Revenue_Build!H10>=Assumptions!$F$262*Assumptions!$B$51)),Assumptions!$D$262,0) | I47: =IF(OR(H47>0,AND(I$3>=Assumptions!$E$262,I$3>=Assumptions!$B$14,Revenue_Build!I10>=Assumptions!$F$262*Assumptions!$B$51)),Assumptions!$D$262,0) | J47: =IF(OR(I47>0,AND(J$3>=Assumptions!$E$262,J$3>=Assumptions!$B$14,Revenue_Build!J10>=Assumptions!$F$262*Assumptions!$B$51)),Assumptions!$D$262,0) | K47: =IF(OR(J47>0,AND(K$3>=Assumptions!$E$262,K$3>=Assumptions!$B$14,Revenue_Build!K10>=Assumptions!$F$262*Assumptions!$B$51)),Assumptions!$D$262,0) | ... BJ47: =IF(OR(BI47>0,AND(BJ$3>=Assumptions!$E$262,BJ$3>=Assumptions!$B$14,Revenue_Build!BJ10>=Assumptions!$F$262*Assumptions!$B$51)),Assumptions!$D$262,0)
A48: CS agents V | B48: FTE | C48: =IF(AND(C$3>=Assumptions!$E$263,C$3>=Assumptions!$B$14,Revenue_Build!C10>=Assumptions!$F$263*Assumptions!$B$51),Assumptions!$D$263,0) | D48: =IF(OR(C48>0,AND(D$3>=Assumptions!$E$263,D$3>=Assumptions!$B$14,Revenue_Build!D10>=Assumptions!$F$263*Assumptions!$B$51)),Assumptions!$D$263,0) | E48: =IF(OR(D48>0,AND(E$3>=Assumptions!$E$263,E$3>=Assumptions!$B$14,Revenue_Build!E10>=Assumptions!$F$263*Assumptions!$B$51)),Assumptions!$D$263,0) | F48: =IF(OR(E48>0,AND(F$3>=Assumptions!$E$263,F$3>=Assumptions!$B$14,Revenue_Build!F10>=Assumptions!$F$263*Assumptions!$B$51)),Assumptions!$D$263,0) | G48: =IF(OR(F48>0,AND(G$3>=Assumptions!$E$263,G$3>=Assumptions!$B$14,Revenue_Build!G10>=Assumptions!$F$263*Assumptions!$B$51)),Assumptions!$D$263,0) | H48: =IF(OR(G48>0,AND(H$3>=Assumptions!$E$263,H$3>=Assumptions!$B$14,Revenue_Build!H10>=Assumptions!$F$263*Assumptions!$B$51)),Assumptions!$D$263,0) | I48: =IF(OR(H48>0,AND(I$3>=Assumptions!$E$263,I$3>=Assumptions!$B$14,Revenue_Build!I10>=Assumptions!$F$263*Assumptions!$B$51)),Assumptions!$D$263,0) | J48: =IF(OR(I48>0,AND(J$3>=Assumptions!$E$263,J$3>=Assumptions!$B$14,Revenue_Build!J10>=Assumptions!$F$263*Assumptions!$B$51)),Assumptions!$D$263,0) | K48: =IF(OR(J48>0,AND(K$3>=Assumptions!$E$263,K$3>=Assumptions!$B$14,Revenue_Build!K10>=Assumptions!$F$263*Assumptions!$B$51)),Assumptions!$D$263,0) | ... BJ48: =IF(OR(BI48>0,AND(BJ$3>=Assumptions!$E$263,BJ$3>=Assumptions!$B$14,Revenue_Build!BJ10>=Assumptions!$F$263*Assumptions!$B$51)),Assumptions!$D$263,0)
A49: Finance & compliance manager | B49: FTE | C49: =IF(AND(C$3>=Assumptions!$E$264,C$3>=Assumptions!$B$14,Revenue_Build!C10>=Assumptions!$F$264*Assumptions!$B$51),Assumptions!$D$264,0) | D49: =IF(OR(C49>0,AND(D$3>=Assumptions!$E$264,D$3>=Assumptions!$B$14,Revenue_Build!D10>=Assumptions!$F$264*Assumptions!$B$51)),Assumptions!$D$264,0) | E49: =IF(OR(D49>0,AND(E$3>=Assumptions!$E$264,E$3>=Assumptions!$B$14,Revenue_Build!E10>=Assumptions!$F$264*Assumptions!$B$51)),Assumptions!$D$264,0) | F49: =IF(OR(E49>0,AND(F$3>=Assumptions!$E$264,F$3>=Assumptions!$B$14,Revenue_Build!F10>=Assumptions!$F$264*Assumptions!$B$51)),Assumptions!$D$264,0) | G49: =IF(OR(F49>0,AND(G$3>=Assumptions!$E$264,G$3>=Assumptions!$B$14,Revenue_Build!G10>=Assumptions!$F$264*Assumptions!$B$51)),Assumptions!$D$264,0) | H49: =IF(OR(G49>0,AND(H$3>=Assumptions!$E$264,H$3>=Assumptions!$B$14,Revenue_Build!H10>=Assumptions!$F$264*Assumptions!$B$51)),Assumptions!$D$264,0) | I49: =IF(OR(H49>0,AND(I$3>=Assumptions!$E$264,I$3>=Assumptions!$B$14,Revenue_Build!I10>=Assumptions!$F$264*Assumptions!$B$51)),Assumptions!$D$264,0) | J49: =IF(OR(I49>0,AND(J$3>=Assumptions!$E$264,J$3>=Assumptions!$B$14,Revenue_Build!J10>=Assumptions!$F$264*Assumptions!$B$51)),Assumptions!$D$264,0) | K49: =IF(OR(J49>0,AND(K$3>=Assumptions!$E$264,K$3>=Assumptions!$B$14,Revenue_Build!K10>=Assumptions!$F$264*Assumptions!$B$51)),Assumptions!$D$264,0) | ... BJ49: =IF(OR(BI49>0,AND(BJ$3>=Assumptions!$E$264,BJ$3>=Assumptions!$B$14,Revenue_Build!BJ10>=Assumptions!$F$264*Assumptions!$B$51)),Assumptions!$D$264,0)
A50: Operations & admin | B50: FTE | C50: =IF(AND(C$3>=Assumptions!$E$265,C$3>=Assumptions!$B$14,Revenue_Build!C10>=Assumptions!$F$265*Assumptions!$B$51),Assumptions!$D$265,0) | D50: =IF(OR(C50>0,AND(D$3>=Assumptions!$E$265,D$3>=Assumptions!$B$14,Revenue_Build!D10>=Assumptions!$F$265*Assumptions!$B$51)),Assumptions!$D$265,0) | E50: =IF(OR(D50>0,AND(E$3>=Assumptions!$E$265,E$3>=Assumptions!$B$14,Revenue_Build!E10>=Assumptions!$F$265*Assumptions!$B$51)),Assumptions!$D$265,0) | F50: =IF(OR(E50>0,AND(F$3>=Assumptions!$E$265,F$3>=Assumptions!$B$14,Revenue_Build!F10>=Assumptions!$F$265*Assumptions!$B$51)),Assumptions!$D$265,0) | G50: =IF(OR(F50>0,AND(G$3>=Assumptions!$E$265,G$3>=Assumptions!$B$14,Revenue_Build!G10>=Assumptions!$F$265*Assumptions!$B$51)),Assumptions!$D$265,0) | H50: =IF(OR(G50>0,AND(H$3>=Assumptions!$E$265,H$3>=Assumptions!$B$14,Revenue_Build!H10>=Assumptions!$F$265*Assumptions!$B$51)),Assumptions!$D$265,0) | I50: =IF(OR(H50>0,AND(I$3>=Assumptions!$E$265,I$3>=Assumptions!$B$14,Revenue_Build!I10>=Assumptions!$F$265*Assumptions!$B$51)),Assumptions!$D$265,0) | J50: =IF(OR(I50>0,AND(J$3>=Assumptions!$E$265,J$3>=Assumptions!$B$14,Revenue_Build!J10>=Assumptions!$F$265*Assumptions!$B$51)),Assumptions!$D$265,0) | K50: =IF(OR(J50>0,AND(K$3>=Assumptions!$E$265,K$3>=Assumptions!$B$14,Revenue_Build!K10>=Assumptions!$F$265*Assumptions!$B$51)),Assumptions!$D$265,0) | ... BJ50: =IF(OR(BI50>0,AND(BJ$3>=Assumptions!$E$265,BJ$3>=Assumptions!$B$14,Revenue_Build!BJ10>=Assumptions!$F$265*Assumptions!$B$51)),Assumptions!$D$265,0)
A51: Legal & data-protection counsel | B51: FTE | C51: =IF(AND(C$3>=Assumptions!$E$266,C$3>=Assumptions!$B$14,Revenue_Build!C10>=Assumptions!$F$266*Assumptions!$B$51),Assumptions!$D$266,0) | D51: =IF(OR(C51>0,AND(D$3>=Assumptions!$E$266,D$3>=Assumptions!$B$14,Revenue_Build!D10>=Assumptions!$F$266*Assumptions!$B$51)),Assumptions!$D$266,0) | E51: =IF(OR(D51>0,AND(E$3>=Assumptions!$E$266,E$3>=Assumptions!$B$14,Revenue_Build!E10>=Assumptions!$F$266*Assumptions!$B$51)),Assumptions!$D$266,0) | F51: =IF(OR(E51>0,AND(F$3>=Assumptions!$E$266,F$3>=Assumptions!$B$14,Revenue_Build!F10>=Assumptions!$F$266*Assumptions!$B$51)),Assumptions!$D$266,0) | G51: =IF(OR(F51>0,AND(G$3>=Assumptions!$E$266,G$3>=Assumptions!$B$14,Revenue_Build!G10>=Assumptions!$F$266*Assumptions!$B$51)),Assumptions!$D$266,0) | H51: =IF(OR(G51>0,AND(H$3>=Assumptions!$E$266,H$3>=Assumptions!$B$14,Revenue_Build!H10>=Assumptions!$F$266*Assumptions!$B$51)),Assumptions!$D$266,0) | I51: =IF(OR(H51>0,AND(I$3>=Assumptions!$E$266,I$3>=Assumptions!$B$14,Revenue_Build!I10>=Assumptions!$F$266*Assumptions!$B$51)),Assumptions!$D$266,0) | J51: =IF(OR(I51>0,AND(J$3>=Assumptions!$E$266,J$3>=Assumptions!$B$14,Revenue_Build!J10>=Assumptions!$F$266*Assumptions!$B$51)),Assumptions!$D$266,0) | K51: =IF(OR(J51>0,AND(K$3>=Assumptions!$E$266,K$3>=Assumptions!$B$14,Revenue_Build!K10>=Assumptions!$F$266*Assumptions!$B$51)),Assumptions!$D$266,0) | ... BJ51: =IF(OR(BI51>0,AND(BJ$3>=Assumptions!$E$266,BJ$3>=Assumptions!$B$14,Revenue_Build!BJ10>=Assumptions!$F$266*Assumptions!$B$51)),Assumptions!$D$266,0)
A52: People & HR partner | B52: FTE | C52: =IF(AND(C$3>=Assumptions!$E$267,C$3>=Assumptions!$B$14,Revenue_Build!C10>=Assumptions!$F$267*Assumptions!$B$51),Assumptions!$D$267,0) | D52: =IF(OR(C52>0,AND(D$3>=Assumptions!$E$267,D$3>=Assumptions!$B$14,Revenue_Build!D10>=Assumptions!$F$267*Assumptions!$B$51)),Assumptions!$D$267,0) | E52: =IF(OR(D52>0,AND(E$3>=Assumptions!$E$267,E$3>=Assumptions!$B$14,Revenue_Build!E10>=Assumptions!$F$267*Assumptions!$B$51)),Assumptions!$D$267,0) | F52: =IF(OR(E52>0,AND(F$3>=Assumptions!$E$267,F$3>=Assumptions!$B$14,Revenue_Build!F10>=Assumptions!$F$267*Assumptions!$B$51)),Assumptions!$D$267,0) | G52: =IF(OR(F52>0,AND(G$3>=Assumptions!$E$267,G$3>=Assumptions!$B$14,Revenue_Build!G10>=Assumptions!$F$267*Assumptions!$B$51)),Assumptions!$D$267,0) | H52: =IF(OR(G52>0,AND(H$3>=Assumptions!$E$267,H$3>=Assumptions!$B$14,Revenue_Build!H10>=Assumptions!$F$267*Assumptions!$B$51)),Assumptions!$D$267,0) | I52: =IF(OR(H52>0,AND(I$3>=Assumptions!$E$267,I$3>=Assumptions!$B$14,Revenue_Build!I10>=Assumptions!$F$267*Assumptions!$B$51)),Assumptions!$D$267,0) | J52: =IF(OR(I52>0,AND(J$3>=Assumptions!$E$267,J$3>=Assumptions!$B$14,Revenue_Build!J10>=Assumptions!$F$267*Assumptions!$B$51)),Assumptions!$D$267,0) | K52: =IF(OR(J52>0,AND(K$3>=Assumptions!$E$267,K$3>=Assumptions!$B$14,Revenue_Build!K10>=Assumptions!$F$267*Assumptions!$B$51)),Assumptions!$D$267,0) | ... BJ52: =IF(OR(BI52>0,AND(BJ$3>=Assumptions!$E$267,BJ$3>=Assumptions!$B$14,Revenue_Build!BJ10>=Assumptions!$F$267*Assumptions!$B$51)),Assumptions!$D$267,0)
A53: Finance analyst | B53: FTE | C53: =IF(AND(C$3>=Assumptions!$E$268,C$3>=Assumptions!$B$14,Revenue_Build!C10>=Assumptions!$F$268*Assumptions!$B$51),Assumptions!$D$268,0) | D53: =IF(OR(C53>0,AND(D$3>=Assumptions!$E$268,D$3>=Assumptions!$B$14,Revenue_Build!D10>=Assumptions!$F$268*Assumptions!$B$51)),Assumptions!$D$268,0) | E53: =IF(OR(D53>0,AND(E$3>=Assumptions!$E$268,E$3>=Assumptions!$B$14,Revenue_Build!E10>=Assumptions!$F$268*Assumptions!$B$51)),Assumptions!$D$268,0) | F53: =IF(OR(E53>0,AND(F$3>=Assumptions!$E$268,F$3>=Assumptions!$B$14,Revenue_Build!F10>=Assumptions!$F$268*Assumptions!$B$51)),Assumptions!$D$268,0) | G53: =IF(OR(F53>0,AND(G$3>=Assumptions!$E$268,G$3>=Assumptions!$B$14,Revenue_Build!G10>=Assumptions!$F$268*Assumptions!$B$51)),Assumptions!$D$268,0) | H53: =IF(OR(G53>0,AND(H$3>=Assumptions!$E$268,H$3>=Assumptions!$B$14,Revenue_Build!H10>=Assumptions!$F$268*Assumptions!$B$51)),Assumptions!$D$268,0) | I53: =IF(OR(H53>0,AND(I$3>=Assumptions!$E$268,I$3>=Assumptions!$B$14,Revenue_Build!I10>=Assumptions!$F$268*Assumptions!$B$51)),Assumptions!$D$268,0) | J53: =IF(OR(I53>0,AND(J$3>=Assumptions!$E$268,J$3>=Assumptions!$B$14,Revenue_Build!J10>=Assumptions!$F$268*Assumptions!$B$51)),Assumptions!$D$268,0) | K53: =IF(OR(J53>0,AND(K$3>=Assumptions!$E$268,K$3>=Assumptions!$B$14,Revenue_Build!K10>=Assumptions!$F$268*Assumptions!$B$51)),Assumptions!$D$268,0) | ... BJ53: =IF(OR(BI53>0,AND(BJ$3>=Assumptions!$E$268,BJ$3>=Assumptions!$B$14,Revenue_Build!BJ10>=Assumptions!$F$268*Assumptions!$B$51)),Assumptions!$D$268,0)
A54: CFO | B54: FTE | C54: =IF(AND(C$3>=Assumptions!$E$269,C$3>=Assumptions!$B$14,Revenue_Build!C10>=Assumptions!$F$269*Assumptions!$B$51),Assumptions!$D$269,0) | D54: =IF(OR(C54>0,AND(D$3>=Assumptions!$E$269,D$3>=Assumptions!$B$14,Revenue_Build!D10>=Assumptions!$F$269*Assumptions!$B$51)),Assumptions!$D$269,0) | E54: =IF(OR(D54>0,AND(E$3>=Assumptions!$E$269,E$3>=Assumptions!$B$14,Revenue_Build!E10>=Assumptions!$F$269*Assumptions!$B$51)),Assumptions!$D$269,0) | F54: =IF(OR(E54>0,AND(F$3>=Assumptions!$E$269,F$3>=Assumptions!$B$14,Revenue_Build!F10>=Assumptions!$F$269*Assumptions!$B$51)),Assumptions!$D$269,0) | G54: =IF(OR(F54>0,AND(G$3>=Assumptions!$E$269,G$3>=Assumptions!$B$14,Revenue_Build!G10>=Assumptions!$F$269*Assumptions!$B$51)),Assumptions!$D$269,0) | H54: =IF(OR(G54>0,AND(H$3>=Assumptions!$E$269,H$3>=Assumptions!$B$14,Revenue_Build!H10>=Assumptions!$F$269*Assumptions!$B$51)),Assumptions!$D$269,0) | I54: =IF(OR(H54>0,AND(I$3>=Assumptions!$E$269,I$3>=Assumptions!$B$14,Revenue_Build!I10>=Assumptions!$F$269*Assumptions!$B$51)),Assumptions!$D$269,0) | J54: =IF(OR(I54>0,AND(J$3>=Assumptions!$E$269,J$3>=Assumptions!$B$14,Revenue_Build!J10>=Assumptions!$F$269*Assumptions!$B$51)),Assumptions!$D$269,0) | K54: =IF(OR(J54>0,AND(K$3>=Assumptions!$E$269,K$3>=Assumptions!$B$14,Revenue_Build!K10>=Assumptions!$F$269*Assumptions!$B$51)),Assumptions!$D$269,0) | ... BJ54: =IF(OR(BI54>0,AND(BJ$3>=Assumptions!$E$269,BJ$3>=Assumptions!$B$14,Revenue_Build!BJ10>=Assumptions!$F$269*Assumptions!$B$51)),Assumptions!$D$269,0)
A55: CS agents VI | B55: FTE | C55: =IF(AND(C$3>=Assumptions!$E$270,C$3>=Assumptions!$B$14,Revenue_Build!C10>=Assumptions!$F$270*Assumptions!$B$51),Assumptions!$D$270,0) | D55: =IF(OR(C55>0,AND(D$3>=Assumptions!$E$270,D$3>=Assumptions!$B$14,Revenue_Build!D10>=Assumptions!$F$270*Assumptions!$B$51)),Assumptions!$D$270,0) | E55: =IF(OR(D55>0,AND(E$3>=Assumptions!$E$270,E$3>=Assumptions!$B$14,Revenue_Build!E10>=Assumptions!$F$270*Assumptions!$B$51)),Assumptions!$D$270,0) | F55: =IF(OR(E55>0,AND(F$3>=Assumptions!$E$270,F$3>=Assumptions!$B$14,Revenue_Build!F10>=Assumptions!$F$270*Assumptions!$B$51)),Assumptions!$D$270,0) | G55: =IF(OR(F55>0,AND(G$3>=Assumptions!$E$270,G$3>=Assumptions!$B$14,Revenue_Build!G10>=Assumptions!$F$270*Assumptions!$B$51)),Assumptions!$D$270,0) | H55: =IF(OR(G55>0,AND(H$3>=Assumptions!$E$270,H$3>=Assumptions!$B$14,Revenue_Build!H10>=Assumptions!$F$270*Assumptions!$B$51)),Assumptions!$D$270,0) | I55: =IF(OR(H55>0,AND(I$3>=Assumptions!$E$270,I$3>=Assumptions!$B$14,Revenue_Build!I10>=Assumptions!$F$270*Assumptions!$B$51)),Assumptions!$D$270,0) | J55: =IF(OR(I55>0,AND(J$3>=Assumptions!$E$270,J$3>=Assumptions!$B$14,Revenue_Build!J10>=Assumptions!$F$270*Assumptions!$B$51)),Assumptions!$D$270,0) | K55: =IF(OR(J55>0,AND(K$3>=Assumptions!$E$270,K$3>=Assumptions!$B$14,Revenue_Build!K10>=Assumptions!$F$270*Assumptions!$B$51)),Assumptions!$D$270,0) | ... BJ55: =IF(OR(BI55>0,AND(BJ$3>=Assumptions!$E$270,BJ$3>=Assumptions!$B$14,Revenue_Build!BJ10>=Assumptions!$F$270*Assumptions!$B$51)),Assumptions!$D$270,0)
A56: Finance, legal & people team expansion | B56: FTE | C56: =IF(AND(C$3>=Assumptions!$E$271,C$3>=Assumptions!$B$14,Revenue_Build!C10>=Assumptions!$F$271*Assumptions!$B$51),Assumptions!$D$271,0) | D56: =IF(OR(C56>0,AND(D$3>=Assumptions!$E$271,D$3>=Assumptions!$B$14,Revenue_Build!D10>=Assumptions!$F$271*Assumptions!$B$51)),Assumptions!$D$271,0) | E56: =IF(OR(D56>0,AND(E$3>=Assumptions!$E$271,E$3>=Assumptions!$B$14,Revenue_Build!E10>=Assumptions!$F$271*Assumptions!$B$51)),Assumptions!$D$271,0) | F56: =IF(OR(E56>0,AND(F$3>=Assumptions!$E$271,F$3>=Assumptions!$B$14,Revenue_Build!F10>=Assumptions!$F$271*Assumptions!$B$51)),Assumptions!$D$271,0) | G56: =IF(OR(F56>0,AND(G$3>=Assumptions!$E$271,G$3>=Assumptions!$B$14,Revenue_Build!G10>=Assumptions!$F$271*Assumptions!$B$51)),Assumptions!$D$271,0) | H56: =IF(OR(G56>0,AND(H$3>=Assumptions!$E$271,H$3>=Assumptions!$B$14,Revenue_Build!H10>=Assumptions!$F$271*Assumptions!$B$51)),Assumptions!$D$271,0) | I56: =IF(OR(H56>0,AND(I$3>=Assumptions!$E$271,I$3>=Assumptions!$B$14,Revenue_Build!I10>=Assumptions!$F$271*Assumptions!$B$51)),Assumptions!$D$271,0) | J56: =IF(OR(I56>0,AND(J$3>=Assumptions!$E$271,J$3>=Assumptions!$B$14,Revenue_Build!J10>=Assumptions!$F$271*Assumptions!$B$51)),Assumptions!$D$271,0) | K56: =IF(OR(J56>0,AND(K$3>=Assumptions!$E$271,K$3>=Assumptions!$B$14,Revenue_Build!K10>=Assumptions!$F$271*Assumptions!$B$51)),Assumptions!$D$271,0) | ... BJ56: =IF(OR(BI56>0,AND(BJ$3>=Assumptions!$E$271,BJ$3>=Assumptions!$B$14,Revenue_Build!BJ10>=Assumptions!$F$271*Assumptions!$B$51)),Assumptions!$D$271,0)
A57: Country lead: Nigeria | B57: FTE | C57: =IF(Revenue_Build!C14=1,Assumptions!$D$272,0) | D57: =IF(Revenue_Build!D14=1,Assumptions!$D$272,0) | E57: =IF(Revenue_Build!E14=1,Assumptions!$D$272,0) | F57: =IF(Revenue_Build!F14=1,Assumptions!$D$272,0) | G57: =IF(Revenue_Build!G14=1,Assumptions!$D$272,0) | H57: =IF(Revenue_Build!H14=1,Assumptions!$D$272,0) | I57: =IF(Revenue_Build!I14=1,Assumptions!$D$272,0) | J57: =IF(Revenue_Build!J14=1,Assumptions!$D$272,0) | ... BJ57: =IF(Revenue_Build!BJ14=1,Assumptions!$D$272,0)
A58: Nigeria sales & CS | B58: FTE | C58: =IF(Revenue_Build!C15=1,Assumptions!$D$273,0) | D58: =IF(Revenue_Build!D15=1,Assumptions!$D$273,0) | E58: =IF(Revenue_Build!E15=1,Assumptions!$D$273,0) | F58: =IF(Revenue_Build!F15=1,Assumptions!$D$273,0) | G58: =IF(Revenue_Build!G15=1,Assumptions!$D$273,0) | H58: =IF(Revenue_Build!H15=1,Assumptions!$D$273,0) | I58: =IF(Revenue_Build!I15=1,Assumptions!$D$273,0) | J58: =IF(Revenue_Build!J15=1,Assumptions!$D$273,0) | ... BJ58: =IF(Revenue_Build!BJ15=1,Assumptions!$D$273,0)
A59: Nigeria team expansion | B59: FTE | C59: =0 | D59: =0 | E59: =0 | F59: =0 | G59: =0 | H59: =0 | I59: =0 | J59: =0 | ... N59: =0 | O59: =IF(Revenue_Build!C15=1,Assumptions!$D$274,0) | P59: =IF(Revenue_Build!D15=1,Assumptions!$D$274,0) | Q59: =IF(Revenue_Build!E15=1,Assumptions!$D$274,0) | R59: =IF(Revenue_Build!F15=1,Assumptions!$D$274,0) | S59: =IF(Revenue_Build!G15=1,Assumptions!$D$274,0) | T59: =IF(Revenue_Build!H15=1,Assumptions!$D$274,0) | U59: =IF(Revenue_Build!I15=1,Assumptions!$D$274,0) | V59: =IF(Revenue_Build!J15=1,Assumptions!$D$274,0) | ... BJ59: =IF(Revenue_Build!AX15=1,Assumptions!$D$274,0)
A60: Country lead: Kenya | B60: FTE | C60: =IF(Revenue_Build!C16=1,Assumptions!$D$275,0) | D60: =IF(Revenue_Build!D16=1,Assumptions!$D$275,0) | E60: =IF(Revenue_Build!E16=1,Assumptions!$D$275,0) | F60: =IF(Revenue_Build!F16=1,Assumptions!$D$275,0) | G60: =IF(Revenue_Build!G16=1,Assumptions!$D$275,0) | H60: =IF(Revenue_Build!H16=1,Assumptions!$D$275,0) | I60: =IF(Revenue_Build!I16=1,Assumptions!$D$275,0) | J60: =IF(Revenue_Build!J16=1,Assumptions!$D$275,0) | ... BJ60: =IF(Revenue_Build!BJ16=1,Assumptions!$D$275,0)
A61: Kenya sales & CS | B61: FTE | C61: =IF(Revenue_Build!C17=1,Assumptions!$D$276,0) | D61: =IF(Revenue_Build!D17=1,Assumptions!$D$276,0) | E61: =IF(Revenue_Build!E17=1,Assumptions!$D$276,0) | F61: =IF(Revenue_Build!F17=1,Assumptions!$D$276,0) | G61: =IF(Revenue_Build!G17=1,Assumptions!$D$276,0) | H61: =IF(Revenue_Build!H17=1,Assumptions!$D$276,0) | I61: =IF(Revenue_Build!I17=1,Assumptions!$D$276,0) | J61: =IF(Revenue_Build!J17=1,Assumptions!$D$276,0) | ... BJ61: =IF(Revenue_Build!BJ17=1,Assumptions!$D$276,0)
A62: Kenya team expansion | B62: FTE | C62: =0 | D62: =0 | E62: =0 | F62: =0 | G62: =0 | H62: =0 | I62: =0 | J62: =0 | ... N62: =0 | O62: =IF(Revenue_Build!C17=1,Assumptions!$D$277,0) | P62: =IF(Revenue_Build!D17=1,Assumptions!$D$277,0) | Q62: =IF(Revenue_Build!E17=1,Assumptions!$D$277,0) | R62: =IF(Revenue_Build!F17=1,Assumptions!$D$277,0) | S62: =IF(Revenue_Build!G17=1,Assumptions!$D$277,0) | T62: =IF(Revenue_Build!H17=1,Assumptions!$D$277,0) | U62: =IF(Revenue_Build!I17=1,Assumptions!$D$277,0) | V62: =IF(Revenue_Build!J17=1,Assumptions!$D$277,0) | ... BJ62: =IF(Revenue_Build!AX17=1,Assumptions!$D$277,0)
A63: Country lead: Ghana | B63: FTE | C63: =IF(Revenue_Build!C18=1,Assumptions!$D$278,0) | D63: =IF(Revenue_Build!D18=1,Assumptions!$D$278,0) | E63: =IF(Revenue_Build!E18=1,Assumptions!$D$278,0) | F63: =IF(Revenue_Build!F18=1,Assumptions!$D$278,0) | G63: =IF(Revenue_Build!G18=1,Assumptions!$D$278,0) | H63: =IF(Revenue_Build!H18=1,Assumptions!$D$278,0) | I63: =IF(Revenue_Build!I18=1,Assumptions!$D$278,0) | J63: =IF(Revenue_Build!J18=1,Assumptions!$D$278,0) | ... BJ63: =IF(Revenue_Build!BJ18=1,Assumptions!$D$278,0)
A64: Ghana sales & CS | B64: FTE | C64: =IF(Revenue_Build!C19=1,Assumptions!$D$279,0) | D64: =IF(Revenue_Build!D19=1,Assumptions!$D$279,0) | E64: =IF(Revenue_Build!E19=1,Assumptions!$D$279,0) | F64: =IF(Revenue_Build!F19=1,Assumptions!$D$279,0) | G64: =IF(Revenue_Build!G19=1,Assumptions!$D$279,0) | H64: =IF(Revenue_Build!H19=1,Assumptions!$D$279,0) | I64: =IF(Revenue_Build!I19=1,Assumptions!$D$279,0) | J64: =IF(Revenue_Build!J19=1,Assumptions!$D$279,0) | ... BJ64: =IF(Revenue_Build!BJ19=1,Assumptions!$D$279,0)
A65: Ghana team expansion | B65: FTE | C65: =0 | D65: =0 | E65: =0 | F65: =0 | G65: =0 | H65: =0 | I65: =0 | J65: =0 | ... N65: =0 | O65: =IF(Revenue_Build!C19=1,Assumptions!$D$280,0) | P65: =IF(Revenue_Build!D19=1,Assumptions!$D$280,0) | Q65: =IF(Revenue_Build!E19=1,Assumptions!$D$280,0) | R65: =IF(Revenue_Build!F19=1,Assumptions!$D$280,0) | S65: =IF(Revenue_Build!G19=1,Assumptions!$D$280,0) | T65: =IF(Revenue_Build!H19=1,Assumptions!$D$280,0) | U65: =IF(Revenue_Build!I19=1,Assumptions!$D$280,0) | V65: =IF(Revenue_Build!J19=1,Assumptions!$D$280,0) | ... BJ65: =IF(Revenue_Build!AX19=1,Assumptions!$D$280,0)
A67: FTEs by department
A68: Leadership | B68: FTE | C68: =C8+C9 | D68: =D8+D9 | E68: =E8+E9 | F68: =F8+F9 | G68: =G8+G9 | H68: =H8+H9 | I68: =I8+I9 | J68: =J8+J9 | ... BJ68: =BJ8+BJ9
A69: Engineering & product | B69: FTE | C69: =C10+C11+C12+C13+C14+C15+C16+C17+C18+C19+C20+C21+C22+C23+C24+C25+C26 | D69: =D10+D11+D12+D13+D14+D15+D16+D17+D18+D19+D20+D21+D22+D23+D24+D25+D26 | E69: =E10+E11+E12+E13+E14+E15+E16+E17+E18+E19+E20+E21+E22+E23+E24+E25+E26 | F69: =F10+F11+F12+F13+F14+F15+F16+F17+F18+F19+F20+F21+F22+F23+F24+F25+F26 | G69: =G10+G11+G12+G13+G14+G15+G16+G17+G18+G19+G20+G21+G22+G23+G24+G25+G26 | H69: =H10+H11+H12+H13+H14+H15+H16+H17+H18+H19+H20+H21+H22+H23+H24+H25+H26 | I69: =I10+I11+I12+I13+I14+I15+I16+I17+I18+I19+I20+I21+I22+I23+I24+I25+I26 | J69: =J10+J11+J12+J13+J14+J15+J16+J17+J18+J19+J20+J21+J22+J23+J24+J25+J26 | ... BJ69: =BJ10+BJ11+BJ12+BJ13+BJ14+BJ15+BJ16+BJ17+BJ18+BJ19+BJ20+BJ21+BJ22+BJ23+BJ24+BJ25+BJ26
A70: Marketing | B70: FTE | C70: =C27+C28+C29+C30+C31+C32+C33 | D70: =D27+D28+D29+D30+D31+D32+D33 | E70: =E27+E28+E29+E30+E31+E32+E33 | F70: =F27+F28+F29+F30+F31+F32+F33 | G70: =G27+G28+G29+G30+G31+G32+G33 | H70: =H27+H28+H29+H30+H31+H32+H33 | I70: =I27+I28+I29+I30+I31+I32+I33 | J70: =J27+J28+J29+J30+J31+J32+J33 | ... BJ70: =BJ27+BJ28+BJ29+BJ30+BJ31+BJ32+BJ33
A71: Sales & partnerships | B71: FTE | C71: =C34+C35+C36+C37+C38+C39+C40+C41+C42 | D71: =D34+D35+D36+D37+D38+D39+D40+D41+D42 | E71: =E34+E35+E36+E37+E38+E39+E40+E41+E42 | F71: =F34+F35+F36+F37+F38+F39+F40+F41+F42 | G71: =G34+G35+G36+G37+G38+G39+G40+G41+G42 | H71: =H34+H35+H36+H37+H38+H39+H40+H41+H42 | I71: =I34+I35+I36+I37+I38+I39+I40+I41+I42 | J71: =J34+J35+J36+J37+J38+J39+J40+J41+J42 | ... BJ71: =BJ34+BJ35+BJ36+BJ37+BJ38+BJ39+BJ40+BJ41+BJ42
A72: Customer success | B72: FTE | C72: =C43+C44+C45+C46+C47+C48+C55 | D72: =D43+D44+D45+D46+D47+D48+D55 | E72: =E43+E44+E45+E46+E47+E48+E55 | F72: =F43+F44+F45+F46+F47+F48+F55 | G72: =G43+G44+G45+G46+G47+G48+G55 | H72: =H43+H44+H45+H46+H47+H48+H55 | I72: =I43+I44+I45+I46+I47+I48+I55 | J72: =J43+J44+J45+J46+J47+J48+J55 | ... BJ72: =BJ43+BJ44+BJ45+BJ46+BJ47+BJ48+BJ55
A73: G&A & compliance | B73: FTE | C73: =C49+C50+C51+C52+C53+C54+C56 | D73: =D49+D50+D51+D52+D53+D54+D56 | E73: =E49+E50+E51+E52+E53+E54+E56 | F73: =F49+F50+F51+F52+F53+F54+F56 | G73: =G49+G50+G51+G52+G53+G54+G56 | H73: =H49+H50+H51+H52+H53+H54+H56 | I73: =I49+I50+I51+I52+I53+I54+I56 | J73: =J49+J50+J51+J52+J53+J54+J56 | ... BJ73: =BJ49+BJ50+BJ51+BJ52+BJ53+BJ54+BJ56
A74: Country teams | B74: FTE | C74: =C57+C58+C59+C60+C61+C62+C63+C64+C65 | D74: =D57+D58+D59+D60+D61+D62+D63+D64+D65 | E74: =E57+E58+E59+E60+E61+E62+E63+E64+E65 | F74: =F57+F58+F59+F60+F61+F62+F63+F64+F65 | G74: =G57+G58+G59+G60+G61+G62+G63+G64+G65 | H74: =H57+H58+H59+H60+H61+H62+H63+H64+H65 | I74: =I57+I58+I59+I60+I61+I62+I63+I64+I65 | J74: =J57+J58+J59+J60+J61+J62+J63+J64+J65 | ... BJ74: =BJ57+BJ58+BJ59+BJ60+BJ61+BJ62+BJ63+BJ64+BJ65
A75: Total headcount | B75: FTE | C75: =C68+C69+C70+C71+C72+C73+C74 | D75: =D68+D69+D70+D71+D72+D73+D74 | E75: =E68+E69+E70+E71+E72+E73+E74 | F75: =F68+F69+F70+F71+F72+F73+F74 | G75: =G68+G69+G70+G71+G72+G73+G74 | H75: =H68+H69+H70+H71+H72+H73+H74 | I75: =I68+I69+I70+I71+I72+I73+I74 | J75: =J68+J69+J70+J71+J72+J73+J74 | ... BJ75: =BJ68+BJ69+BJ70+BJ71+BJ72+BJ73+BJ74
A76: New hires in month | B76: FTE | C76: =MAX(0,C75) | D76: =MAX(0,D75-C75) | E76: =MAX(0,E75-D75) | F76: =MAX(0,F75-E75) | G76: =MAX(0,G75-F75) | H76: =MAX(0,H75-G75) | I76: =MAX(0,I75-H75) | J76: =MAX(0,J75-I75) | K76: =MAX(0,K75-J75) | ... BJ76: =MAX(0,BJ75-BI75)
A77: Partnerships managers active (SA agency programme) | B77: FTE | C77: =C34+C35+C36+C37+C41 | D77: =D34+D35+D36+D37+D41 | E77: =E34+E35+E36+E37+E41 | F77: =F34+F35+F36+F37+F41 | G77: =G34+G35+G36+G37+G41 | H77: =H34+H35+H36+H37+H41 | I77: =I34+I35+I36+I37+I41 | J77: =J34+J35+J36+J37+J41 | ... BJ77: =BJ34+BJ35+BJ36+BJ37+BJ41
A78: Country lead active: Nigeria | B78: FTE | C78: =C57 | D78: =D57 | E78: =E57 | F78: =F57 | G78: =G57 | H78: =H57 | I78: =I57 | J78: =J57 | ... BJ78: =BJ57
A79: Country lead active: Kenya | B79: FTE | C79: =C60 | D79: =D60 | E79: =E60 | F79: =F60 | G79: =G60 | H79: =H60 | I79: =I60 | J79: =J60 | ... BJ79: =BJ60
A80: Country lead active: Ghana | B80: FTE | C80: =C63 | D80: =D63 | E80: =E63 | F80: =F63 | G80: =G63 | H80: =H63 | I80: =I63 | J80: =J63 | ... BJ80: =BJ63
A82: Payroll cost by role (cost-to-company incl. on-costs, escalated annually)
A83: Salary escalation factor | B83: x | C83: =(1+Assumptions!$B$190)^(C$5-1) | D83: =(1+Assumptions!$B$190)^(D$5-1) | E83: =(1+Assumptions!$B$190)^(E$5-1) | F83: =(1+Assumptions!$B$190)^(F$5-1) | G83: =(1+Assumptions!$B$190)^(G$5-1) | H83: =(1+Assumptions!$B$190)^(H$5-1) | I83: =(1+Assumptions!$B$190)^(I$5-1) | J83: =(1+Assumptions!$B$190)^(J$5-1) | ... BJ83: =(1+Assumptions!$B$190)^(BJ$5-1)
A84: Founder & CEO (reduced salary) | B84: R | C84: =C8*Assumptions!$B$223*C83*(1+Assumptions!$B$191) | D84: =D8*Assumptions!$B$223*D83*(1+Assumptions!$B$191) | E84: =E8*Assumptions!$B$223*E83*(1+Assumptions!$B$191) | F84: =F8*Assumptions!$B$223*F83*(1+Assumptions!$B$191) | G84: =G8*Assumptions!$B$223*G83*(1+Assumptions!$B$191) | H84: =H8*Assumptions!$B$223*H83*(1+Assumptions!$B$191) | I84: =I8*Assumptions!$B$223*I83*(1+Assumptions!$B$191) | J84: =J8*Assumptions!$B$223*J83*(1+Assumptions!$B$191) | ... BJ84: =BJ8*Assumptions!$B$223*BJ83*(1+Assumptions!$B$191)
A85: CTO / founding engineer (reduced salary) | B85: R | C85: =C9*Assumptions!$B$224*C83*(1+Assumptions!$B$191) | D85: =D9*Assumptions!$B$224*D83*(1+Assumptions!$B$191) | E85: =E9*Assumptions!$B$224*E83*(1+Assumptions!$B$191) | F85: =F9*Assumptions!$B$224*F83*(1+Assumptions!$B$191) | G85: =G9*Assumptions!$B$224*G83*(1+Assumptions!$B$191) | H85: =H9*Assumptions!$B$224*H83*(1+Assumptions!$B$191) | I85: =I9*Assumptions!$B$224*I83*(1+Assumptions!$B$191) | J85: =J9*Assumptions!$B$224*J83*(1+Assumptions!$B$191) | ... BJ85: =BJ9*Assumptions!$B$224*BJ83*(1+Assumptions!$B$191)
A86: Senior full-stack engineers | B86: R | C86: =C10*Assumptions!$B$225*C83*(1+Assumptions!$B$191) | D86: =D10*Assumptions!$B$225*D83*(1+Assumptions!$B$191) | E86: =E10*Assumptions!$B$225*E83*(1+Assumptions!$B$191) | F86: =F10*Assumptions!$B$225*F83*(1+Assumptions!$B$191) | G86: =G10*Assumptions!$B$225*G83*(1+Assumptions!$B$191) | H86: =H10*Assumptions!$B$225*H83*(1+Assumptions!$B$191) | I86: =I10*Assumptions!$B$225*I83*(1+Assumptions!$B$191) | J86: =J10*Assumptions!$B$225*J83*(1+Assumptions!$B$191) | ... BJ86: =BJ10*Assumptions!$B$225*BJ83*(1+Assumptions!$B$191)
A87: AI / ML engineer | B87: R | C87: =C11*Assumptions!$B$226*C83*(1+Assumptions!$B$191) | D87: =D11*Assumptions!$B$226*D83*(1+Assumptions!$B$191) | E87: =E11*Assumptions!$B$226*E83*(1+Assumptions!$B$191) | F87: =F11*Assumptions!$B$226*F83*(1+Assumptions!$B$191) | G87: =G11*Assumptions!$B$226*G83*(1+Assumptions!$B$191) | H87: =H11*Assumptions!$B$226*H83*(1+Assumptions!$B$191) | I87: =I11*Assumptions!$B$226*I83*(1+Assumptions!$B$191) | J87: =J11*Assumptions!$B$226*J83*(1+Assumptions!$B$191) | ... BJ87: =BJ11*Assumptions!$B$226*BJ83*(1+Assumptions!$B$191)
A88: Product designer (UX) | B88: R | C88: =C12*Assumptions!$B$227*C83*(1+Assumptions!$B$191) | D88: =D12*Assumptions!$B$227*D83*(1+Assumptions!$B$191) | E88: =E12*Assumptions!$B$227*E83*(1+Assumptions!$B$191) | F88: =F12*Assumptions!$B$227*F83*(1+Assumptions!$B$191) | G88: =G12*Assumptions!$B$227*G83*(1+Assumptions!$B$191) | H88: =H12*Assumptions!$B$227*H83*(1+Assumptions!$B$191) | I88: =I12*Assumptions!$B$227*I83*(1+Assumptions!$B$191) | J88: =J12*Assumptions!$B$227*J83*(1+Assumptions!$B$191) | ... BJ88: =BJ12*Assumptions!$B$227*BJ83*(1+Assumptions!$B$191)
A89: Full-stack engineers | B89: R | C89: =C13*Assumptions!$B$228*C83*(1+Assumptions!$B$191) | D89: =D13*Assumptions!$B$228*D83*(1+Assumptions!$B$191) | E89: =E13*Assumptions!$B$228*E83*(1+Assumptions!$B$191) | F89: =F13*Assumptions!$B$228*F83*(1+Assumptions!$B$191) | G89: =G13*Assumptions!$B$228*G83*(1+Assumptions!$B$191) | H89: =H13*Assumptions!$B$228*H83*(1+Assumptions!$B$191) | I89: =I13*Assumptions!$B$228*I83*(1+Assumptions!$B$191) | J89: =J13*Assumptions!$B$228*J83*(1+Assumptions!$B$191) | ... BJ89: =BJ13*Assumptions!$B$228*BJ83*(1+Assumptions!$B$191)
A90: DevOps / QA engineer | B90: R | C90: =C14*Assumptions!$B$229*C83*(1+Assumptions!$B$191) | D90: =D14*Assumptions!$B$229*D83*(1+Assumptions!$B$191) | E90: =E14*Assumptions!$B$229*E83*(1+Assumptions!$B$191) | F90: =F14*Assumptions!$B$229*F83*(1+Assumptions!$B$191) | G90: =G14*Assumptions!$B$229*G83*(1+Assumptions!$B$191) | H90: =H14*Assumptions!$B$229*H83*(1+Assumptions!$B$191) | I90: =I14*Assumptions!$B$229*I83*(1+Assumptions!$B$191) | J90: =J14*Assumptions!$B$229*J83*(1+Assumptions!$B$191) | ... BJ90: =BJ14*Assumptions!$B$229*BJ83*(1+Assumptions!$B$191)
A91: Integrations engineers (social adapters, commerce, CRM) | B91: R | C91: =C15*Assumptions!$B$230*C83*(1+Assumptions!$B$191) | D91: =D15*Assumptions!$B$230*D83*(1+Assumptions!$B$191) | E91: =E15*Assumptions!$B$230*E83*(1+Assumptions!$B$191) | F91: =F15*Assumptions!$B$230*F83*(1+Assumptions!$B$191) | G91: =G15*Assumptions!$B$230*G83*(1+Assumptions!$B$191) | H91: =H15*Assumptions!$B$230*H83*(1+Assumptions!$B$191) | I91: =I15*Assumptions!$B$230*I83*(1+Assumptions!$B$191) | J91: =J15*Assumptions!$B$230*J83*(1+Assumptions!$B$191) | ... BJ91: =BJ15*Assumptions!$B$230*BJ83*(1+Assumptions!$B$191)
A92: Product manager | B92: R | C92: =C16*Assumptions!$B$231*C83*(1+Assumptions!$B$191) | D92: =D16*Assumptions!$B$231*D83*(1+Assumptions!$B$191) | E92: =E16*Assumptions!$B$231*E83*(1+Assumptions!$B$191) | F92: =F16*Assumptions!$B$231*F83*(1+Assumptions!$B$191) | G92: =G16*Assumptions!$B$231*G83*(1+Assumptions!$B$191) | H92: =H16*Assumptions!$B$231*H83*(1+Assumptions!$B$191) | I92: =I16*Assumptions!$B$231*I83*(1+Assumptions!$B$191) | J92: =J16*Assumptions!$B$231*J83*(1+Assumptions!$B$191) | ... BJ92: =BJ16*Assumptions!$B$231*BJ83*(1+Assumptions!$B$191)
A93: Security & compliance engineer | B93: R | C93: =C17*Assumptions!$B$232*C83*(1+Assumptions!$B$191) | D93: =D17*Assumptions!$B$232*D83*(1+Assumptions!$B$191) | E93: =E17*Assumptions!$B$232*E83*(1+Assumptions!$B$191) | F93: =F17*Assumptions!$B$232*F83*(1+Assumptions!$B$191) | G93: =G17*Assumptions!$B$232*G83*(1+Assumptions!$B$191) | H93: =H17*Assumptions!$B$232*H83*(1+Assumptions!$B$191) | I93: =I17*Assumptions!$B$232*I83*(1+Assumptions!$B$191) | J93: =J17*Assumptions!$B$232*J83*(1+Assumptions!$B$191) | ... BJ93: =BJ17*Assumptions!$B$232*BJ83*(1+Assumptions!$B$191)
A94: Payments & data engineers | B94: R | C94: =C18*Assumptions!$B$233*C83*(1+Assumptions!$B$191) | D94: =D18*Assumptions!$B$233*D83*(1+Assumptions!$B$191) | E94: =E18*Assumptions!$B$233*E83*(1+Assumptions!$B$191) | F94: =F18*Assumptions!$B$233*F83*(1+Assumptions!$B$191) | G94: =G18*Assumptions!$B$233*G83*(1+Assumptions!$B$191) | H94: =H18*Assumptions!$B$233*H83*(1+Assumptions!$B$191) | I94: =I18*Assumptions!$B$233*I83*(1+Assumptions!$B$191) | J94: =J18*Assumptions!$B$233*J83*(1+Assumptions!$B$191) | ... BJ94: =BJ18*Assumptions!$B$233*BJ83*(1+Assumptions!$B$191)
A95: Engineers (scale-up I) | B95: R | C95: =C19*Assumptions!$B$234*C83*(1+Assumptions!$B$191) | D95: =D19*Assumptions!$B$234*D83*(1+Assumptions!$B$191) | E95: =E19*Assumptions!$B$234*E83*(1+Assumptions!$B$191) | F95: =F19*Assumptions!$B$234*F83*(1+Assumptions!$B$191) | G95: =G19*Assumptions!$B$234*G83*(1+Assumptions!$B$191) | H95: =H19*Assumptions!$B$234*H83*(1+Assumptions!$B$191) | I95: =I19*Assumptions!$B$234*I83*(1+Assumptions!$B$191) | J95: =J19*Assumptions!$B$234*J83*(1+Assumptions!$B$191) | ... BJ95: =BJ19*Assumptions!$B$234*BJ83*(1+Assumptions!$B$191)
A96: VP Engineering | B96: R | C96: =C20*Assumptions!$B$235*C83*(1+Assumptions!$B$191) | D96: =D20*Assumptions!$B$235*D83*(1+Assumptions!$B$191) | E96: =E20*Assumptions!$B$235*E83*(1+Assumptions!$B$191) | F96: =F20*Assumptions!$B$235*F83*(1+Assumptions!$B$191) | G96: =G20*Assumptions!$B$235*G83*(1+Assumptions!$B$191) | H96: =H20*Assumptions!$B$235*H83*(1+Assumptions!$B$191) | I96: =I20*Assumptions!$B$235*I83*(1+Assumptions!$B$191) | J96: =J20*Assumptions!$B$235*J83*(1+Assumptions!$B$191) | ... BJ96: =BJ20*Assumptions!$B$235*BJ83*(1+Assumptions!$B$191)
A97: Product manager #2 | B97: R | C97: =C21*Assumptions!$B$236*C83*(1+Assumptions!$B$191) | D97: =D21*Assumptions!$B$236*D83*(1+Assumptions!$B$191) | E97: =E21*Assumptions!$B$236*E83*(1+Assumptions!$B$191) | F97: =F21*Assumptions!$B$236*F83*(1+Assumptions!$B$191) | G97: =G21*Assumptions!$B$236*G83*(1+Assumptions!$B$191) | H97: =H21*Assumptions!$B$236*H83*(1+Assumptions!$B$191) | I97: =I21*Assumptions!$B$236*I83*(1+Assumptions!$B$191) | J97: =J21*Assumptions!$B$236*J83*(1+Assumptions!$B$191) | ... BJ97: =BJ21*Assumptions!$B$236*BJ83*(1+Assumptions!$B$191)
A98: Engineers (scale-up II) | B98: R | C98: =C22*Assumptions!$B$237*C83*(1+Assumptions!$B$191) | D98: =D22*Assumptions!$B$237*D83*(1+Assumptions!$B$191) | E98: =E22*Assumptions!$B$237*E83*(1+Assumptions!$B$191) | F98: =F22*Assumptions!$B$237*F83*(1+Assumptions!$B$191) | G98: =G22*Assumptions!$B$237*G83*(1+Assumptions!$B$191) | H98: =H22*Assumptions!$B$237*H83*(1+Assumptions!$B$191) | I98: =I22*Assumptions!$B$237*I83*(1+Assumptions!$B$191) | J98: =J22*Assumptions!$B$237*J83*(1+Assumptions!$B$191) | ... BJ98: =BJ22*Assumptions!$B$237*BJ83*(1+Assumptions!$B$191)
A99: Data / AI engineers | B99: R | C99: =C23*Assumptions!$B$238*C83*(1+Assumptions!$B$191) | D99: =D23*Assumptions!$B$238*D83*(1+Assumptions!$B$191) | E99: =E23*Assumptions!$B$238*E83*(1+Assumptions!$B$191) | F99: =F23*Assumptions!$B$238*F83*(1+Assumptions!$B$191) | G99: =G23*Assumptions!$B$238*G83*(1+Assumptions!$B$191) | H99: =H23*Assumptions!$B$238*H83*(1+Assumptions!$B$191) | I99: =I23*Assumptions!$B$238*I83*(1+Assumptions!$B$191) | J99: =J23*Assumptions!$B$238*J83*(1+Assumptions!$B$191) | ... BJ99: =BJ23*Assumptions!$B$238*BJ83*(1+Assumptions!$B$191)
A100: Engineers (scale-up III) | B100: R | C100: =C24*Assumptions!$B$239*C83*(1+Assumptions!$B$191) | D100: =D24*Assumptions!$B$239*D83*(1+Assumptions!$B$191) | E100: =E24*Assumptions!$B$239*E83*(1+Assumptions!$B$191) | F100: =F24*Assumptions!$B$239*F83*(1+Assumptions!$B$191) | G100: =G24*Assumptions!$B$239*G83*(1+Assumptions!$B$191) | H100: =H24*Assumptions!$B$239*H83*(1+Assumptions!$B$191) | I100: =I24*Assumptions!$B$239*I83*(1+Assumptions!$B$191) | J100: =J24*Assumptions!$B$239*J83*(1+Assumptions!$B$191) | ... BJ100: =BJ24*Assumptions!$B$239*BJ83*(1+Assumptions!$B$191)
A101: Engineers (scale-up IV: social adapters & integrations at scale) | B101: R | C101: =C25*Assumptions!$B$240*C83*(1+Assumptions!$B$191) | D101: =D25*Assumptions!$B$240*D83*(1+Assumptions!$B$191) | E101: =E25*Assumptions!$B$240*E83*(1+Assumptions!$B$191) | F101: =F25*Assumptions!$B$240*F83*(1+Assumptions!$B$191) | G101: =G25*Assumptions!$B$240*G83*(1+Assumptions!$B$191) | H101: =H25*Assumptions!$B$240*H83*(1+Assumptions!$B$191) | I101: =I25*Assumptions!$B$240*I83*(1+Assumptions!$B$191) | J101: =J25*Assumptions!$B$240*J83*(1+Assumptions!$B$191) | ... BJ101: =BJ25*Assumptions!$B$240*BJ83*(1+Assumptions!$B$191)
A102: Data & AI team II | B102: R | C102: =C26*Assumptions!$B$241*C83*(1+Assumptions!$B$191) | D102: =D26*Assumptions!$B$241*D83*(1+Assumptions!$B$191) | E102: =E26*Assumptions!$B$241*E83*(1+Assumptions!$B$191) | F102: =F26*Assumptions!$B$241*F83*(1+Assumptions!$B$191) | G102: =G26*Assumptions!$B$241*G83*(1+Assumptions!$B$191) | H102: =H26*Assumptions!$B$241*H83*(1+Assumptions!$B$191) | I102: =I26*Assumptions!$B$241*I83*(1+Assumptions!$B$191) | J102: =J26*Assumptions!$B$241*J83*(1+Assumptions!$B$191) | ... BJ102: =BJ26*Assumptions!$B$241*BJ83*(1+Assumptions!$B$191)
A103: Head of Growth | B103: R | C103: =C27*Assumptions!$B$242*C83*(1+Assumptions!$B$191) | D103: =D27*Assumptions!$B$242*D83*(1+Assumptions!$B$191) | E103: =E27*Assumptions!$B$242*E83*(1+Assumptions!$B$191) | F103: =F27*Assumptions!$B$242*F83*(1+Assumptions!$B$191) | G103: =G27*Assumptions!$B$242*G83*(1+Assumptions!$B$191) | H103: =H27*Assumptions!$B$242*H83*(1+Assumptions!$B$191) | I103: =I27*Assumptions!$B$242*I83*(1+Assumptions!$B$191) | J103: =J27*Assumptions!$B$242*J83*(1+Assumptions!$B$191) | ... BJ103: =BJ27*Assumptions!$B$242*BJ83*(1+Assumptions!$B$191)
...

Sheet P&L
A1: P&L
A2: Monthly profit and loss (ZAR). EBITDA excludes D&A (immaterial: equipment is expensed).
A3: Month # | B3: Unit | C3: 1 | D3: 2 | E3: 3 | F3: 4 | G3: 5 | H3: 6 | I3: 7 | J3: 8 | K3: 9 | L3: 10 | M3: 11 | N3: 12 | O3: 13 | P3: 14 | Q3: 15 | R3: 16 | S3: 17 | T3: 18 | U3: 19 | V3: 20 | W3: 21 | X3: 22 | Y3: 23 | Z3: 24 | AA3: 25 | AB3: 26 | AC3: 27 | AD3: 28 | AE3: 29 | AF3: 30 | AG3: 31 | AH3: 32 | AI3: 33 | AJ3: 34 | AK3: 35 | AL3: 36 | AM3: 37 | AN3: 38 | AO3: 39 | AP3: 40 | AQ3: 41 | AR3: 42 | AS3: 43 | AT3: 44 | AU3: 45 | AV3: 46 | AW3: 47 | AX3: 48 | AY3: 49 | AZ3: 50 | BA3: 51 | BB3: 52 | BC3: 53 | BD3: 54 | BE3: 55 | BF3: 56 | BG3: 57 | BH3: 58 | BI3: 59 | BJ3: 60
A4: Month | C4: Oct 2026 | D4: Nov 2026 | E4: Dec 2026 | F4: Jan 2027 | G4: Feb 2027 | H4: Mar 2027 | I4: Apr 2027 | J4: May 2027 | K4: Jun 2027 | L4: Jul 2027 | M4: Aug 2027 | N4: Sep 2027 | O4: Oct 2027 | P4: Nov 2027 | Q4: Dec 2027 | R4: Jan 2028 | S4: Feb 2028 | T4: Mar 2028 | U4: Apr 2028 | V4: May 2028 | W4: Jun 2028 | X4: Jul 2028 | Y4: Aug 2028 | Z4: Sep 2028 | AA4: Oct 2028 | AB4: Nov 2028 | AC4: Dec 2028 | AD4: Jan 2029 | AE4: Feb 2029 | AF4: Mar 2029 | AG4: Apr 2029 | AH4: May 2029 | AI4: Jun 2029 | AJ4: Jul 2029 | AK4: Aug 2029 | AL4: Sep 2029 | AM4: Oct 2029 | AN4: Nov 2029 | AO4: Dec 2029 | AP4: Jan 2030 | AQ4: Feb 2030 | AR4: Mar 2030 | AS4: Apr 2030 | AT4: May 2030 | AU4: Jun 2030 | AV4: Jul 2030 | AW4: Aug 2030 | AX4: Sep 2030 | AY4: Oct 2030 | AZ4: Nov 2030 | BA4: Dec 2030 | BB4: Jan 2031 | BC4: Feb 2031 | BD4: Mar 2031 | BE4: Apr 2031 | BF4: May 2031 | BG4: Jun 2031 | BH4: Jul 2031 | BI4: Aug 2031 | BJ4: Sep 2031
A5: Fiscal year (Oct-Sep) | C5: 1 | D5: 1 | E5: 1 | F5: 1 | G5: 1 | H5: 1 | I5: 1 | J5: 1 | K5: 1 | L5: 1 | M5: 1 | N5: 1 | O5: 2 | P5: 2 | Q5: 2 | R5: 2 | S5: 2 | T5: 2 | U5: 2 | V5: 2 | W5: 2 | X5: 2 | Y5: 2 | Z5: 2 | AA5: 3 | AB5: 3 | AC5: 3 | AD5: 3 | AE5: 3 | AF5: 3 | AG5: 3 | AH5: 3 | AI5: 3 | AJ5: 3 | AK5: 3 | AL5: 3 | AM5: 4 | AN5: 4 | AO5: 4 | AP5: 4 | AQ5: 4 | AR5: 4 | AS5: 4 | AT5: 4 | AU5: 4 | AV5: 4 | AW5: 4 | AX5: 4 | AY5: 5 | AZ5: 5 | BA5: 5 | BB5: 5 | BC5: 5 | BD5: 5 | BE5: 5 | BF5: 5 | BG5: 5 | BH5: 5 | BI5: 5 | BJ5: 5
A7: Revenue: gross subscriptions -> launch discounts -> net
A8: Subscriptions (gross, at list / parity prices) | B8: R | C8: =Revenue_Build!C479 | D8: =Revenue_Build!D479 | E8: =Revenue_Build!E479 | F8: =Revenue_Build!F479 | G8: =Revenue_Build!G479 | H8: =Revenue_Build!H479 | I8: =Revenue_Build!I479 | J8: =Revenue_Build!J479 | ... BJ8: =Revenue_Build!BJ479
A9: less: Founding Member launch discount | B9: R | C9: =-Revenue_Build!C484 | D9: =-Revenue_Build!D484 | E9: =-Revenue_Build!E484 | F9: =-Revenue_Build!F484 | G9: =-Revenue_Build!G484 | H9: =-Revenue_Build!H484 | I9: =-Revenue_Build!I484 | J9: =-Revenue_Build!J484 | ... BJ9: =-Revenue_Build!BJ484
A10: Subscriptions (net) | B10: R | C10: =C8+C9 | D10: =D8+D9 | E10: =E8+E9 | F10: =F8+F9 | G10: =G8+G9 | H10: =H8+H9 | I10: =I8+I9 | J10: =J8+J9 | ... BJ10: =BJ8+BJ9
A11: AI-credit packs | B11: R | C11: =Revenue_Build!C496 | D11: =Revenue_Build!D496 | E11: =Revenue_Build!E496 | F11: =Revenue_Build!F496 | G11: =Revenue_Build!G496 | H11: =Revenue_Build!H496 | I11: =Revenue_Build!I496 | J11: =Revenue_Build!J496 | ... BJ11: =Revenue_Build!BJ496
A12: WhatsApp messaging (pass-through + margin) | B12: R | C12: =Revenue_Build!C498 | D12: =Revenue_Build!D498 | E12: =Revenue_Build!E498 | F12: =Revenue_Build!F498 | G12: =Revenue_Build!G498 | H12: =Revenue_Build!H498 | I12: =Revenue_Build!I498 | J12: =Revenue_Build!J498 | ... BJ12: =Revenue_Build!BJ498
A13: FluxMuse checkout fee (0%: pass-through only) | B13: R | C13: =Revenue_Build!C501 | D13: =Revenue_Build!D501 | E13: =Revenue_Build!E501 | F13: =Revenue_Build!F501 | G13: =Revenue_Build!G501 | H13: =Revenue_Build!H501 | I13: =Revenue_Build!I501 | J13: =Revenue_Build!J501 | ... BJ13: =Revenue_Build!BJ501
A14: Custom (Enterprise) setup fees | B14: R | C14: =Revenue_Build!C502 | D14: =Revenue_Build!D502 | E14: =Revenue_Build!E502 | F14: =Revenue_Build!F502 | G14: =Revenue_Build!G502 | H14: =Revenue_Build!H502 | I14: =Revenue_Build!I502 | J14: =Revenue_Build!J502 | ... BJ14: =Revenue_Build!BJ502
A15: Agency white-label setup fees | B15: R | C15: =Revenue_Build!C503 | D15: =Revenue_Build!D503 | E15: =Revenue_Build!E503 | F15: =Revenue_Build!F503 | G15: =Revenue_Build!G503 | H15: =Revenue_Build!H503 | I15: =Revenue_Build!I503 | J15: =Revenue_Build!J503 | ... BJ15: =Revenue_Build!BJ503
A16: Total revenue | B16: R | C16: =C10+C11+C12+C13+C14+C15 | D16: =D10+D11+D12+D13+D14+D15 | E16: =E10+E11+E12+E13+E14+E15 | F16: =F10+F11+F12+F13+F14+F15 | G16: =G10+G11+G12+G13+G14+G15 | H16: =H10+H11+H12+H13+H14+H15 | I16: =I10+I11+I12+I13+I14+I15 | J16: =J10+J11+J12+J13+J14+J15 | ... BJ16: =BJ10+BJ11+BJ12+BJ13+BJ14+BJ15
A18: Cost of revenue
A19: AI provider cost (incl. Free plan) | B19: R | C19: =Costs!C160 | D19: =Costs!D160 | E19: =Costs!E160 | F19: =Costs!F160 | G19: =Costs!G160 | H19: =Costs!H160 | I19: =Costs!I160 | J19: =Costs!J160 | ... BJ19: =Costs!BJ160
A20: Hosting | B20: R | C20: =Costs!C161 | D20: =Costs!D161 | E20: =Costs!E161 | F20: =Costs!F161 | G20: =Costs!G161 | H20: =Costs!H161 | I20: =Costs!I161 | J20: =Costs!J161 | ... BJ20: =Costs!BJ161
A21: WhatsApp Meta fees | B21: R | C21: =Costs!C162 | D21: =Costs!D162 | E21: =Costs!E162 | F21: =Costs!F162 | G21: =Costs!G162 | H21: =Costs!H162 | I21: =Costs!I162 | J21: =Costs!J162 | ... BJ21: =Costs!BJ162
A22: Payment processing | B22: R | C22: =Costs!C165 | D22: =Costs!D165 | E22: =Costs!E165 | F22: =Costs!F165 | G22: =Costs!G165 | H22: =Costs!H165 | I22: =Costs!I165 | J22: =Costs!J165 | ... BJ22: =Costs!BJ165
A23: Variable support | B23: R | C23: =Costs!C166 | D23: =Costs!D166 | E23: =Costs!E166 | F23: =Costs!F166 | G23: =Costs!G166 | H23: =Costs!H166 | I23: =Costs!I166 | J23: =Costs!J166 | ... BJ23: =Costs!BJ166
A24: Customer success team | B24: R | C24: =Costs!C167 | D24: =Costs!D167 | E24: =Costs!E167 | F24: =Costs!F167 | G24: =Costs!G167 | H24: =Costs!H167 | I24: =Costs!I167 | J24: =Costs!J167 | ... BJ24: =Costs!BJ167
A25: Total cost of revenue | B25: R | C25: =C19+C20+C21+C22+C23+C24 | D25: =D19+D20+D21+D22+D23+D24 | E25: =E19+E20+E21+E22+E23+E24 | F25: =F19+F20+F21+F22+F23+F24 | G25: =G19+G20+G21+G22+G23+G24 | H25: =H19+H20+H21+H22+H23+H24 | I25: =I19+I20+I21+I22+I23+I24 | J25: =J19+J20+J21+J22+J23+J24 | ... BJ25: =BJ19+BJ20+BJ21+BJ22+BJ23+BJ24
A26: Gross profit | B26: R | C26: =C16-C25 | D26: =D16-D25 | E26: =E16-E25 | F26: =F16-F25 | G26: =G16-G25 | H26: =H16-H25 | I26: =I16-I25 | J26: =J16-J25 | ... BJ26: =BJ16-BJ25
A27: Gross margin % | B27: % | C27: =IF(C16=0,0,C26/C16) | D27: =IF(D16=0,0,D26/D16) | E27: =IF(E16=0,0,E26/E16) | F27: =IF(F16=0,0,F26/F16) | G27: =IF(G16=0,0,G26/G16) | H27: =IF(H16=0,0,H26/H16) | I27: =IF(I16=0,0,I26/I16) | J27: =IF(J16=0,0,J26/J16) | ... BJ27: =IF(BJ16=0,0,BJ26/BJ16)
A29: Operating expenses
A30: Payroll: Leadership | B30: R | C30: =Costs!C144 | D30: =Costs!D144 | E30: =Costs!E144 | F30: =Costs!F144 | G30: =Costs!G144 | H30: =Costs!H144 | I30: =Costs!I144 | J30: =Costs!J144 | ... BJ30: =Costs!BJ144
A31: Payroll: Engineering & product | B31: R | C31: =Costs!C145 | D31: =Costs!D145 | E31: =Costs!E145 | F31: =Costs!F145 | G31: =Costs!G145 | H31: =Costs!H145 | I31: =Costs!I145 | J31: =Costs!J145 | ... BJ31: =Costs!BJ145
A32: Payroll: Marketing | B32: R | C32: =Costs!C146 | D32: =Costs!D146 | E32: =Costs!E146 | F32: =Costs!F146 | G32: =Costs!G146 | H32: =Costs!H146 | I32: =Costs!I146 | J32: =Costs!J146 | ... BJ32: =Costs!BJ146
A33: Payroll: Sales & partnerships | B33: R | C33: =Costs!C147 | D33: =Costs!D147 | E33: =Costs!E147 | F33: =Costs!F147 | G33: =Costs!G147 | H33: =Costs!H147 | I33: =Costs!I147 | J33: =Costs!J147 | ... BJ33: =Costs!BJ147
A34: Payroll: G&A & compliance | B34: R | C34: =Costs!C149 | D34: =Costs!D149 | E34: =Costs!E149 | F34: =Costs!F149 | G34: =Costs!G149 | H34: =Costs!H149 | I34: =Costs!I149 | J34: =Costs!J149 | ... BJ34: =Costs!BJ149
A35: Payroll: Country teams | B35: R | C35: =Costs!C150 | D35: =Costs!D150 | E35: =Costs!E150 | F35: =Costs!F150 | G35: =Costs!G150 | H35: =Costs!H150 | I35: =Costs!I150 | J35: =Costs!J150 | ... BJ35: =Costs!BJ150
A36: Total payroll (excl. customer success in COGS) | B36: R | C36: =C30+C31+C32+C33+C34+C35 | D36: =D30+D31+D32+D33+D34+D35 | E36: =E30+E31+E32+E33+E34+E35 | F36: =F30+F31+F32+F33+F34+F35 | G36: =G30+G31+G32+G33+G34+G35 | H36: =H30+H31+H32+H33+H34+H35 | I36: =I30+I31+I32+I33+I34+I35 | J36: =J30+J31+J32+J33+J34+J35 | ... BJ36: =BJ30+BJ31+BJ32+BJ33+BJ34+BJ35
A37: Marketing & sales programmes | B37: R | C37: =Costs!C179 | D37: =Costs!D179 | E37: =Costs!E179 | F37: =Costs!F179 | G37: =Costs!G179 | H37: =Costs!H179 | I37: =Costs!I179 | J37: =Costs!J179 | ... BJ37: =Costs!BJ179
A38: G&A (non-payroll) | B38: R | C38: =Costs!C185 | D38: =Costs!D185 | E38: =Costs!E185 | F38: =Costs!F185 | G38: =Costs!G185 | H38: =Costs!H185 | I38: =Costs!I185 | J38: =Costs!J185 | ... BJ38: =Costs!BJ185
A39: Meta, legal & compliance | B39: R | C39: =Costs!C186 | D39: =Costs!D186 | E39: =Costs!E186 | F39: =Costs!F186 | G39: =Costs!G186 | H39: =Costs!H186 | I39: =Costs!I186 | J39: =Costs!J186 | ... BJ39: =Costs!BJ186
A40: Software & tools | B40: R | C40: =Costs!C187 | D40: =Costs!D187 | E40: =Costs!E187 | F40: =Costs!F187 | G40: =Costs!G187 | H40: =Costs!H187 | I40: =Costs!I187 | J40: =Costs!J187 | ... BJ40: =Costs!BJ187
A41: Travel | B41: R | C41: =Costs!C188 | D41: =Costs!D188 | E41: =Costs!E188 | F41: =Costs!F188 | G41: =Costs!G188 | H41: =Costs!H188 | I41: =Costs!I188 | J41: =Costs!J188 | ... BJ41: =Costs!BJ188
A42: Total operating expenses | B42: R | C42: =C36+C37+C38+C39+C40+C41 | D42: =D36+D37+D38+D39+D40+D41 | E42: =E36+E37+E38+E39+E40+E41 | F42: =F36+F37+F38+F39+F40+F41 | G42: =G36+G37+G38+G39+G40+G41 | H42: =H36+H37+H38+H39+H40+H41 | I42: =I36+I37+I38+I39+I40+I41 | J42: =J36+J37+J38+J39+J40+J41 | ... BJ42: =BJ36+BJ37+BJ38+BJ39+BJ40+BJ41
A44: Profit
A45: EBITDA | B45: R | C45: =C26-C42 | D45: =D26-D42 | E45: =E26-E42 | F45: =F26-F42 | G45: =G26-G42 | H45: =H26-H42 | I45: =I26-I42 | J45: =J26-J42 | ... BJ45: =BJ26-BJ42
A46: EBITDA margin % | B46: % | C46: =IF(C16=0,0,C45/C16) | D46: =IF(D16=0,0,D45/D16) | E46: =IF(E16=0,0,E45/E16) | F46: =IF(F16=0,0,F45/F16) | G46: =IF(G16=0,0,G45/G16) | H46: =IF(H16=0,0,H45/H16) | I46: =IF(I16=0,0,I45/I16) | J46: =IF(J16=0,0,J45/J16) | ... BJ46: =IF(BJ16=0,0,BJ45/BJ16)
A47: Cumulative EBITDA (assessed-loss tracker; D&A and interest ignored) | B47: R | C47: =C45 | D47: =C47+D45 | E47: =D47+E45 | F47: =E47+F45 | G47: =F47+G45 | H47: =G47+H45 | I47: =H47+I45 | J47: =I47+J45 | K47: =J47+K45 | ... BJ47: =BI47+BJ45
A48: Income tax (27% once cumulatively profitable) | B48: R | C48: =Assumptions!$B$11*MAX(0,C47) | D48: =Assumptions!$B$11*(MAX(0,D47)-MAX(0,C47)) | E48: =Assumptions!$B$11*(MAX(0,E47)-MAX(0,D47)) | F48: =Assumptions!$B$11*(MAX(0,F47)-MAX(0,E47)) | G48: =Assumptions!$B$11*(MAX(0,G47)-MAX(0,F47)) | H48: =Assumptions!$B$11*(MAX(0,H47)-MAX(0,G47)) | I48: =Assumptions!$B$11*(MAX(0,I47)-MAX(0,H47)) | J48: =Assumptions!$B$11*(MAX(0,J47)-MAX(0,I47)) | K48: =Assumptions!$B$11*(MAX(0,K47)-MAX(0,J47)) | ... BJ48: =Assumptions!$B$11*(MAX(0,BJ47)-MAX(0,BI47))
A49: Net income | B49: R | C49: =C45-C48 | D49: =D45-D48 | E49: =E45-E48 | F49: =F45-F48 | G49: =G45-G48 | H49: =H45-H48 | I49: =I45-I48 | J49: =J45-J48 | ... BJ49: =BJ45-BJ48
A51: Memo: software gross margin (net subscriptions, top-ups, setup fees; excl. WhatsApp pass-through & commerce)
A52: Software revenue | B52: R | C52: =C10+C11+C14+C15 | D52: =D10+D11+D14+D15 | E52: =E10+E11+E14+E15 | F52: =F10+F11+F14+F15 | G52: =G10+G11+G14+G15 | H52: =H10+H11+H14+H15 | I52: =I10+I11+I14+I15 | J52: =J10+J11+J14+J15 | ... BJ52: =BJ10+BJ11+BJ14+BJ15
A53: Software COGS | B53: R | C53: =C19+C20+C23+C24+C52*Costs!C164 | D53: =D19+D20+D23+D24+D52*Costs!D164 | E53: =E19+E20+E23+E24+E52*Costs!E164 | F53: =F19+F20+F23+F24+F52*Costs!F164 | G53: =G19+G20+G23+G24+G52*Costs!G164 | H53: =H19+H20+H23+H24+H52*Costs!H164 | I53: =I19+I20+I23+I24+I52*Costs!I164 | J53: =J19+J20+J23+J24+J52*Costs!J164 | ... BJ53: =BJ19+BJ20+BJ23+BJ24+BJ52*Costs!BJ164
A54: Software gross margin % | B54: % | C54: =IF(C52=0,0,1-C53/C52) | D54: =IF(D52=0,0,1-D53/D52) | E54: =IF(E52=0,0,1-E53/E52) | F54: =IF(F52=0,0,1-F53/F52) | G54: =IF(G52=0,0,1-G53/G52) | H54: =IF(H52=0,0,1-H53/H52) | I54: =IF(I52=0,0,1-I53/I52) | J54: =IF(J52=0,0,1-J53/J52) | ... BJ54: =IF(BJ52=0,0,1-BJ53/BJ52)
A55: Sales & marketing total (programmes + marketing & sales payroll) | B55: R | C55: =C37+C32+C33 | D55: =D37+D32+D33 | E55: =E37+E32+E33 | F55: =F37+F32+F33 | G55: =G37+G32+G33 | H55: =H37+H32+H33 | I55: =I37+I32+I33 | J55: =J37+J32+J33 | ... BJ55: =BJ37+BJ32+BJ33

Sheet Annual_Summary
A1: Annual Summary
A2: FY1-FY5 (Oct-Sep) roll-up of the monthly model, selected scenario.
A4: R unless stated | B4: Unit | C4: FY1 | D4: FY2 | E4: FY3 | F4: FY4 | G4: FY5
C5: Oct 2026 - Sep 2027 | D5: Oct 2027 - Sep 2028 | E5: Oct 2028 - Sep 2029 | F5: Oct 2029 - Sep 2030 | G5: Oct 2030 - Sep 2031
A7: Revenue by stream (gross subscriptions -> launch discounts -> net)
A8: Subscriptions (gross) | B8: R | C8: =SUM('P&L'!C8:N8) | D8: =SUM('P&L'!O8:Z8) | E8: =SUM('P&L'!AA8:AL8) | F8: =SUM('P&L'!AM8:AX8) | G8: =SUM('P&L'!AY8:BJ8)
A9: less: Founding Member discount | B9: R | C9: =SUM('P&L'!C9:N9) | D9: =SUM('P&L'!O9:Z9) | E9: =SUM('P&L'!AA9:AL9) | F9: =SUM('P&L'!AM9:AX9) | G9: =SUM('P&L'!AY9:BJ9)
A10: Subscriptions (net) | B10: R | C10: =C8+C9 | D10: =D8+D9 | E10: =E8+E9 | F10: =F8+F9 | G10: =G8+G9
A11: AI-credit packs | B11: R | C11: =SUM('P&L'!C11:N11) | D11: =SUM('P&L'!O11:Z11) | E11: =SUM('P&L'!AA11:AL11) | F11: =SUM('P&L'!AM11:AX11) | G11: =SUM('P&L'!AY11:BJ11)
A12: WhatsApp messaging (pass-through + margin) | B12: R | C12: =SUM('P&L'!C12:N12) | D12: =SUM('P&L'!O12:Z12) | E12: =SUM('P&L'!AA12:AL12) | F12: =SUM('P&L'!AM12:AX12) | G12: =SUM('P&L'!AY12:BJ12)
A13: FluxMuse checkout fee (0%: pass-through only) | B13: R | C13: =SUM('P&L'!C13:N13) | D13: =SUM('P&L'!O13:Z13) | E13: =SUM('P&L'!AA13:AL13) | F13: =SUM('P&L'!AM13:AX13) | G13: =SUM('P&L'!AY13:BJ13)
A14: Custom (Enterprise) setup fees | B14: R | C14: =SUM('P&L'!C14:N14) | D14: =SUM('P&L'!O14:Z14) | E14: =SUM('P&L'!AA14:AL14) | F14: =SUM('P&L'!AM14:AX14) | G14: =SUM('P&L'!AY14:BJ14)
A15: Agency white-label setup fees | B15: R | C15: =SUM('P&L'!C15:N15) | D15: =SUM('P&L'!O15:Z15) | E15: =SUM('P&L'!AA15:AL15) | F15: =SUM('P&L'!AM15:AX15) | G15: =SUM('P&L'!AY15:BJ15)
A16: Total revenue | B16: R | C16: =C10+C11+C12+C13+C14+C15 | D16: =D10+D11+D12+D13+D14+D15 | E16: =E10+E11+E12+E13+E14+E15 | F16: =F10+F11+F12+F13+F14+F15 | G16: =G10+G11+G12+G13+G14+G15
A17: Total revenue (US$) | B17: US$ | C17: =C16/Assumptions!$B$10 | D17: =D16/Assumptions!$B$10 | E17: =E16/Assumptions!$B$10 | F17: =F16/Assumptions!$B$10 | G17: =G16/Assumptions!$B$10
A18: Revenue growth y/y | B18: % | C18: ="n/a" | D18: =IF(C16=0,0,(D16-C16)/C16) | E18: =IF(D16=0,0,(E16-D16)/D16) | F18: =IF(E16=0,0,(F16-E16)/E16) | G18: =IF(F16=0,0,(G16-F16)/F16)
A20: Launch discounts (cost of the offer, positive = revenue given up)
A21: Founding Member discount cost | B21: R | C21: =SUM(Revenue_Build!C484:N484) | D21: =SUM(Revenue_Build!O484:Z484) | E21: =SUM(Revenue_Build!AA484:AL484) | F21: =SUM(Revenue_Build!AM484:AX484) | G21: =SUM(Revenue_Build!AY484:BJ484)
A22: of which South Africa | B22: R | C22: =SUM(Revenue_Build!C483:N483) | D22: =SUM(Revenue_Build!O483:Z483) | E22: =SUM(Revenue_Build!AA483:AL483) | F22: =SUM(Revenue_Build!AM483:AX483) | G22: =SUM(Revenue_Build!AY483:BJ483)
A23: Launch discounts as % of gross subscriptions | B23: % | C23: =IF(C8=0,0,C21/C8) | D23: =IF(D8=0,0,D21/D8) | E23: =IF(E8=0,0,E21/E8) | F23: =IF(F8=0,0,F21/F8) | G23: =IF(G8=0,0,G21/G8)
A25: Net subscription revenue by market
A26: South Africa | B26: R | C26: =SUM(Revenue_Build!C487:N487) | D26: =SUM(Revenue_Build!O487:Z487) | E26: =SUM(Revenue_Build!AA487:AL487) | F26: =SUM(Revenue_Build!AM487:AX487) | G26: =SUM(Revenue_Build!AY487:BJ487)
A27: Nigeria | B27: R | C27: =SUM(Revenue_Build!C488:N488) | D27: =SUM(Revenue_Build!O488:Z488) | E27: =SUM(Revenue_Build!AA488:AL488) | F27: =SUM(Revenue_Build!AM488:AX488) | G27: =SUM(Revenue_Build!AY488:BJ488)
A28: Kenya | B28: R | C28: =SUM(Revenue_Build!C489:N489) | D28: =SUM(Revenue_Build!O489:Z489) | E28: =SUM(Revenue_Build!AA489:AL489) | F28: =SUM(Revenue_Build!AM489:AX489) | G28: =SUM(Revenue_Build!AY489:BJ489)
A29: Ghana | B29: R | C29: =SUM(Revenue_Build!C490:N490) | D29: =SUM(Revenue_Build!O490:Z490) | E29: =SUM(Revenue_Build!AA490:AL490) | F29: =SUM(Revenue_Build!AM490:AX490) | G29: =SUM(Revenue_Build!AY490:BJ490)
A30: Rest of Africa (USD) | B30: R | C30: =SUM(Revenue_Build!C491:N491) | D30: =SUM(Revenue_Build!O491:Z491) | E30: =SUM(Revenue_Build!AA491:AL491) | F30: =SUM(Revenue_Build!AM491:AX491) | G30: =SUM(Revenue_Build!AY491:BJ491)
A31: Botswana & Namibia | B31: R | C31: =SUM(Revenue_Build!C492:N492) | D31: =SUM(Revenue_Build!O492:Z492) | E31: =SUM(Revenue_Build!AA492:AL492) | F31: =SUM(Revenue_Build!AM492:AX492) | G31: =SUM(Revenue_Build!AY492:BJ492)
A33: Gross profit
A34: Cost of revenue | B34: R | C34: =SUM('P&L'!C25:N25) | D34: =SUM('P&L'!O25:Z25) | E34: =SUM('P&L'!AA25:AL25) | F34: =SUM('P&L'!AM25:AX25) | G34: =SUM('P&L'!AY25:BJ25)
A35: Gross profit | B35: R | C35: =C16-C34 | D35: =D16-D34 | E35: =E16-E34 | F35: =F16-F34 | G35: =G16-G34
A36: Gross margin % (all revenue) | B36: % | C36: =IF(C16=0,0,C35/C16) | D36: =IF(D16=0,0,D35/D16) | E36: =IF(E16=0,0,E35/E16) | F36: =IF(F16=0,0,F35/F16) | G36: =IF(G16=0,0,G35/G16)
A37: Software gross margin % | B37: % | C37: =IF(SUM('P&L'!C52:N52)=0,0,1-SUM('P&L'!C53:N53)/SUM('P&L'!C52:N52)) | D37: =IF(SUM('P&L'!O52:Z52)=0,0,1-SUM('P&L'!O53:Z53)/SUM('P&L'!O52:Z52)) | E37: =IF(SUM('P&L'!AA52:AL52)=0,0,1-SUM('P&L'!AA53:AL53)/SUM('P&L'!AA52:AL52)) | F37: =IF(SUM('P&L'!AM52:AX52)=0,0,1-SUM('P&L'!AM53:AX53)/SUM('P&L'!AM52:AX52)) | G37: =IF(SUM('P&L'!AY52:BJ52)=0,0,1-SUM('P&L'!AY53:BJ53)/SUM('P&L'!AY52:BJ52))
A39: Operating expenses by category
A40: Payroll (excl. customer success) | B40: R | C40: =SUM('P&L'!C36:N36) | D40: =SUM('P&L'!O36:Z36) | E40: =SUM('P&L'!AA36:AL36) | F40: =SUM('P&L'!AM36:AX36) | G40: =SUM('P&L'!AY36:BJ36)
A41: Marketing & sales programmes | B41: R | C41: =SUM('P&L'!C37:N37) | D41: =SUM('P&L'!O37:Z37) | E41: =SUM('P&L'!AA37:AL37) | F41: =SUM('P&L'!AM37:AX37) | G41: =SUM('P&L'!AY37:BJ37)
A42: G&A (non-payroll) | B42: R | C42: =SUM('P&L'!C38:N38) | D42: =SUM('P&L'!O38:Z38) | E42: =SUM('P&L'!AA38:AL38) | F42: =SUM('P&L'!AM38:AX38) | G42: =SUM('P&L'!AY38:BJ38)
A43: Meta, legal & compliance | B43: R | C43: =SUM('P&L'!C39:N39) | D43: =SUM('P&L'!O39:Z39) | E43: =SUM('P&L'!AA39:AL39) | F43: =SUM('P&L'!AM39:AX39) | G43: =SUM('P&L'!AY39:BJ39)
A44: Software & tools | B44: R | C44: =SUM('P&L'!C40:N40) | D44: =SUM('P&L'!O40:Z40) | E44: =SUM('P&L'!AA40:AL40) | F44: =SUM('P&L'!AM40:AX40) | G44: =SUM('P&L'!AY40:BJ40)
A45: Travel | B45: R | C45: =SUM('P&L'!C41:N41) | D45: =SUM('P&L'!O41:Z41) | E45: =SUM('P&L'!AA41:AL41) | F45: =SUM('P&L'!AM41:AX41) | G45: =SUM('P&L'!AY41:BJ41)
A46: Total operating expenses | B46: R | C46: =C40+C41+C42+C43+C44+C45 | D46: =D40+D41+D42+D43+D44+D45 | E46: =E40+E41+E42+E43+E44+E45 | F46: =F40+F41+F42+F43+F44+F45 | G46: =G40+G41+G42+G43+G44+G45
A47: memo: paid acquisition spend (after cap) | B47: R | C47: =SUM(Revenue_Build!C142:N142) | D47: =SUM(Revenue_Build!O142:Z142) | E47: =SUM(Revenue_Build!AA142:AL142) | F47: =SUM(Revenue_Build!AM142:AX142) | G47: =SUM(Revenue_Build!AY142:BJ142)
A48: memo: share of desired paid acquisition funded by the cap | B48: % | C48: =IF(SUM(Revenue_Build!C137:N137)=0,0,SUM(Revenue_Build!C142:N142)/SUM(Revenue_Build!C137:N137)) | D48: =IF(SUM(Revenue_Build!O137:Z137)=0,0,SUM(Revenue_Build!O142:Z142)/SUM(Revenue_Build!O137:Z137)) | E48: =IF(SUM(Revenue_Build!AA137:AL137)=0,0,SUM(Revenue_Build!AA142:AL142)/SUM(Revenue_Build!AA137:AL137)) | F48: =IF(SUM(Revenue_Build!AM137:AX137)=0,0,SUM(Revenue_Build!AM142:AX142)/SUM(Revenue_Build!AM137:AX137)) | G48: =IF(SUM(Revenue_Build!AY137:BJ137)=0,0,SUM(Revenue_Build!AY142:BJ142)/SUM(Revenue_Build!AY137:BJ137))
A50: Profit
A51: EBITDA | B51: R | C51: =C35-C46 | D51: =D35-D46 | E51: =E35-E46 | F51: =F35-F46 | G51: =G35-G46
A52: EBITDA margin % | B52: % | C52: =IF(C16=0,0,C51/C16) | D52: =IF(D16=0,0,D51/D16) | E52: =IF(E16=0,0,E51/E16) | F52: =IF(F16=0,0,F51/F16) | G52: =IF(G16=0,0,G51/G16)
A53: EBITDA (US$) | B53: US$ | C53: =C51/Assumptions!$B$10 | D53: =D51/Assumptions!$B$10 | E53: =E51/Assumptions!$B$10 | F53: =F51/Assumptions!$B$10 | G53: =G51/Assumptions!$B$10
A54: Income tax | B54: R | C54: =SUM('P&L'!C48:N48) | D54: =SUM('P&L'!O48:Z48) | E54: =SUM('P&L'!AA48:AL48) | F54: =SUM('P&L'!AM48:AX48) | G54: =SUM('P&L'!AY48:BJ48)
A55: Net income | B55: R | C55: =C51-C54 | D55: =D51-D54 | E55: =E51-E54 | F55: =F51-F54 | G55: =G51-G54
A57: Cash
A58: Operating cash flow (before funding) | B58: R | C58: =SUM(Cash_Flow!C14:N14) | D58: =SUM(Cash_Flow!O14:Z14) | E58: =SUM(Cash_Flow!AA14:AL14) | F58: =SUM(Cash_Flow!AM14:AX14) | G58: =SUM(Cash_Flow!AY14:BJ14)
A59: Equity funding received | B59: R | C59: =SUM(Cash_Flow!C17:N17)+SUM(Cash_Flow!C18:N18) | D59: =SUM(Cash_Flow!O17:Z17)+SUM(Cash_Flow!O18:Z18) | E59: =SUM(Cash_Flow!AA17:AL17)+SUM(Cash_Flow!AA18:AL18) | F59: =SUM(Cash_Flow!AM17:AX17)+SUM(Cash_Flow!AM18:AX18) | G59: =SUM(Cash_Flow!AY17:BJ17)+SUM(Cash_Flow!AY18:BJ18)
A60: Closing cash (end of FY) | B60: R | C60: =Cash_Flow!N23 | D60: =Cash_Flow!Z23 | E60: =Cash_Flow!AL23 | F60: =Cash_Flow!AX23 | G60: =Cash_Flow!BJ23
A61: Lowest month-end cash in FY | B61: R | C61: =MIN(Cash_Flow!C23:N23) | D61: =MIN(Cash_Flow!O23:Z23) | E61: =MIN(Cash_Flow!AA23:AL23) | F61: =MIN(Cash_Flow!AM23:AX23) | G61: =MIN(Cash_Flow!AY23:BJ23)
A63: Paying workspaces at end of FY: by segment
A64: Solo | B64: workspaces | C64: =Revenue_Build!N367 | D64: =Revenue_Build!Z367 | E64: =Revenue_Build!AL367 | F64: =Revenue_Build!AX367 | G64: =Revenue_Build!BJ367
A65: SMEs | B65: workspaces | C65: =Revenue_Build!N371 | D65: =Revenue_Build!Z371 | E65: =Revenue_Build!AL371 | F65: =Revenue_Build!AX371 | G65: =Revenue_Build!BJ371
A66: Agencies | B66: workspaces | C66: =Revenue_Build!N375 | D66: =Revenue_Build!Z375 | E66: =Revenue_Build!AL375 | F66: =Revenue_Build!AX375 | G66: =Revenue_Build!BJ375
A67: Corporate | B67: workspaces | C67: =Revenue_Build!N379 | D67: =Revenue_Build!Z379 | E67: =Revenue_Build!AL379 | F67: =Revenue_Build!AX379 | G67: =Revenue_Build!BJ379
A68: Enterprise | B68: workspaces | C68: =Revenue_Build!N383 | D68: =Revenue_Build!Z383 | E68: =Revenue_Build!AL383 | F68: =Revenue_Build!AX383 | G68: =Revenue_Build!BJ383
A70: Paying workspaces at end of FY: by market (gated countries = 0)
A71: South Africa | B71: workspaces | C71: =Revenue_Build!N360 | D71: =Revenue_Build!Z360 | E71: =Revenue_Build!AL360 | F71: =Revenue_Build!AX360 | G71: =Revenue_Build!BJ360
